Workbook
Name AccountrEquity: #REF!
Name IV: #REF!
Name ListCP: #REF!
Name MCK: #REF!

Sheet Tìm nhanh CP
A1: Cách sử dụng | F1: - Phân loại nhóm ngành, HĐKD của doanh nghiệp
F2: - Tìm cổ phiếu tăng trưởng trong quý hiện tại | I2: Chú ý: các DN phần LN ghi 0, LN% cùng kì 100%... Là các DN chưa ra báo cáo
F3: - Tìm nhanh 1CP bằng cách gõ tên vào ô bên dưới | I3: Và EPS cùng kì chỉ tính 3 quý thôi.
A4: 28/04/2026 | H4: Doanh thu | I4: ='Doanh thu'!H2 -> Q1.25 | J4: ='Doanh thu'!I2 -> Q2.25 | K4: ='Doanh thu'!J2 -> Q3.25 | L4: ='Doanh thu'!K2 -> Q4.25 | M4: ='Doanh thu'!L2 -> Q1.26
B5: NHẬP MÃ | H5: Giá trị | I5: =VLOOKUP($B$6,'Doanh thu'!$A$3:$L$2000,8,FALSE) -> 37621674553578 | J5: =VLOOKUP($B$6,'Doanh thu'!$A$3:$L$2000,9,FALSE) -> 35910519111209 | K5: =VLOOKUP($B$6,'Doanh thu'!$A$3:$L$2000,10,FALSE) -> 36407416403924 | L5: =VLOOKUP($B$6,'Doanh thu'!$A$3:$L$2000,11,FALSE) -> 46176484549771 | M5: =VLOOKUP($B$6,'Doanh thu'!$A$3:$L$2000,12,FALSE) -> 52900847302653
B6: hpg | H6: YoY% | I6: =VLOOKUP($B$6,'Doanh thu'!$A$3:$Q$2000,U41,FALSE) -> 0.21940996 | J6: =VLOOKUP($B$6,'Doanh thu'!$A$3:$Q$2000,V41,FALSE) -> -0.092148748 | K6: =VLOOKUP($B$6,'Doanh thu'!$A$3:$Q$2000,W41,FALSE) -> 0.072185691 | L6: =VLOOKUP($B$6,'Doanh thu'!$A$3:$Q$2000,X41,FALSE) -> 0.33879876 | M6: =VLOOKUP($B$6,'Doanh thu'!$A$3:$Q$2000,Y41,FALSE) -> 0.40612687
B8: =VLOOKUP($B$6,LNST!$A$2:$B$1671,2,FALSE) -> Hòa Phát | H8: Lợi nhuận gộp | I8: =I4 -> Q1.25 | J8: =J4 -> Q2.25 | K8: =K4 -> Q3.25 | L8: =L4 -> Q4.25 | M8: =M4 -> Q1.26
H9: Giá trị | I9: =VLOOKUP($B$6,LNG!$A$2:$I$1999,L41,FALSE) -> 5424153925132 | J9: =VLOOKUP($B$6,LNG!$A$2:$I$1999,M41,FALSE) -> 6589722485709 | K9: =VLOOKUP($B$6,LNG!$A$2:$I$1999,N41,FALSE) -> 6087261275166 | L9: =VLOOKUP($B$6,LNG!$A$2:$I$1999,O41,FALSE) -> 6396650497175 | M9: =VLOOKUP($B$6,LNG!$A$2:$I$1999,P41,FALSE) -> 8365068607995
B10: Ngành | C10: =VLOOKUP($B$6,'GIÁ CP'!$K$2:$M$2000,3,FALSE) -> Thép và sản phẩm thép | E10: Giá (VND) | F10: =VLOOKUP($B$6,'GIÁ CP'!$A$2:$D$2000,4,FALSE) -> 27000 | H10: Biên | I10: =I9/I5 -> 0.1441763 | J10: =J9/J5 -> 0.18350396 | K10: =K9/K5 -> 0.16719839 | L10: =L9/L5 -> 0.13852615 | M10: =M9/M5 -> 0.15812731
B11: P/E | C11: =F10/C12 -> 9.8203399 | E11: LNST4Q | F11: =SUM(J13:M13)/10^9 -> 21102.893 | G11: tỷ
B12: EPS | C12: =VLOOKUP(B6,'EPS pha loãng'!$A$1:$D$1672,4,FALSE) -> 2749.3957 | E12: Vốn hóa | F12: =F10*F13/10^9 -> 207237.58 | G12: tỷ | H12: LNST | I12: =I4 -> Q1.25 | J12: =J4 -> Q2.25 | K12: =K4 -> Q3.25 | L12: =L4 -> Q4.25 | M12: =M4 -> Q1.26
B13: P/B | C13: =VLOOKUP($B$6,P.B!$A$2:$I$1997,4,FALSE) -> 1.54 | E13: SLCP | F13: =VLOOKUP($B$6,'SLCP lưu hành'!$A$1:$D$1677,4,FALSE) -> 7675465855 | H13: Giá trị | I13: =VLOOKUP($B$6,LNST!$A$3:$L$1613,LNST!H1,FALSE) -> 3344284694388 | J13: =VLOOKUP($B$6,LNST!$A$3:$L$1613,LNST!I1,FALSE) -> 4256487211764 | K13: =VLOOKUP($B$6,LNST!$A$3:$L$1613,LNST!J1,FALSE) -> 3988318474539 | L13: =VLOOKUP($B$6,LNST!$A$3:$L$1613,LNST!K1,FALSE) -> 3864083625532 | M13: =VLOOKUP($B$6,LNST!$A$3:$L$1613,LNST!L1,FALSE) -> 8994003244142
H14: YoY% | I14: =VLOOKUP($B$6,LNST!$A$3:$S$1671,LNST!M1,FALSE) -> 0.16501702 | J14: =VLOOKUP($B$6,LNST!$A$3:$S$1671,LNST!N1,FALSE) -> 0.28235907 | K14: =VLOOKUP($B$6,LNST!$A$3:$S$1671,LNST!O1,FALSE) -> 0.31934796 | L14: =VLOOKUP($B$6,LNST!$A$3:$S$1671,LNST!P1,FALSE) -> 0.37578196 | M14: =VLOOKUP($B$6,LNST!$A$3:$S$1671,LNST!Q1,FALSE) -> 1.6893653
H16: Trend tăng trưởng
H17: 3Q gần nhất | I17: 2025 so với 2024 | J17: Bình quân 4 năm | L17: ► Đăng ký mở tài khoản CK
H18: =VLOOKUP($B$6,LNST!$A$3:$S$1671,18,FALSE) -> 0.83594504 | I18: =VLOOKUP($B$6,'LNST năm'!$A$2:$J$2000,8,FALSE) -> 0.28521042 | J18: =VLOOKUP($B$6,'LNST năm'!$A$2:$J$2000,9,FALSE) -> 0.2211952 | L18: ► Tham gia Room Tư vấn TVI
L19: Liên hệ trợ lý: | M19: Quỳnh Anh 0395.626.368 (zalo/SĐT)
C20: Sản phẩm dành riêng cho khách hàng của đội ngũ TVI!
H23: 12 | I23: 13
I41: 1 | J41: 2 | K41: 3 | L41: 4 | M41: 5 | N41: 6 | O41: 7 | P41: 8 | Q41: 9 | R41: 10 | S41: 11 | T41: 12 | U41: 13 | V41: 14 | W41: 15 | X41: 16 | Y41: 17 | Z41: 18 | AA41: 19

Sheet Doanh thu
A1: 1 | B1: =A1+1 -> 2 | C1: =B1+1 -> 3 | D1: =C1+1 -> 4 | E1: =D1+1 -> 5 | F1: =E1+1 -> 6 | G1: =F1+1 -> 7 | H1: =G1+1 -> 8 | I1: =H1+1 -> 9 | ... Q1: =P1+1 -> 17
A2: Mã CK | B2: Tên | C2: Sàn | D2: Q1.24 | E2: Q2.24 | F2: Q3.24 | G2: Q4.24 | H2: Q1.25 | I2: Q2.25 | J2: Q3.25 | K2: Q4.25 | L2: Q1.26 | M2: Tăng | N2: Tăng trưởng 1 | O2: Tăng trưởng 2 | P2: Tăng trưởng 3 | Q2: Tăng trưởng 4
A3: AAA | B3: An Phát Bioplastics | C3: HOSE | D3: 2963831327623 | E3: 2782480085532 | F3: 3193399535332 | G3: 3842519612561 | H3: 3856408101891 | I3: 2309974267663 | J3: 2369473905606 | K3: 2192291125691 | L3: =VLOOKUP(A3,Sheet2!$A$1:$E$2000,5,FALSE) -> 2224065397921 | M3: =(H3-D3)/ABS(D3) -> 0.3011564 | N3: =(I3-E3)/ABS(E3) -> -0.16981463 | O3: =(J3-F3)/ABS(F3) -> -0.25800894 | P3: =(K3-G3)/ABS(G3) -> -0.42946521 | Q3: =(L3-H3)/ABS(H3) -> -0.42328059
A4: AAM | B4: Thủy sản Mekong | C4: HOSE | D4: 34565421958 | E4: 34000786456 | F4: 49775079174 | G4: 35142056786 | H4: 54375428180 | I4: 64320760366 | J4: 42450172367 | K4: 9309919152 | L4: =VLOOKUP(A4,Sheet2!$A$1:$E$2000,5,FALSE) -> 33444004710 | M4: =(H4-D4)/ABS(D4) -> 0.57311628 | N4: =(I4-E4)/ABS(E4) -> 0.89174331 | O4: =(J4-F4)/ABS(F4) -> -0.14716012 | P4: =(K4-G4)/ABS(G4) -> -0.73507757 | Q4: =(L4-H4)/ABS(H4) -> -0.38494269
A5: AAT | B5: Tập đoàn Tiên Sơn Thanh Hóa | C5: HOSE | D5: 204683899039 | E5: 179718744794 | F5: 65332021050 | G5: 133277166354 | H5: 207268038521 | I5: 179192185423 | J5: 213108789097 | K5: 409112380019 | L5: =VLOOKUP(A5,Sheet2!$A$1:$E$2000,5,FALSE) -> 235047541189 | M5: =(H5-D5)/ABS(D5) -> 0.012625026 | N5: =(I5-E5)/ABS(E5) -> -0.0029299079 | O5: =(J5-F5)/ABS(F5) -> 2.2619347 | P5: =(K5-G5)/ABS(G5) -> 2.0696359 | Q5: =(L5-H5)/ABS(H5) -> 0.13402695
A6: ABR | B6: Đầu tư Nhãn Hiệu Việt | C6: HOSE | D6: 16478251145 | E6: -4044824828 | F6: 6356015314 | G6: 6106913728 | H6: 6365061149 | I6: 6260496681 | J6: 6107587629 | K6: 6918722892 | L6: =VLOOKUP(A6,Sheet2!$A$1:$E$2000,5,FALSE) -> 6335090877 | M6: =(H6-D6)/ABS(D6) -> -0.61372957 | N6: =(I6-E6)/ABS(E6) -> 2.5477794 | O6: =(J6-F6)/ABS(F6) -> -0.039085445 | P6: =(K6-G6)/ABS(G6) -> 0.1329328 | Q6: =(L6-H6)/ABS(H6) -> -0.0047085599
A7: ABS | B7: DV Nông nghiệp Bình Thuận | C7: HOSE | D7: 35974612465 | E7: 172571741971 | F7: 101023376333 | G7: 86571126645 | H7: 65838104122 | I7: 35255635011 | J7: 30017456759 | K7: 38913283093 | L7: =VLOOKUP(A7,Sheet2!$A$1:$E$2000,5,FALSE) -> 42956175499 | M7: =(H7-D7)/ABS(D7) -> 0.83012685 | N7: =(I7-E7)/ABS(E7) -> -0.79570447 | O7: =(J7-F7)/ABS(F7) -> -0.70286623 | P7: =(K7-G7)/ABS(G7) -> -0.55050506 | Q7: =(L7-H7)/ABS(H7) -> -0.34754841
A8: ABT | B8: Thủy sản Bến Tre | C8: HOSE | D8: 121866077150 | E8: 158672545091 | F8: 151758000405 | G8: 151194400776 | H8: 163767610564 | I8: 177492607944 | J8: 192791973602 | K8: 172768790575 | L8: =VLOOKUP(A8,Sheet2!$A$1:$E$2000,5,FALSE) -> 187835693906 | M8: =(H8-D8)/ABS(D8) -> 0.34383263 | N8: =(I8-E8)/ABS(E8) -> 0.11860945 | O8: =(J8-F8)/ABS(F8) -> 0.27039084 | P8: =(K8-G8)/ABS(G8) -> 0.14269305 | Q8: =(L8-H8)/ABS(H8) -> 0.14696486
A9: ACB | B9: ACB | C9: HOSE | L9: =VLOOKUP(A9,Sheet2!$A$1:$E$2000,5,FALSE) -> 0 | M9: =(H9-D9)/ABS(D9) -> #DIV/0! | N9: =(I9-E9)/ABS(E9) -> #DIV/0! | O9: =(J9-F9)/ABS(F9) -> #DIV/0! | P9: =(K9-G9)/ABS(G9) -> #DIV/0! | Q9: =(L9-H9)/ABS(H9) -> #DIV/0!
A10: ACC | B10: Đầu tư và XD Bình Dương ACC | C10: HOSE | D10: 111374088456 | E10: 143915267320 | F10: 178278200430 | G10: 266456354306 | H10: 130281092225 | I10: 197176052456 | J10: 329365260237 | K10: 111721499096 | L10: =VLOOKUP(A10,Sheet2!$A$1:$E$2000,5,FALSE) -> 151639959465 | M10: =(H10-D10)/ABS(D10) -> 0.16976124 | N10: =(I10-E10)/ABS(E10) -> 0.37008433 | O10: =(J10-F10)/ABS(F10) -> 0.84747916 | P10: =(K10-G10)/ABS(G10) -> -0.5807137 | Q10: =(L10-H10)/ABS(H10) -> 0.16394449
A11: ACG | B11: Gỗ An Cường | C11: HOSE | D11: 694977577935 | E11: 1025855544080 | F11: 1043817347876 | G11: 1216213551747 | H11: 802034366779 | I11: 961089934272 | J11: 1177462519376 | K11: 1668116456301 | L11: =VLOOKUP(A11,Sheet2!$A$1:$E$2000,5,FALSE) -> 1109927947175 | M11: =(H11-D11)/ABS(D11) -> 0.15404351 | N11: =(I11-E11)/ABS(E11) -> -0.063133265 | O11: =(J11-F11)/ABS(F11) -> 0.12803502 | P11: =(K11-G11)/ABS(G11) -> 0.37156542 | Q11: =(L11-H11)/ABS(H11) -> 0.38389076
A12: ACL | B12: Thủy sản CL An Giang | C12: HOSE | D12: 316083402526 | E12: 561952923923 | F12: 415244211842 | G12: 455454523780 | H12: 418239076318 | I12: 581438536254 | J12: 542220091436 | K12: 569426349082 | L12: =VLOOKUP(A12,Sheet2!$A$1:$E$2000,5,FALSE) -> 427960489100 | M12: =(H12-D12)/ABS(D12) -> 0.32319215 | N12: =(I12-E12)/ABS(E12) -> 0.034674813 | O12: =(J12-F12)/ABS(F12) -> 0.30578603 | P12: =(K12-G12)/ABS(G12) -> 0.25023755 | Q12: =(L12-H12)/ABS(H12) -> 0.023243674
A13: ADG | B13: Clever Group | C13: HOSE | D13: 84079773542 | E13: 118397334255 | F13: 108353091804 | G13: 153355832775 | H13: 84023894096 | I13: 114324685009 | J13: 117024077114 | K13: 182993617934 | L13: =VLOOKUP(A13,Sheet2!$A$1:$E$2000,5,FALSE) -> 0 | M13: =(H13-D13)/ABS(D13) -> -0.00066460034 | N13: =(I13-E13)/ABS(E13) -> -0.03439815 | O13: =(J13-F13)/ABS(F13) -> 0.080025269 | P13: =(K13-G13)/ABS(G13) -> 0.19326154 | Q13: =(L13-H13)/ABS(H13) -> -1
A14: ADP | B14: Sơn Á Đông | C14: HOSE | D14: 166343628268 | E14: 245427056333 | F14: 214528322649 | G14: 191555691169 | H14: 200827697629 | I14: 175668167694 | J14: 140076412171 | K14: 135188360842 | L14: =VLOOKUP(A14,Sheet2!$A$1:$E$2000,5,FALSE) -> 154364991714 | M14: =(H14-D14)/ABS(D14) -> 0.20730622 | N14: =(I14-E14)/ABS(E14) -> -0.28423471 | O14: =(J14-F14)/ABS(F14) -> -0.34704933 | P14: =(K14-G14)/ABS(G14) -> -0.2942608 | Q14: =(L14-H14)/ABS(H14) -> -0.23135607
A15: ADS | B15: Dệt sợi DAMSAN | C15: HOSE | D15: 389818986236 | E15: 391134872475 | F15: 365744169139 | G15: 481935542946 | H15: 356587407631 | I15: 445523957067 | J15: 430237235488 | K15: 637589253573 | L15: =VLOOKUP(A15,Sheet2!$A$1:$E$2000,5,FALSE) -> 408191712082 | M15: =(H15-D15)/ABS(D15) -> -0.085248743 | N15: =(I15-E15)/ABS(E15) -> 0.13905455 | O15: =(J15-F15)/ABS(F15) -> 0.17633382 | P15: =(K15-G15)/ABS(G15) -> 0.3229762 | Q15: =(L15-H15)/ABS(H15) -> 0.14471713
A16: AFX | B16: XNK Nông sản Thực phẩm An Giang | C16: HOSE | D16: 396970062620 | E16: 609337697349 | F16: 358650589072 | G16: 692072587810 | H16: 307970517569 | I16: 713323995790 | J16: 735278673951 | K16: 1057049145042 | L16: =VLOOKUP(A16,Sheet2!$A$1:$E$2000,5,FALSE) -> 884015930897 | M16: =(H16-D16)/ABS(D16) -> -0.22419712 | N16: =(I16-E16)/ABS(E16) -> 0.17065463 | O16: =(J16-F16)/ABS(F16) -> 1.0501254 | P16: =(K16-G16)/ABS(G16) -> 0.52736745 | Q16: =(L16-H16)/ABS(H16) -> 1.8704564
A17: AGG | B17: Bất động sản An Gia | C17: HOSE | D17: 1312787417097 | E17: 169043316241 | F17: 268367573759 | G17: 163200171412 | H17: 191772044951 | I17: 193906331896 | J17: 170367839185 | K17: 273042314718 | L17: =VLOOKUP(A17,Sheet2!$A$1:$E$2000,5,FALSE) -> 67263896896 | M17: =(H17-D17)/ABS(D17) -> -0.85391996 | N17: =(I17-E17)/ABS(E17) -> 0.14708074 | O17: =(J17-F17)/ABS(F17) -> -0.3651698 | P17: =(K17-G17)/ABS(G17) -> 0.67305164 | Q17: =(L17-H17)/ABS(H17) -> -0.64925077
A18: AGR | B18: Agriseco | C18: HOSE | D18: 92248189883 | E18: 122101376845 | F18: 98115370595 | G18: 100431955672 | H18: 103757872066 | I18: 97968845732 | J18: 156899568846 | K18: 123385164667 | L18: =VLOOKUP(A18,Sheet2!$A$1:$E$2000,5,FALSE) -> 145316560382 | M18: =(H18-D18)/ABS(D18) -> 0.12476865 | N18: =(I18-E18)/ABS(E18) -> -0.1976434 | O18: =(J18-F18)/ABS(F18) -> 0.59913343 | P18: =(K18-G18)/ABS(G18) -> 0.22854488 | Q18: =(L18-H18)/ABS(H18) -> 0.40053528
A19: ANT | B19: Rau quả thực phẩm An Giang | C19: HOSE | D19: 293176003276 | E19: 404725261338 | F19: 415923493910 | G19: 293941042233 | H19: 467122052811 | I19: 519026260564 | J19: 464650862510 | K19: 348998785003 | L19: =VLOOKUP(A19,Sheet2!$A$1:$E$2000,5,FALSE) -> 0 | M19: =(H19-D19)/ABS(D19) -> 0.59331612 | N19: =(I19-E19)/ABS(E19) -> 0.28241627 | O19: =(J19-F19)/ABS(F19) -> 0.11715464 | P19: =(K19-G19)/ABS(G19) -> 0.1873088 | Q19: =(L19-H19)/ABS(H19) -> -1
A20: ANV | B20: Thủy sản Nam Việt | C20: HOSE | D20: 1016008704124 | E20: 1193412864585 | F20: 1341021310612 | G20: 1360823093592 | H20: 1106263191785 | I20: 1726231655961 | J20: 2000082975336 | K20: 2118930435283 | L20: =VLOOKUP(A20,Sheet2!$A$1:$E$2000,5,FALSE) -> 1841296117934 | M20: =(H20-D20)/ABS(D20) -> 0.088832396 | N20: =(I20-E20)/ABS(E20) -> 0.44646644 | O20: =(J20-F20)/ABS(F20) -> 0.49146248 | P20: =(K20-G20)/ABS(G20) -> 0.55709471 | Q20: =(L20-H20)/ABS(H20) -> 0.66442862
A21: APG | B21: Chứng khoán APG | C21: HOSE | D21: 30204152396 | E21: 65033318681 | F21: 26227531639 | G21: -5443203936 | H21: 24772441725 | I21: 161287771412 | J21: 87245906320 | K21: 73528174391 | L21: =VLOOKUP(A21,Sheet2!$A$1:$E$2000,5,FALSE) -> 84974653113 | M21: =(H21-D21)/ABS(D21) -> -0.17983324 | N21: =(I21-E21)/ABS(E21) -> 1.4800791 | O21: =(J21-F21)/ABS(F21) -> 2.3265009 | P21: =(K21-G21)/ABS(G21) -> 14.508253 | Q21: =(L21-H21)/ABS(H21) -> 2.430209
... A26: AST | B26: Dịch vụ Hàng không Taseco | C26: HOSE | D26: 339525473495 | E26: 309802933086 | F26: 329211695662 | G26: 351502149109 | H26: 384845799703 | I26: 393791048196 | J26: 458209035755 | K26: 490102667620 | L26: =VLOOKUP(A26,Sheet2!$A$1:$E$2000,5,FALSE) -> 555973947060 | M26: =(H26-D26)/ABS(D26) -> 0.13348137 | N26: =(I26-E26)/ABS(E26) -> 0.27110174 | O26: =(J26-F26)/ABS(F26) -> 0.39183705 | P26: =(K26-G26)/ABS(G26) -> 0.39430916 | Q26: =(L26-H26)/ABS(H26) -> 0.44466679
A27: ATP | B27: T.Mại và DV An Thành | C27: HOSE | L27: =VLOOKUP(A27,Sheet2!$A$1:$E$2000,5,FALSE) -> 0 | M27: =(H27-D27)/ABS(D27) -> #DIV/0! | N27: =(I27-E27)/ABS(E27) -> #DIV/0! | O27: =(J27-F27)/ABS(F27) -> #DIV/0! | P27: =(K27-G27)/ABS(G27) -> #DIV/0! | Q27: =(L27-H27)/ABS(H27) -> #DIV/0!
A28: BAF | B28: Nông nghiệp BAF Việt Nam | C28: HOSE | D28: 1292013483890 | E28: 1321178494029 | F28: 1313762843295 | G28: 1713730913054 | H28: 1123604043904 | I28: 1386838129431 | J28: 1136263347895 | K28: 1391145758074 | L28: =VLOOKUP(A28,Sheet2!$A$1:$E$2000,5,FALSE) -> 1762207980539 | M28: =(H28-D28)/ABS(D28) -> -0.1303465 | N28: =(I28-E28)/ABS(E28) -> 0.049697778 | O28: =(J28-F28)/ABS(F28) -> -0.13510771 | P28: =(K28-G28)/ABS(G28) -> -0.18823559 | Q28: =(L28-H28)/ABS(H28) -> 0.56835318
A29: BCE | B29: XD và GT Bình Dương | C29: HOSE | D29: 10588494898 | E29: 16562950556 | F29: 10350287177 | G29: 254464002316 | H29: 9379556294 | I29: 117973529093 | J29: 189949118469 | K29: 562243170086 | L29: =VLOOKUP(A29,Sheet2!$A$1:$E$2000,5,FALSE) -> 63015458144 | M29: =(H29-D29)/ABS(D29) -> -0.11417474 | N29: =(I29-E29)/ABS(E29) -> 6.1227363 | O29: =(J29-F29)/ABS(F29) -> 17.352063 | P29: =(K29-G29)/ABS(G29) -> 1.2095195 | Q29: =(L29-H29)/ABS(H29) -> 5.7183837
A30: BCG | B30: Bamboo Capital | C30: HOSE | D30: 985437239704 | E30: 1114820056534 | F30: 1137868443276 | G30: 1133731815353 | L30: =VLOOKUP(A30,Sheet2!$A$1:$E$2000,5,FALSE) -> 0 | M30: =(H30-D30)/ABS(D30) -> -1 | N30: =(I30-E30)/ABS(E30) -> -1 | O30: =(J30-F30)/ABS(F30) -> -1 | P30: =(K30-G30)/ABS(G30) -> -1 | Q30: =(L30-H30)/ABS(H30) -> #DIV/0!
A31: BCM | B31: Becamex Group | C31: HOSE | D31: 811605444546 | E31: 1156018236714 | F31: 1227612256297 | G31: 2044000623070 | H31: 1842515299282 | I31: 2903596879027 | J31: 828384301042 | K31: 1376454513805 | L31: =VLOOKUP(A31,Sheet2!$A$1:$E$2000,5,FALSE) -> 1104960466553 | M31: =(H31-D31)/ABS(D31) -> 1.2702106 | N31: =(I31-E31)/ABS(E31) -> 1.5117224 | O31: =(J31-F31)/ABS(F31) -> -0.32520688 | P31: =(K31-G31)/ABS(G31) -> -0.32658802 | Q31: =(L31-H31)/ABS(H31) -> -0.40029781
A32: BFC | B32: Phân bón Bình Điền | C32: HOSE | D32: 1940449006153 | E32: 2916008103459 | F32: 2030983062685 | G32: 2470803574580 | H32: 2554263681231 | I32: 3534561210826 | J32: 2059537036302 | K32: 2468094589244 | L32: =VLOOKUP(A32,Sheet2!$A$1:$E$2000,5,FALSE) -> 3345445434562 | M32: =(H32-D32)/ABS(D32) -> 0.3163261 | N32: =(I32-E32)/ABS(E32) -> 0.21212325 | O32: =(J32-F32)/ABS(F32) -> 0.014059188 | P32: =(K32-G32)/ABS(G32) -> -0.0010963985 | Q32: =(L32-H32)/ABS(H32) -> 0.30974944
A33: BHN | B33: HABECO | C33: HOSE | D33: 1308100051331 | E33: 2305566275712 | F33: 2335256892188 | G33: 2270697593043 | H33: 1458025664821 | I33: 2356020079914 | J33: 2507409811105 | K33: 2203147758159 | L33: =VLOOKUP(A33,Sheet2!$A$1:$E$2000,5,FALSE) -> 1929641088961 | M33: =(H33-D33)/ABS(D33) -> 0.11461326 | N33: =(I33-E33)/ABS(E33) -> 0.021883476 | O33: =(J33-F33)/ABS(F33) -> 0.07371905 | P33: =(K33-G33)/ABS(G33) -> -0.029748495 | Q33: =(L33-H33)/ABS(H33) -> 0.32346168
A34: BIC | B34: Bảo hiểm BIDV | C34: HOSE | D34: 984231382085 | E34: 1124794719925 | F34: 983764299627 | G34: 1170862079783 | H34: 1033198742002 | I34: 1120979677832 | J34: 1035612243283 | K34: 1096571314717 | L34: =VLOOKUP(A34,Sheet2!$A$1:$E$2000,5,FALSE) -> 1137200217440 | M34: =(H34-D34)/ABS(D34) -> 0.049751878 | N34: =(I34-E34)/ABS(E34) -> -0.0033917674 | O34: =(J34-F34)/ABS(F34) -> 0.052703624 | P34: =(K34-G34)/ABS(G34) -> -0.063449629 | Q34: =(L34-H34)/ABS(H34) -> 0.1006597
A35: BID | B35: BIDV | C35: HOSE | L35: =VLOOKUP(A35,Sheet2!$A$1:$E$2000,5,FALSE) -> 0 | M35: =(H35-D35)/ABS(D35) -> #DIV/0! | N35: =(I35-E35)/ABS(E35) -> #DIV/0! | O35: =(J35-F35)/ABS(F35) -> #DIV/0! | P35: =(K35-G35)/ABS(G35) -> #DIV/0! | Q35: =(L35-H35)/ABS(H35) -> #DIV/0!
A36: BKG | B36: Đầu tư BKG Việt Nam | C36: HOSE | D36: 69734595158 | E36: 88471245041 | F36: 65169105897 | G36: 65351706715 | H36: 44475337897 | I36: 86302338481 | J36: 41179706272 | K36: 61864883210 | L36: =VLOOKUP(A36,Sheet2!$A$1:$E$2000,5,FALSE) -> 46725536629 | M36: =(H36-D36)/ABS(D36) -> -0.36221989 | N36: =(I36-E36)/ABS(E36) -> -0.024515384 | O36: =(J36-F36)/ABS(F36) -> -0.36811 | P36: =(K36-G36)/ABS(G36) -> -0.053354743 | Q36: =(L36-H36)/ABS(H36) -> 0.050594303
A37: BMC | B37: Khoáng sản Bình Định | C37: HOSE | D37: 40752593359 | E37: 47604246642 | F37: 46710990271 | G37: 60251731910 | H37: 11630507216 | I37: 38966853575 | J37: 39602162013 | K37: 29703235504 | L37: =VLOOKUP(A37,Sheet2!$A$1:$E$2000,5,FALSE) -> 23608555252 | M37: =(H37-D37)/ABS(D37) -> -0.71460694 | N37: =(I37-E37)/ABS(E37) -> -0.18144165 | O37: =(J37-F37)/ABS(F37) -> -0.15218749 | P37: =(K37-G37)/ABS(G37) -> -0.50701441 | Q37: =(L37-H37)/ABS(H37) -> 1.0298818
A38: BMI | B38: Bảo hiểm Bảo Minh | C38: HOSE | D38: 1274319102954 | E38: 1278362337536 | F38: 1284431816427 | G38: 1285634849338 | H38: 1340438820817 | I38: 1349781084472 | J38: 1330844174779 | K38: 1340101826964 | L38: =VLOOKUP(A38,Sheet2!$A$1:$E$2000,5,FALSE) -> 1360420068969 | M38: =(H38-D38)/ABS(D38) -> 0.051886311 | N38: =(I38-E38)/ABS(E38) -> 0.055867374 | O38: =(J38-F38)/ABS(F38) -> 0.036134544 | P38: =(K38-G38)/ABS(G38) -> 0.042365822 | Q38: =(L38-H38)/ABS(H38) -> 0.014906498
A39: BMP | B39: Nhựa Bình Minh | C39: HOSE | D39: 1002851021600 | E39: 1153199582323 | F39: 1406831392235 | G39: 1052796659388 | H39: 1383100181955 | I39: 1308129555745 | J39: 1532289910260 | K39: 1286058323278 | L39: =VLOOKUP(A39,Sheet2!$A$1:$E$2000,5,FALSE) -> 1457310965938 | M39: =(H39-D39)/ABS(D39) -> 0.37916814 | N39: =(I39-E39)/ABS(E39) -> 0.13434793 | O39: =(J39-F39)/ABS(F39) -> 0.089178077 | P39: =(K39-G39)/ABS(G39) -> 0.22156383 | Q39: =(L39-H39)/ABS(H39) -> 0.053655393
A40: BRC | B40: Cao su Bến Thành | C40: HOSE | D40: 73547629597 | E40: 103489553943 | F40: 123717111297 | G40: 118299997313 | H40: 97939222338 | I40: 114457491873 | J40: 111239328391 | K40: 113250645892 | L40: =VLOOKUP(A40,Sheet2!$A$1:$E$2000,5,FALSE) -> 95250799894 | M40: =(H40-D40)/ABS(D40) -> 0.33164349 | N40: =(I40-E40)/ABS(E40) -> 0.10598111 | O40: =(J40-F40)/ABS(F40) -> -0.10085737 | P40: =(K40-G40)/ABS(G40) -> -0.0426826 | Q40: =(L40-H40)/ABS(H40) -> -0.027449906
A41: BSI | B41: Chứng khoán BIDV | C41: HOSE | D41: 351747406193 | E41: 424150114113 | F41: 319111392500 | G41: 318505024865 | H41: 337183663045 | I41: 506431146251 | J41: 687921042574 | K41: 565654599730 | L41: =VLOOKUP(A41,Sheet2!$A$1:$E$2000,5,FALSE) -> 697140773775 | M41: =(H41-D41)/ABS(D41) -> -0.041403982 | N41: =(I41-E41)/ABS(E41) -> 0.19399036 | O41: =(J41-F41)/ABS(F41) -> 1.1557395 | P41: =(K41-G41)/ABS(G41) -> 0.77596758 | Q41: =(L41-H41)/ABS(H41) -> 1.0675402
A42: BSR | B42: Lọc Hóa dầu Bình Sơn | C42: HOSE | D42: 30689342319179 | E42: 24423588755537 | F42: 31945856725324 | G42: 35968276079519 | H42: 31894592097760 | I42: 36771954932170 | J42: 35290234805794 | K42: 37625367271578 | L42: =VLOOKUP(A42,Sheet2!$A$1:$E$2000,5,FALSE) -> 45919538260329 | M42: =(H42-D42)/ABS(D42) -> 0.039272584 | N42: =(I42-E42)/ABS(E42) -> 0.5055918 | O42: =(J42-F42)/ABS(F42) -> 0.10468895 | P42: =(K42-G42)/ABS(G42) -> 0.046070909 | Q42: =(L42-H42)/ABS(H42) -> 0.43972803
A43: BTP | B43: Nhiệt điện Bà Rịa | C43: HOSE | D43: 49337909707 | E43: 154550543175 | F43: 74754248596 | G43: 78764061844 | H43: 56942027607 | I43: 66412488368 | J43: 67796700481 | K43: 72127190454 | L43: =VLOOKUP(A43,Sheet2!$A$1:$E$2000,5,FALSE) -> 54780672813 | M43: =(H43-D43)/ABS(D43) -> 0.15412323 | N43: =(I43-E43)/ABS(E43) -> -0.57028628 | O43: =(J43-F43)/ABS(F43) -> -0.093072277 | P43: =(K43-G43)/ABS(G43) -> -0.084262686 | Q43: =(L43-H43)/ABS(H43) -> -0.03795711
A44: BTT | B44: TM - DV Bến Thành | C44: HOSE | D44: 66140765965 | E44: 69915470607 | F44: 59982950252 | G44: 80478532804 | H44: 79222494630 | I44: 60169253989 | J44: 63070500996 | K44: 66243941752 | L44: =VLOOKUP(A44,Sheet2!$A$1:$E$2000,5,FALSE) -> 61327349085 | M44: =(H44-D44)/ABS(D44) -> 0.19778617 | N44: =(I44-E44)/ABS(E44) -> -0.1394 | O44: =(J44-F44)/ABS(F44) -> 0.051473806 | P44: =(K44-G44)/ABS(G44) -> -0.17687439 | Q44: =(L44-H44)/ABS(H44) -> -0.22588465
A45: BVH | B45: Tập đoàn Bảo Việt | C45: HOSE | D45: 9618629223508 | E45: 9990729929129 | F45: 9746436905802 | G45: 10467379625209 | H45: 9974027964437 | I45: 10660794116853 | J45: 9749591088065 | K45: 10563838232459 | L45: =VLOOKUP(A45,Sheet2!$A$1:$E$2000,5,FALSE) -> 9819434237555 | M45: =(H45-D45)/ABS(D45) -> 0.036949001 | N45: =(I45-E45)/ABS(E45) -> 0.067068592 | O45: =(J45-F45)/ABS(F45) -> 0.00032362414 | P45: =(K45-G45)/ABS(G45) -> 0.0092151628 | Q45: =(L45-H45)/ABS(H45) -> -0.015499628
A46: BWE | B46: Nước - Môi trường Bình Dương | C46: HOSE | D46: 791698501791 | E46: 1034300694422 | F46: 942459342041 | G46: 1190539284818 | H46: 923926906721 | I46: 1325150951067 | J46: 903417770373 | K46: 1390372420937 | L46: =VLOOKUP(A46,Sheet2!$A$1:$E$2000,5,FALSE) -> 1034748443534 | M46: =(H46-D46)/ABS(D46) -> 0.16701864 | N46: =(I46-E46)/ABS(E46) -> 0.28120474 | O46: =(J46-F46)/ABS(F46) -> -0.041425205 | P46: =(K46-G46)/ABS(G46) -> 0.16785094 | Q46: =(L46-H46)/ABS(H46) -> 0.11994622
A47: C32 | B47: Đầu tư và Xây dựng 3-2 | C47: HOSE | D47: 163595772831 | E47: 190844419480 | F47: 121671712919 | G47: 150720004119 | H47: 74567977001 | I47: 128133447785 | J47: 124174383636 | K47: 219957100132 | L47: =VLOOKUP(A47,Sheet2!$A$1:$E$2000,5,FALSE) -> 0 | M47: =(H47-D47)/ABS(D47) -> -0.54419374 | N47: =(I47-E47)/ABS(E47) -> -0.32859736 | O47: =(J47-F47)/ABS(F47) -> 0.020569043 | P47: =(K47-G47)/ABS(G47) -> 0.45937562 | Q47: =(L47-H47)/ABS(H47) -> -1
... A71: CTF | B71: City Auto | C71: HOSE | D71: 1504909301829 | E71: 1818735417535 | F71: 2076918642847 | G71: 2773510964627 | H71: 2010532177627 | I71: 2084807453999 | J71: 1939906935330 | K71: 2406980813973 | L71: =VLOOKUP(A71,Sheet2!$A$1:$E$2000,5,FALSE) -> 1914554329693 | M71: =(H71-D71)/ABS(D71) -> 0.33598229 | N71: =(I71-E71)/ABS(E71) -> 0.14629508 | O71: =(J71-F71)/ABS(F71) -> -0.065968741 | P71: =(K71-G71)/ABS(G71) -> -0.13215385 | Q71: =(L71-H71)/ABS(H71) -> -0.047737534
A72: CTG | B72: VietinBank | C72: HOSE | L72: =VLOOKUP(A72,Sheet2!$A$1:$E$2000,5,FALSE) -> 0 | M72: =(H72-D72)/ABS(D72) -> #DIV/0! | N72: =(I72-E72)/ABS(E72) -> #DIV/0! | O72: =(J72-F72)/ABS(F72) -> #DIV/0! | P72: =(K72-G72)/ABS(G72) -> #DIV/0! | Q72: =(L72-H72)/ABS(H72) -> #DIV/0!
A73: CTI | B73: Cường Thuận IDICO | C73: HOSE | D73: 257338250265 | E73: 256511345612 | F73: 273429609837 | G73: 324310776466 | H73: 282486715839 | I73: 348066044583 | J73: 363383278162 | K73: 482825672702 | L73: =VLOOKUP(A73,Sheet2!$A$1:$E$2000,5,FALSE) -> 358198735630 | M73: =(H73-D73)/ABS(D73) -> 0.097725331 | N73: =(I73-E73)/ABS(E73) -> 0.35692261 | O73: =(J73-F73)/ABS(F73) -> 0.32898291 | P73: =(K73-G73)/ABS(G73) -> 0.48877468 | Q73: =(L73-H73)/ABS(H73) -> 0.26801975
A74: CTR | B74: Công trình Viettel | C74: HOSE | D74: 2623099908208 | E74: 3008973474702 | F74: 3475567349174 | G74: 3501878827997 | H74: 2738456545036 | I74: 3236356740123 | J74: 3965175718709 | K74: 3999528265274 | L74: =VLOOKUP(A74,Sheet2!$A$1:$E$2000,5,FALSE) -> 3804825619753 | M74: =(H74-D74)/ABS(D74) -> 0.043977218 | N74: =(I74-E74)/ABS(E74) -> 0.075568385 | O74: =(J74-F74)/ABS(F74) -> 0.1408715 | P74: =(K74-G74)/ABS(G74) -> 0.14210927 | Q74: =(L74-H74)/ABS(H74) -> 0.38940515
A75: CTS | B75: Chứng khoán Vietinbank | C75: HOSE | D75: 323737096591 | E75: 273734551773 | F75: 301660892474 | G75: 133114212574 | H75: 464733343775 | I75: 578312729348 | J75: 652910955482 | K75: 399884917712 | L75: =VLOOKUP(A75,Sheet2!$A$1:$E$2000,5,FALSE) -> 351925777950 | M75: =(H75-D75)/ABS(D75) -> 0.435527 | N75: =(I75-E75)/ABS(E75) -> 1.1126771 | O75: =(J75-F75)/ABS(F75) -> 1.1643871 | P75: =(K75-G75)/ABS(G75) -> 2.0040738 | Q75: =(L75-H75)/ABS(H75) -> -0.24273611
A76: CVT | B76: CMC JSC | C76: HOSE | D76: 294876217410 | E76: 431714097449 | F76: 456490661360 | G76: 528768883698 | H76: 470446371694 | I76: 593371180724 | J76: 521338360721 | K76: 529300315271 | L76: =VLOOKUP(A76,Sheet2!$A$1:$E$2000,5,FALSE) -> 595276508359 | M76: =(H76-D76)/ABS(D76) -> 0.5954029 | N76: =(I76-E76)/ABS(E76) -> 0.37445403 | O76: =(J76-F76)/ABS(F76) -> 0.14205701 | P76: =(K76-G76)/ABS(G76) -> 0.0010050356 | Q76: =(L76-H76)/ABS(H76) -> 0.26534403
A77: D2D | B77: Phát triển Đô thị số 2 | C77: HOSE | D77: 25760719127 | E77: 27456658901 | F77: 26815978444 | G77: 266288025401 | H77: 92017735264 | I77: 551522490811 | J77: 101610423686 | K77: 35811843031 | L77: =VLOOKUP(A77,Sheet2!$A$1:$E$2000,5,FALSE) -> 44125900320 | M77: =(H77-D77)/ABS(D77) -> 2.5720173 | N77: =(I77-E77)/ABS(E77) -> 19.087021 | O77: =(J77-F77)/ABS(F77) -> 2.7891746 | P77: =(K77-G77)/ABS(G77) -> -0.86551463 | Q77: =(L77-H77)/ABS(H77) -> -0.52046309
A78: DAH | B78: Tập đoàn Khách sạn Đông Á | C78: HOSE | D78: 19886922596 | E78: 20403887785 | F78: 20962600416 | G78: 13015206877 | H78: 11257582568 | I78: 13597004454 | J78: 11486260989 | K78: 16161684738 | L78: =VLOOKUP(A78,Sheet2!$A$1:$E$2000,5,FALSE) -> 9803544980 | M78: =(H78-D78)/ABS(D78) -> -0.43392033 | N78: =(I78-E78)/ABS(E78) -> -0.33360717 | O78: =(J78-F78)/ABS(F78) -> -0.45205935 | P78: =(K78-G78)/ABS(G78) -> 0.24175396 | Q78: =(L78-H78)/ABS(H78) -> -0.12916073
A79: DAT | B79: ĐT Du lịch và PT Thủy sản | C79: HOSE | D79: 704846521704 | E79: 765548092856 | F79: 812780999168 | G79: 655358985032 | H79: 581184107912 | I79: 716556597272 | J79: 562655688727 | K79: 673379770005 | L79: =VLOOKUP(A79,Sheet2!$A$1:$E$2000,5,FALSE) -> 641935879522 | M79: =(H79-D79)/ABS(D79) -> -0.17544587 | N79: =(I79-E79)/ABS(E79) -> -0.063995321 | O79: =(J79-F79)/ABS(F79) -> -0.30774011 | P79: =(K79-G79)/ABS(G79) -> 0.027497578 | Q79: =(L79-H79)/ABS(H79) -> 0.10453103
A80: DBC | B80: Tập đoàn DABACO | C80: HOSE | D80: 3252591683255 | E80: 3184669219459 | F80: 3525028180704 | G80: 3611234148480 | H80: 3609350336234 | I80: 3820095842716 | J80: 4841245769242 | K80: 2626978506282 | L80: =VLOOKUP(A80,Sheet2!$A$1:$E$2000,5,FALSE) -> 4124177863856 | M80: =(H80-D80)/ABS(D80) -> 0.10968443 | N80: =(I80-E80)/ABS(E80) -> 0.19952673 | O80: =(J80-F80)/ABS(F80) -> 0.37339208 | P80: =(K80-G80)/ABS(G80) -> -0.27255381 | Q80: =(L80-H80)/ABS(H80) -> 0.14263717
A81: DBD | B81: Dược - TB Y tế Bình Định | C81: HOSE | D81: 383778665897 | E81: 433050487585 | F81: 432818329034 | G81: 477900905055 | H81: 441045052970 | I81: 474537017072 | J81: 439698372187 | K81: 510099147402 | L81: =VLOOKUP(A81,Sheet2!$A$1:$E$2000,5,FALSE) -> 448086937367 | M81: =(H81-D81)/ABS(D81) -> 0.14921722 | N81: =(I81-E81)/ABS(E81) -> 0.095800676 | O81: =(J81-F81)/ABS(F81) -> 0.015895915 | P81: =(K81-G81)/ABS(G81) -> 0.067374307 | Q81: =(L81-H81)/ABS(H81) -> 0.015966361
A82: DBT | B82: Dược phẩm Bến Tre | C82: HOSE | D82: 185370286930 | E82: 224091878454 | F82: 200555874144 | G82: 258393303616 | H82: 161230721110 | I82: 243175119984 | J82: 176992960512 | K82: 278913965821 | L82: =VLOOKUP(A82,Sheet2!$A$1:$E$2000,5,FALSE) -> 189952055785 | M82: =(H82-D82)/ABS(D82) -> -0.13022349 | N82: =(I82-E82)/ABS(E82) -> 0.085158113 | O82: =(J82-F82)/ABS(F82) -> -0.11748803 | P82: =(K82-G82)/ABS(G82) -> 0.079416385 | Q82: =(L82-H82)/ABS(H82) -> 0.1781381
A83: DC4 | B83: Dicera Holdings | C83: HOSE | D83: 111874323895 | E83: 495751240066 | F83: 283801770154 | G83: 203284585728 | H83: 291361094967 | I83: 491187145878 | J83: 520867899801 | K83: 342228051977 | L83: =VLOOKUP(A83,Sheet2!$A$1:$E$2000,5,FALSE) -> 173489614678 | M83: =(H83-D83)/ABS(D83) -> 1.6043607 | N83: =(I83-E83)/ABS(E83) -> -0.0092064201 | O83: =(J83-F83)/ABS(F83) -> 0.83532294 | P83: =(K83-G83)/ABS(G83) -> 0.68349238 | Q83: =(L83-H83)/ABS(H83) -> -0.40455463
A84: DCL | B84: Dược phẩm Cửu Long | C84: HOSE | D84: 277940285207 | E84: 282978661265 | F84: 235615337806 | G84: 510263157742 | H84: 340016729737 | I84: 323238169368 | J84: 285741018794 | K84: 372593194366 | L84: =VLOOKUP(A84,Sheet2!$A$1:$E$2000,5,FALSE) -> 324121488178 | M84: =(H84-D84)/ABS(D84) -> 0.22334454 | N84: =(I84-E84)/ABS(E84) -> 0.14227047 | O84: =(J84-F84)/ABS(F84) -> 0.21274371 | P84: =(K84-G84)/ABS(G84) -> -0.26980189 | Q84: =(L84-H84)/ABS(H84) -> -0.04674841
... A111: DXV | B111: Vật liệu Xây dựng Đà Nẵng | C111: HOSE | D111: 32358273081 | E111: 48592343298 | F111: 48447965987 | G111: 48226610840 | H111: 40265383665 | I111: 61112738964 | J111: 50856820325 | K111: 54499840655 | L111: =VLOOKUP(A111,Sheet2!$A$1:$E$2000,5,FALSE) -> 52437090160 | M111: =(H111-D111)/ABS(D111) -> 0.24436133 | N111: =(I111-E111)/ABS(E111) -> 0.2576619 | O111: =(J111-F111)/ABS(F111) -> 0.049720443 | P111: =(K111-G111)/ABS(G111) -> 0.13007818 | Q111: =(L111-H111)/ABS(H111) -> 0.30228711
A112: E1VFVN30 | B112: Quỹ ETF DCVFMVN30 | C112: HOSE | L112: =VLOOKUP(A112,Sheet2!$A$1:$E$2000,5,FALSE) -> 0 | M112: =(H112-D112)/ABS(D112) -> #DIV/0! | N112: =(I112-E112)/ABS(E112) -> #DIV/0! | O112: =(J112-F112)/ABS(F112) -> #DIV/0! | P112: =(K112-G112)/ABS(G112) -> #DIV/0! | Q112: =(L112-H112)/ABS(H112) -> #DIV/0!
A113: EIB | B113: Eximbank | C113: HOSE | L113: =VLOOKUP(A113,Sheet2!$A$1:$E$2000,5,FALSE) -> 0 | M113: =(H113-D113)/ABS(D113) -> #DIV/0! | N113: =(I113-E113)/ABS(E113) -> #DIV/0! | O113: =(J113-F113)/ABS(F113) -> #DIV/0! | P113: =(K113-G113)/ABS(G113) -> #DIV/0! | Q113: =(L113-H113)/ABS(H113) -> #DIV/0!
A114: ELC | B114: ELCOM | C114: HOSE | D114: 107366643687 | E114: 143220780925 | F114: 177037289650 | G114: 372520507119 | H114: 61372439153 | I114: 268635538139 | J114: 427600200690 | K114: 760127444147 | L114: =VLOOKUP(A114,Sheet2!$A$1:$E$2000,5,FALSE) -> 114302504502 | M114: =(H114-D114)/ABS(D114) -> -0.42838449 | N114: =(I114-E114)/ABS(E114) -> 0.8756743 | O114: =(J114-F114)/ABS(F114) -> 1.4153115 | P114: =(K114-G114)/ABS(G114) -> 1.0404983 | Q114: =(L114-H114)/ABS(H114) -> 0.86244031
A115: EVE | B115: Everpia | C115: HOSE | D115: 167410445897 | E115: 169099414923 | F115: 208195720501 | G115: 196536107341 | H115: 143289810430 | I115: 188760934854 | J115: 205997999711 | K115: 212684101747 | L115: =VLOOKUP(A115,Sheet2!$A$1:$E$2000,5,FALSE) -> 151685804553 | M115: =(H115-D115)/ABS(D115) -> -0.14408083 | N115: =(I115-E115)/ABS(E115) -> 0.11627196 | O115: =(J115-F115)/ABS(F115) -> -0.010556032 | P115: =(K115-G115)/ABS(G115) -> 0.082162991 | Q115: =(L115-H115)/ABS(H115) -> 0.058594495
A116: EVF | B116: Tài chính Tổng hợp Điện lực | C116: HOSE | L116: =VLOOKUP(A116,Sheet2!$A$1:$E$2000,5,FALSE) -> 0 | M116: =(H116-D116)/ABS(D116) -> #DIV/0! | N116: =(I116-E116)/ABS(E116) -> #DIV/0! | O116: =(J116-F116)/ABS(F116) -> #DIV/0! | P116: =(K116-G116)/ABS(G116) -> #DIV/0! | Q116: =(L116-H116)/ABS(H116) -> #DIV/0!
A117: EVG | B117: Tập đoàn Everland | C117: HOSE | D117: 143414908601 | E117: 486278494674 | F117: 332453929763 | G117: 230242273359 | H117: 191760881028 | I117: 195408771816 | J117: 187383993923 | K117: 544641208535 | L117: =VLOOKUP(A117,Sheet2!$A$1:$E$2000,5,FALSE) -> 323088889571 | M117: =(H117-D117)/ABS(D117) -> 0.33710563 | N117: =(I117-E117)/ABS(E117) -> -0.59815461 | O117: =(J117-F117)/ABS(F117) -> -0.43636102 | P117: =(K117-G117)/ABS(G117) -> 1.3655135 | Q117: =(L117-H117)/ABS(H117) -> 0.68485297
A118: FCM | B118: Bê tông Phan Vũ Hà Nam | C118: HOSE | D118: 78947571502 | E118: 165388633712 | F118: 103344742676 | G118: 121393289444 | H118: 112051935900 | I118: 116276135909 | J118: 93142355192 | K118: 140560748936 | L118: =VLOOKUP(A118,Sheet2!$A$1:$E$2000,5,FALSE) -> 121936472256 | M118: =(H118-D118)/ABS(D118) -> 0.41932087 | N118: =(I118-E118)/ABS(E118) -> -0.29695207 | O118: =(J118-F118)/ABS(F118) -> -0.098721882 | P118: =(K118-G118)/ABS(G118) -> 0.15789554 | Q118: =(L118-H118)/ABS(H118) -> 0.088213883
A119: FCN | B119: FECON CORP | C119: HOSE | D119: 611622362836 | E119: 815940775234 | F119: 744389861303 | G119: 1202744357110 | H119: 820683657085 | I119: 1326314982713 | J119: 1142624340275 | K119: 1572214243882 | L119: =VLOOKUP(A119,Sheet2!$A$1:$E$2000,5,FALSE) -> 1302197745510 | M119: =(H119-D119)/ABS(D119) -> 0.34181434 | N119: =(I119-E119)/ABS(E119) -> 0.62550399 | O119: =(J119-F119)/ABS(F119) -> 0.53498106 | P119: =(K119-G119)/ABS(G119) -> 0.30718904 | Q119: =(L119-H119)/ABS(H119) -> 0.58672314
A120: FDC | B120: FIDECO | C120: HOSE | D120: 4866809629 | E120: 4315428503 | F120: 7187883236 | G120: 12568347521 | H120: 18583314049 | I120: 18871918758 | J120: 17975698419 | K120: 17863825704 | L120: =VLOOKUP(A120,Sheet2!$A$1:$E$2000,5,FALSE) -> 17996754671 | M120: =(H120-D120)/ABS(D120) -> 2.818377 | N120: =(I120-E120)/ABS(E120) -> 3.3731274 | O120: =(J120-F120)/ABS(F120) -> 1.5008334 | P120: =(K120-G120)/ABS(G120) -> 0.42133448 | Q120: =(L120-H120)/ABS(H120) -> -0.031563766
A121: FIR | B121: Địa ốc First Real | C121: HOSE | D121: 27606930617 | E121: 14145199460 | F121: 27881759827 | G121: 276755455 | H121: 45770344261 | I121: 43097797288 | J121: 19117621675 | K121: 20769696029 | L121: =VLOOKUP(A121,Sheet2!$A$1:$E$2000,5,FALSE) -> 0 | M121: =(H121-D121)/ABS(D121) -> 0.65792949 | N121: =(I121-E121)/ABS(E121) -> 2.0468144 | O121: =(J121-F121)/ABS(F121) -> -0.31433232 | P121: =(K121-G121)/ABS(G121) -> 74.047106 | Q121: =(L121-H121)/ABS(H121) -> -1
A122: FIT | B122: Tập đoàn F.I.T | C122: HOSE | D122: 408847011567 | E122: 468304334872 | F122: 398021642894 | G122: 678485085808 | H122: 515308580967 | I122: 538777789040 | J122: 487157387793 | K122: 531944042566 | L122: =VLOOKUP(A122,Sheet2!$A$1:$E$2000,5,FALSE) -> 0 | M122: =(H122-D122)/ABS(D122) -> 0.26039464 | N122: =(I122-E122)/ABS(E122) -> 0.15048644 | O122: =(J122-F122)/ABS(F122) -> 0.22394698 | P122: =(K122-G122)/ABS(G122) -> -0.2159827 | Q122: =(L122-H122)/ABS(H122) -> -1
A123: FMC | B123: Thực phẩm Sao Ta | C123: HOSE | D123: 1460715079260 | E123: 1242798664658 | F123: 2845078971792 | G123: 1364030773448 | H123: 1990479369633 | I123: 1876441530358 | J123: 2983564660010 | K123: 1334765171729 | L123: =VLOOKUP(A123,Sheet2!$A$1:$E$2000,5,FALSE) -> 1398523350604 | M123: =(H123-D123)/ABS(D123) -> 0.36267462 | N123: =(I123-E123)/ABS(E123) -> 0.50985158 | O123: =(J123-F123)/ABS(F123) -> 0.048675516 | P123: =(K123-G123)/ABS(G123) -> -0.021455236 | Q123: =(L123-H123)/ABS(H123) -> -0.2973937
A124: FPT | B124: FPT Corp | C124: HOSE | D124: 14092928413699 | E124: 15245226416020 | F124: 15902821715757 | G124: 17607817805891 | H124: 16058140942460 | I124: 16624713040067 | J124: 17204521225302 | K124: 20225449892881 | L124: =VLOOKUP(A124,Sheet2!$A$1:$E$2000,5,FALSE) -> 12479997206775 | M124: =(H124-D124)/ABS(D124) -> 0.13944671 | N124: =(I124-E124)/ABS(E124) -> 0.090486464 | O124: =(J124-F124)/ABS(F124) -> 0.081853367 | P124: =(K124-G124)/ABS(G124) -> 0.14866306 | Q124: =(L124-H124)/ABS(H124) -> -0.22282428
A125: FRT | B125: Bán lẻ FPT | C125: HOSE | D125: 9041655206754 | E125: 9239510142802 | F125: 10375679031706 | G125: 11447648149922 | H125: 11669845454347 | I125: 11390344662987 | J125: 13109916760952 | K125: 14912761566482 | L125: =VLOOKUP(A125,Sheet2!$A$1:$E$2000,5,FALSE) -> 15116909090730 | M125: =(H125-D125)/ABS(D125) -> 0.29067579 | N125: =(I125-E125)/ABS(E125) -> 0.23278664 | O125: =(J125-F125)/ABS(F125) -> 0.26352374 | P125: =(K125-G125)/ABS(G125) -> 0.30269217 | Q125: =(L125-H125)/ABS(H125) -> 0.29538212
A126: FTS | B126: Chứng khoán FPT | C126: HOSE | D126: 299216562768 | E126: 305238766482 | F126: 224627337542 | G126: 318665864268 | H126: 312063617998 | I126: 239142567744 | J126: 284407920603 | K126: 370193994657 | L126: =VLOOKUP(A126,Sheet2!$A$1:$E$2000,5,FALSE) -> 378398564136 | M126: =(H126-D126)/ABS(D126) -> 0.042935642 | N126: =(I126-E126)/ABS(E126) -> -0.21653933 | O126: =(J126-F126)/ABS(F126) -> 0.26613227 | P126: =(K126-G126)/ABS(G126) -> 0.16169956 | Q126: =(L126-H126)/ABS(H126) -> 0.21256866
A127: FUCTVGF3 | B127: Quỹ Đầu tư Tăng trưởng Thiên Việt 3 | C127: HOSE | L127: =VLOOKUP(A127,Sheet2!$A$1:$E$2000,5,FALSE) -> 0 | M127: =(H127-D127)/ABS(D127) -> #DIV/0! | N127: =(I127-E127)/ABS(E127) -> #DIV/0! | O127: =(J127-F127)/ABS(F127) -> #DIV/0! | P127: =(K127-G127)/ABS(G127) -> #DIV/0! | Q127: =(L127-H127)/ABS(H127) -> #DIV/0!
A128: FUCTVGF4 | B128: Quỹ Đầu tư Tăng trưởng Thiên Việt 4 | C128: HOSE | L128: =VLOOKUP(A128,Sheet2!$A$1:$E$2000,5,FALSE) -> 0 | M128: =(H128-D128)/ABS(D128) -> #DIV/0! | N128: =(I128-E128)/ABS(E128) -> #DIV/0! | O128: =(J128-F128)/ABS(F128) -> #DIV/0! | P128: =(K128-G128)/ABS(G128) -> #DIV/0! | Q128: =(L128-H128)/ABS(H128) -> #DIV/0!
A129: FUCTVGF5 | B129: Quỹ Đầu tư Tăng trưởng Thiên Việt 5 | C129: HOSE | L129: =VLOOKUP(A129,Sheet2!$A$1:$E$2000,5,FALSE) -> 0 | M129: =(H129-D129)/ABS(D129) -> #DIV/0! | N129: =(I129-E129)/ABS(E129) -> #DIV/0! | O129: =(J129-F129)/ABS(F129) -> #DIV/0! | P129: =(K129-G129)/ABS(G129) -> #DIV/0! | Q129: =(L129-H129)/ABS(H129) -> #DIV/0!
A130: FUCVREIT | B130: Quỹ Đầu tư BĐS Techcom Việt Nam | C130: HOSE | L130: =VLOOKUP(A130,Sheet2!$A$1:$E$2000,5,FALSE) -> 0 | M130: =(H130-D130)/ABS(D130) -> #DIV/0! | N130: =(I130-E130)/ABS(E130) -> #DIV/0! | O130: =(J130-F130)/ABS(F130) -> #DIV/0! | P130: =(K130-G130)/ABS(G130) -> #DIV/0! | Q130: =(L130-H130)/ABS(H130) -> #DIV/0!
A131: FUEABVND | B131: Quỹ ETF ABFVN DIAMOND | C131: HOSE | L131: =VLOOKUP(A131,Sheet2!$A$1:$E$2000,5,FALSE) -> 0 | M131: =(H131-D131)/ABS(D131) -> #DIV/0! | N131: =(I131-E131)/ABS(E131) -> #DIV/0! | O131: =(J131-F131)/ABS(F131) -> #DIV/0! | P131: =(K131-G131)/ABS(G131) -> #DIV/0! | Q131: =(L131-H131)/ABS(H131) -> #DIV/0!
A132: FUEBFVND | B132: Quỹ ETF BVFVN DIAMOND | C132: HOSE | L132: =VLOOKUP(A132,Sheet2!$A$1:$E$2000,5,FALSE) -> 0 | M132: =(H132-D132)/ABS(D132) -> #DIV/0! | N132: =(I132-E132)/ABS(E132) -> #DIV/0! | O132: =(J132-F132)/ABS(F132) -> #DIV/0! | P132: =(K132-G132)/ABS(G132) -> #DIV/0! | Q132: =(L132-H132)/ABS(H132) -> #DIV/0!
A133: FUEDCMID | B133: Quỹ ETF DCVFMVNMIDCAP | C133: HOSE | L133: =VLOOKUP(A133,Sheet2!$A$1:$E$2000,5,FALSE) -> 0 | M133: =(H133-D133)/ABS(D133) -> #DIV/0! | N133: =(I133-E133)/ABS(E133) -> #DIV/0! | O133: =(J133-F133)/ABS(F133) -> #DIV/0! | P133: =(K133-G133)/ABS(G133) -> #DIV/0! | Q133: =(L133-H133)/ABS(H133) -> #DIV/0!
A134: FUEFCV50 | B134: Quỹ ETF FPT CAPITAL VNX50 | C134: HOSE | L134: =VLOOKUP(A134,Sheet2!$A$1:$E$2000,5,FALSE) -> 0 | M134: =(H134-D134)/ABS(D134) -> #DIV/0! | N134: =(I134-E134)/ABS(E134) -> #DIV/0! | O134: =(J134-F134)/ABS(F134) -> #DIV/0! | P134: =(K134-G134)/ABS(G134) -> #DIV/0! | Q134: =(L134-H134)/ABS(H134) -> #DIV/0!
A135: FUEIP100 | B135: Quỹ ETF IPAAM VN100 | C135: HOSE | L135: =VLOOKUP(A135,Sheet2!$A$1:$E$2000,5,FALSE) -> 0 | M135: =(H135-D135)/ABS(D135) -> #DIV/0! | N135: =(I135-E135)/ABS(E135) -> #DIV/0! | O135: =(J135-F135)/ABS(F135) -> #DIV/0! | P135: =(K135-G135)/ABS(G135) -> #DIV/0! | Q135: =(L135-H135)/ABS(H135) -> #DIV/0!
A136: FUEKIV30 | B136: KIM GROWTH VN30 ETF | C136: HOSE | L136: =VLOOKUP(A136,Sheet2!$A$1:$E$2000,5,FALSE) -> 0 | M136: =(H136-D136)/ABS(D136) -> #DIV/0! | N136: =(I136-E136)/ABS(E136) -> #DIV/0! | O136: =(J136-F136)/ABS(F136) -> #DIV/0! | P136: =(K136-G136)/ABS(G136) -> #DIV/0! | Q136: =(L136-H136)/ABS(H136) -> #DIV/0!
A137: FUEKIVFS | B137: KIM GROWTH VNFINSELECT ETF | C137: HOSE | L137: =VLOOKUP(A137,Sheet2!$A$1:$E$2000,5,FALSE) -> 0 | M137: =(H137-D137)/ABS(D137) -> #DIV/0! | N137: =(I137-E137)/ABS(E137) -> #DIV/0! | O137: =(J137-F137)/ABS(F137) -> #DIV/0! | P137: =(K137-G137)/ABS(G137) -> #DIV/0! | Q137: =(L137-H137)/ABS(H137) -> #DIV/0!
A138: FUEKIVND | B138: Quỹ ETF KIM GROWTH VN DIAMOND | C138: HOSE | L138: =VLOOKUP(A138,Sheet2!$A$1:$E$2000,5,FALSE) -> 0 | M138: =(H138-D138)/ABS(D138) -> #DIV/0! | N138: =(I138-E138)/ABS(E138) -> #DIV/0! | O138: =(J138-F138)/ABS(F138) -> #DIV/0! | P138: =(K138-G138)/ABS(G138) -> #DIV/0! | Q138: =(L138-H138)/ABS(H138) -> #DIV/0!
... A147: FUEVN100 | B147: Quỹ ETF VINACAPITAL VN100 | C147: HOSE | L147: =VLOOKUP(A147,Sheet2!$A$1:$E$2000,5,FALSE) -> 0 | M147: =(H147-D147)/ABS(D147) -> #DIV/0! | N147: =(I147-E147)/ABS(E147) -> #DIV/0! | O147: =(J147-F147)/ABS(F147) -> #DIV/0! | P147: =(K147-G147)/ABS(G147) -> #DIV/0! | Q147: =(L147-H147)/ABS(H147) -> #DIV/0!
A148: GAS | B148: PV Gas | C148: HOSE | D148: 23314997603580 | E148: 30052003597472 | F148: 25252008025471 | G148: 24945117336365 | H148: 25675428574505 | I148: 30080421244663 | J148: 35690134900226 | K148: 43683070609001 | L148: =VLOOKUP(A148,Sheet2!$A$1:$E$2000,5,FALSE) -> 38019609031268 | M148: =(H148-D148)/ABS(D148) -> 0.10124088 | N148: =(I148-E148)/ABS(E148) -> 0.00094561573 | O148: =(J148-F148)/ABS(F148) -> 0.41335829 | P148: =(K148-G148)/ABS(G148) -> 0.75116717 | Q148: =(L148-H148)/ABS(H148) -> 0.48077797
A149: GDT | B149: Gỗ Đức Thành | C149: HOSE | D149: 68682470722 | E149: 88597102839 | F149: 91702323476 | G149: 86527924722 | H149: 70550237911 | I149: 70513883225 | J149: 79672878894 | K149: 112094285055 | L149: =VLOOKUP(A149,Sheet2!$A$1:$E$2000,5,FALSE) -> 67455138294 | M149: =(H149-D149)/ABS(D149) -> 0.027194234 | N149: =(I149-E149)/ABS(E149) -> -0.20410622 | O149: =(J149-F149)/ABS(F149) -> -0.13117928 | P149: =(K149-G149)/ABS(G149) -> 0.29546947 | Q149: =(L149-H149)/ABS(H149) -> -0.04387086
A150: GEE | B150: Thiết bị điện GELEX | C150: HOSE | D150: 3720144773884 | E150: 5309989651609 | F150: 5618728185501 | G150: 6480759208333 | H150: 5280925242420 | I150: 6509730778000 | J150: 6444099274469 | K150: 7228395245265 | L150: =VLOOKUP(A150,Sheet2!$A$1:$E$2000,5,FALSE) -> 7097351777384 | M150: =(H150-D150)/ABS(D150) -> 0.41954831 | N150: =(I150-E150)/ABS(E150) -> 0.22594039 | O150: =(J150-F150)/ABS(F150) -> 0.14689643 | P150: =(K150-G150)/ABS(G150) -> 0.11536242 | Q150: =(L150-H150)/ABS(H150) -> 0.3439599
A151: GEG | B151: Điện Gia Lai | C151: HOSE | D151: 739214916619 | E151: 487632741698 | F151: 543139233330 | G151: 555327531103 | H151: 1112755859981 | I151: 624339137173 | J151: 671328091438 | K151: 590444253989 | L151: =VLOOKUP(A151,Sheet2!$A$1:$E$2000,5,FALSE) -> 767379199934 | M151: =(H151-D151)/ABS(D151) -> 0.50532117 | N151: =(I151-E151)/ABS(E151) -> 0.28034704 | O151: =(J151-F151)/ABS(F151) -> 0.23601473 | P151: =(K151-G151)/ABS(G151) -> 0.063236056 | Q151: =(L151-H151)/ABS(H151) -> -0.31037955
A152: GEL | B152: Hạ tầng GELEX | C152: HOSE | H152: 2984702006176 | I152: 3505305829202 | J152: 3508554253871 | K152: 4303197395454 | L152: =VLOOKUP(A152,Sheet2!$A$1:$E$2000,5,FALSE) -> 3536055100097 | M152: =(H152-D152)/ABS(D152) -> #DIV/0! | N152: =(I152-E152)/ABS(E152) -> #DIV/0! | O152: =(J152-F152)/ABS(F152) -> #DIV/0! | P152: =(K152-G152)/ABS(G152) -> #DIV/0! | Q152: =(L152-H152)/ABS(H152) -> 0.18472635
A153: GEX | B153: Tập đoàn Gelex | C153: HOSE | D153: 6660001228800 | E153: 8248282332683 | F153: 8708567347749 | G153: 10135454503741 | H153: 7916356896711 | I153: 10119234846647 | J153: 9841133304554 | K153: 11635803103041 | L153: =VLOOKUP(A153,Sheet2!$A$1:$E$2000,5,FALSE) -> 10721709075577 | M153: =(H153-D153)/ABS(D153) -> 0.18864196 | N153: =(I153-E153)/ABS(E153) -> 0.22682935 | O153: =(J153-F153)/ABS(F153) -> 0.13005193 | P153: =(K153-G153)/ABS(G153) -> 0.14802973 | Q153: =(L153-H153)/ABS(H153) -> 0.35437414
A154: GHC | B154: Thủy điện Gia Lai | C154: HOSE | D154: 73856610143 | E154: 65970868488 | F154: 84065238401 | G154: 92732365803 | H154: 69327168595 | I154: 74945619564 | J154: 91450272999 | K154: 98028460342 | L154: =VLOOKUP(A154,Sheet2!$A$1:$E$2000,5,FALSE) -> 86791237783 | M154: =(H154-D154)/ABS(D154) -> -0.061327504 | N154: =(I154-E154)/ABS(E154) -> 0.13604112 | O154: =(J154-F154)/ABS(F154) -> 0.087848851 | P154: =(K154-G154)/ABS(G154) -> 0.057111608 | Q154: =(L154-H154)/ABS(H154) -> 0.25190801
A155: GIL | B155: XNK Bình Thạnh | C155: HOSE | D155: 221496606406 | E155: 145072453584 | F155: 152587153072 | G155: 191736082331 | H155: 126021139906 | I155: 128933218150 | J155: 198146057575 | K155: 260520572457 | L155: =VLOOKUP(A155,Sheet2!$A$1:$E$2000,5,FALSE) -> 197370920315 | M155: =(H155-D155)/ABS(D155) -> -0.43104708 | N155: =(I155-E155)/ABS(E155) -> -0.11124948 | O155: =(J155-F155)/ABS(F155) -> 0.29857628 | P155: =(K155-G155)/ABS(G155) -> 0.35874567 | Q155: =(L155-H155)/ABS(H155) -> 0.56617311
A156: GMD | B156: Gemadept | C156: HOSE | D156: 1005539540911 | E156: 1150898425696 | F156: 1264114623523 | G156: 1411472208831 | H156: 1276946137045 | I156: 1493731602173 | J156: 1560495941737 | K156: 1624851616060 | L156: =VLOOKUP(A156,Sheet2!$A$1:$E$2000,5,FALSE) -> 1452406917275 | M156: =(H156-D156)/ABS(D156) -> 0.26991141 | N156: =(I156-E156)/ABS(E156) -> 0.29788309 | O156: =(J156-F156)/ABS(F156) -> 0.23445763 | P156: =(K156-G156)/ABS(G156) -> 0.15117507 | Q156: =(L156-H156)/ABS(H156) -> 0.13740656
A157: GMH | B157: Minh Hưng Quảng Trị | C157: HOSE | D157: 15141382148 | E157: 24102885374 | F157: 26974098131 | G157: 21838736475 | H157: 20347149381 | I157: 37377853545 | J157: 25102556586 | K157: 20749784431 | L157: =VLOOKUP(A157,Sheet2!$A$1:$E$2000,5,FALSE) -> 13336516157 | M157: =(H157-D157)/ABS(D157) -> 0.34381057 | N157: =(I157-E157)/ABS(E157) -> 0.55076261 | O157: =(J157-F157)/ABS(F157) -> -0.069382915 | P157: =(K157-G157)/ABS(G157) -> -0.049863326 | Q157: =(L157-H157)/ABS(H157) -> -0.34455113
A158: GSP | B158: Vận tải Sản phẩm Khí Quốc tế | C158: HOSE | D158: 435923281107 | E158: 639474669222 | F158: 606384877549 | G158: 565220808852 | H158: 474029197568 | I158: 1475448111687 | J158: 837840581961 | K158: 797460128443 | L158: =VLOOKUP(A158,Sheet2!$A$1:$E$2000,5,FALSE) -> 713546906839 | M158: =(H158-D158)/ABS(D158) -> 0.087414272 | N158: =(I158-E158)/ABS(E158) -> 1.3072816 | O158: =(J158-F158)/ABS(F158) -> 0.38169769 | P158: =(K158-G158)/ABS(G158) -> 0.41088247 | Q158: =(L158-H158)/ABS(H158) -> 0.5052805
A159: GTA | B159: Gỗ Thuận An | C159: HOSE | D159: 66195403173 | E159: 64241863613 | F159: 71600808184 | G159: 59355609871 | H159: 62869276369 | I159: 49894720625 | J159: 79158726059 | K159: 63176980963 | L159: =VLOOKUP(A159,Sheet2!$A$1:$E$2000,5,FALSE) -> 49264468834 | M159: =(H159-D159)/ABS(D159) -> -0.050247096 | N159: =(I159-E159)/ABS(E159) -> -0.22333012 | O159: =(J159-F159)/ABS(F159) -> 0.10555632 | P159: =(K159-G159)/ABS(G159) -> 0.064380959 | Q159: =(L159-H159)/ABS(H159) -> -0.21639835
A160: GVR | B160: Tập đoàn CN Cao su VN | C160: HOSE | D160: 4585365205639 | E160: 4652604913441 | F160: 7715773553233 | G160: 9288200442532 | H160: 5676961736513 | I160: 5890007609737 | J160: 9294402677445 | K160: 8644463568626 | L160: =VLOOKUP(A160,Sheet2!$A$1:$E$2000,5,FALSE) -> 8845157076569 | M160: =(H160-D160)/ABS(D160) -> 0.23806098 | N160: =(I160-E160)/ABS(E160) -> 0.26595912 | O160: =(J160-F160)/ABS(F160) -> 0.20459765 | P160: =(K160-G160)/ABS(G160) -> -0.069306953 | Q160: =(L160-H160)/ABS(H160) -> 0.55807939
A161: HAG | B161: Hoàng Anh Gia Lai | C161: HOSE | D161: 1240937790000 | E161: 1521082221000 | F161: 1431701777000 | G161: 1589328214000 | H161: 1379756124000 | I161: 2327420395000 | J161: 1895404577000 | K161: 1829693146000 | L161: =VLOOKUP(A161,Sheet2!$A$1:$E$2000,5,FALSE) -> 1784072297000 | M161: =(H161-D161)/ABS(D161) -> 0.11186567 | N161: =(I161-E161)/ABS(E161) -> 0.53010821 | O161: =(J161-F161)/ABS(F161) -> 0.32388225 | P161: =(K161-G161)/ABS(G161) -> 0.15123681 | Q161: =(L161-H161)/ABS(H161) -> 0.29303452
...

Sheet Sheet2
A1: AAA | B1: An Phát Bioplastics | C1: HOSE | E1: 2224065397921
A2: AAM | B2: Thủy sản Mekong | C2: HOSE | E2: 33444004710
A3: AAT | B3: Tập đoàn Tiên Sơn Thanh Hóa | C3: HOSE | E3: 235047541189
A4: ABR | B4: Đầu tư Nhãn Hiệu Việt | C4: HOSE | E4: 6335090877
A5: ABS | B5: DV Nông nghiệp Bình Thuận | C5: HOSE | E5: 42956175499
A6: ABT | B6: Thủy sản Bến Tre | C6: HOSE | E6: 187835693906
A7: ACB | B7: ACB | C7: HOSE
A8: ACC | B8: Đầu tư và XD Bình Dương ACC | C8: HOSE | E8: 151639959465
A9: ACG | B9: Gỗ An Cường | C9: HOSE | E9: 1109927947175
A10: ACL | B10: Thủy sản CL An Giang | C10: HOSE | E10: 427960489100
A11: ADG | B11: Clever Group | C11: HOSE
A12: ADP | B12: Sơn Á Đông | C12: HOSE | E12: 154364991714
A13: ADS | B13: Dệt sợi DAMSAN | C13: HOSE | E13: 408191712082
A14: AFX | B14: XNK Nông sản Thực phẩm An Giang | C14: HOSE | E14: 884015930897
A15: AGG | B15: Bất động sản An Gia | C15: HOSE | E15: 67263896896
A16: AGR | B16: Agriseco | C16: HOSE | E16: 145316560382
A17: ANT | B17: Rau quả thực phẩm An Giang | C17: HOSE
A18: ANV | B18: Thủy sản Nam Việt | C18: HOSE | E18: 1841296117934
A19: APG | B19: Chứng khoán APG | C19: HOSE | E19: 84974653113
A20: APH | B20: Tập đoàn An Phát Holdings | C20: HOSE | E20: 2224721494680
A21: ASG | B21: Tập đoàn ASG | C21: HOSE | E21: 661404788597
A22: ASM | B22: Tập đoàn Sao Mai | C22: HOSE | E22: 2469598309439
A23: ASP | B23: Dầu khí An Pha | C23: HOSE | E23: 794013619169
A24: AST | B24: Dịch vụ Hàng không Taseco | C24: HOSE | E24: 555973947060
A25: ATP | B25: T.Mại và DV An Thành | C25: HOSE
A26: BAF | B26: Nông nghiệp BAF Việt Nam | C26: HOSE | E26: 1762207980539
A27: BCE | B27: XD và GT Bình Dương | C27: HOSE | E27: 63015458144
A28: BCG | B28: Bamboo Capital | C28: HOSE
A29: BCM | B29: Becamex Group | C29: HOSE | E29: 1104960466553
A30: BFC | B30: Phân bón Bình Điền | C30: HOSE | E30: 3345445434562
A31: BHN | B31: HABECO | C31: HOSE | E31: 1929641088961
A32: BIC | B32: Bảo hiểm BIDV | C32: HOSE | E32: 1137200217440
A33: BID | B33: BIDV | C33: HOSE
A34: BKG | B34: Đầu tư BKG Việt Nam | C34: HOSE | E34: 46725536629
A35: BMC | B35: Khoáng sản Bình Định | C35: HOSE | E35: 23608555252
A36: BMI | B36: Bảo hiểm Bảo Minh | C36: HOSE | E36: 1360420068969
A37: BMP | B37: Nhựa Bình Minh | C37: HOSE | E37: 1457310965938
A38: BRC | B38: Cao su Bến Thành | C38: HOSE | E38: 95250799894
A39: BSI | B39: Chứng khoán BIDV | C39: HOSE | E39: 697140773775
A40: BSR | B40: Lọc Hóa dầu Bình Sơn | C40: HOSE | E40: 45919538260329
A41: BTP | B41: Nhiệt điện Bà Rịa | C41: HOSE | E41: 54780672813
A42: BTT | B42: TM - DV Bến Thành | C42: HOSE | E42: 61327349085
A43: BVH | B43: Tập đoàn Bảo Việt | C43: HOSE | E43: 9819434237555
A44: BWE | B44: Nước - Môi trường Bình Dương | C44: HOSE | E44: 1034748443534
A45: C32 | B45: Đầu tư và Xây dựng 3-2 | C45: HOSE
A46: C47 | B46: Xây dựng 47 | C46: HOSE | E46: 435321320132
A47: CCC | B47: Xây Dựng CDC | C47: HOSE | E47: 703579864941
A48: CCI | B48: CIDICO | C48: HOSE | E48: 102047045541
A49: CCL | B49: ĐT & PT Đô thị Dầu khí Cửu Long | C49: HOSE | E49: 69304635981
A50: CDC | B50: Chương Dương Corp | C50: HOSE | E50: 216934296516
A51: CHP | B51: Thủy điện Miền Trung | C51: HOSE | E51: 198502925399
A52: CIG | B52: Xây dựng COMA 18 | C52: HOSE | E52: 17326104407
A53: CII | B53: Hạ tầng Kỹ thuật TP.HCM | C53: HOSE | E53: 833465515854
A54: CKG | B54: Tập đoàn CIC | C54: HOSE | E54: 82758259768
A55: CLC | B55: Thuốc lá Cát Lợi | C55: HOSE | E55: 1033859386838
A56: CLL | B56: Cảng Cát Lái | C56: HOSE | E56: 88104165859
A57: CLW | B57: Cấp nước Chợ Lớn | C57: HOSE | E57: 305261804811
... A69: CTF | B69: City Auto | C69: HOSE | E69: 1914554329693
A70: CTG | B70: VietinBank | C70: HOSE
A71: CTI | B71: Cường Thuận IDICO | C71: HOSE | E71: 358198735630
A72: CTR | B72: Công trình Viettel | C72: HOSE | E72: 3804825619753
A73: CTS | B73: Chứng khoán Vietinbank | C73: HOSE | E73: 351925777950
A74: CVT | B74: CMC JSC | C74: HOSE | E74: 595276508359
A75: D2D | B75: Phát triển Đô thị số 2 | C75: HOSE | E75: 44125900320
A76: DAH | B76: Tập đoàn Khách sạn Đông Á | C76: HOSE | E76: 9803544980
A77: DAT | B77: ĐT Du lịch và PT Thủy sản | C77: HOSE | E77: 641935879522
A78: DBC | B78: Tập đoàn DABACO | C78: HOSE | E78: 4124177863856
A79: DBD | B79: Dược - TB Y tế Bình Định | C79: HOSE | E79: 448086937367
A80: DBT | B80: Dược phẩm Bến Tre | C80: HOSE | E80: 189952055785
A81: DC4 | B81: Dicera Holdings | C81: HOSE | E81: 173489614678
A82: DCL | B82: Dược phẩm Cửu Long | C82: HOSE | E82: 324121488178
... A109: DXV | B109: Vật liệu Xây dựng Đà Nẵng | C109: HOSE | E109: 52437090160
A110: E1VFVN30 | B110: Quỹ ETF DCVFMVN30 | C110: HOSE
A111: EIB | B111: Eximbank | C111: HOSE
A112: ELC | B112: ELCOM | C112: HOSE | E112: 114302504502
A113: EVE | B113: Everpia | C113: HOSE | E113: 151685804553
A114: EVF | B114: Tài chính Tổng hợp Điện lực | C114: HOSE
A115: EVG | B115: Tập đoàn Everland | C115: HOSE | E115: 323088889571
A116: FCM | B116: Bê tông Phan Vũ Hà Nam | C116: HOSE | E116: 121936472256
A117: FCN | B117: FECON CORP | C117: HOSE | E117: 1302197745510
A118: FDC | B118: FIDECO | C118: HOSE | E118: 17996754671
A119: FIR | B119: Địa ốc First Real | C119: HOSE
A120: FIT | B120: Tập đoàn F.I.T | C120: HOSE
A121: FMC | B121: Thực phẩm Sao Ta | C121: HOSE | E121: 1398523350604
A122: FPT | B122: FPT Corp | C122: HOSE | E122: 12479997206775
A123: FRT | B123: Bán lẻ FPT | C123: HOSE | E123: 15116909090730
A124: FTS | B124: Chứng khoán FPT | C124: HOSE | E124: 378398564136
A125: FUCTVGF3 | B125: Quỹ Đầu tư Tăng trưởng Thiên Việt 3 | C125: HOSE
A126: FUCTVGF4 | B126: Quỹ Đầu tư Tăng trưởng Thiên Việt 4 | C126: HOSE
A127: FUCTVGF5 | B127: Quỹ Đầu tư Tăng trưởng Thiên Việt 5 | C127: HOSE
A128: FUCVREIT | B128: Quỹ Đầu tư BĐS Techcom Việt Nam | C128: HOSE
A129: FUEABVND | B129: Quỹ ETF ABFVN DIAMOND | C129: HOSE
A130: FUEBFVND | B130: Quỹ ETF BVFVN DIAMOND | C130: HOSE
A131: FUEDCMID | B131: Quỹ ETF DCVFMVNMIDCAP | C131: HOSE
A132: FUEFCV50 | B132: Quỹ ETF FPT CAPITAL VNX50 | C132: HOSE
A133: FUEIP100 | B133: Quỹ ETF IPAAM VN100 | C133: HOSE
A134: FUEKIV30 | B134: KIM GROWTH VN30 ETF | C134: HOSE
A135: FUEKIVFS | B135: KIM GROWTH VNFINSELECT ETF | C135: HOSE
A136: FUEKIVND | B136: Quỹ ETF KIM GROWTH VN DIAMOND | C136: HOSE
... A145: FUEVN100 | B145: Quỹ ETF VINACAPITAL VN100 | C145: HOSE
...

Sheet LNST
A1: 1 | B1: 2 | C1: 3 | D1: 4 | E1: 5 | F1: 6 | G1: 7 | H1: 8 | I1: 9 | J1: 10 | K1: 11 | L1: 12 | M1: 13 | N1: 14 | O1: 15 | P1: 16 | Q1: 17 | R1: 18 | S1: 19 | T1: 20
A2: Mã CP | B2: Tên | C2: Sàn | D2: ='Doanh thu'!D2 -> Q1.24 | E2: ='Doanh thu'!E2 -> Q2.24 | F2: ='Doanh thu'!F2 -> Q3.24 | G2: ='Doanh thu'!G2 -> Q4.24 | H2: ='Doanh thu'!H2 -> Q1.25 | I2: ='Doanh thu'!I2 -> Q2.25 | J2: ='Doanh thu'!J2 -> Q3.25 | K2: ='Doanh thu'!K2 -> Q4.25 | L2: ='Doanh thu'!L2 -> Q1.26 | M2: Tăng trưởng 5 | N2: Tăng trưởng 1 | O2: Tăng trưởng 2 | P2: Tăng trưởng 3 | Q2: Tăng trưởng 4 | R2: Luỹ kế 3 quý | S2: Lũy kế 4 quý | T2: 2025
A3: AAA | B3: An Phát Bioplastics | C3: HOSE | D3: 134706559842 | E3: 135887872408 | F3: 21799597923 | G3: 76186464918 | H3: 45239813399 | I3: 131689030063 | J3: 117554438469 | K3: 78429315431 | L3: =VLOOKUP(A3,Sheet1!$A$1:$E$2000,5,FALSE) -> 153668061513 | M3: =(H3-D3)/ABS(D3) -> -0.66416028 | N3: =(I3-E3)/ABS(E3) -> -0.030899316 | O3: =(J3-F3)/ABS(F3) -> 4.3925049 | P3: =(K3-G3)/ABS(G3) -> 0.029438963 | Q3: =(L3-H3)/ABS(H3) -> 2.3967439 | R3: =(SUM(J3:L3)-SUM(F3:H3))/ABS(SUM(F3:H3)) -> 1.4412615 | S3: =SUM(I3:L3)/SUM(E3:H3)-1 -> 0.72453291 | T3: =SUM(I3:L3) -> 481340845476
A4: AAM | B4: Thủy sản Mekong | C4: HOSE | D4: -2071987027 | E4: -1615877371 | F4: -1272980613 | G4: -1334838721 | H4: 1208511116 | I4: 1128258987 | J4: 399288553 | K4: -889306322 | L4: =VLOOKUP(A4,Sheet1!$A$1:$E$2000,5,FALSE) -> 2387603772 | M4: =(H4-D4)/ABS(D4) -> 1.5832619 | N4: =(I4-E4)/ABS(E4) -> 1.6982331 | O4: =(J4-F4)/ABS(F4) -> 1.3136643 | P4: =(K4-G4)/ABS(G4) -> 0.33377246 | Q4: =(L4-H4)/ABS(H4) -> 0.97565727 | R4: =(SUM(J4:L4)-SUM(F4:H4))/ABS(SUM(F4:H4)) -> 2.3560887 | S4: =SUM(I4:L4)/SUM(E4:H4)-1 -> -2.0035352 | T4: =SUM(I4:L4) -> 3025844990
A5: AAT | B5: Tập đoàn Tiên Sơn Thanh Hóa | C5: HOSE | D5: 2124587103 | E5: 1384750361 | F5: 2383114722 | G5: -17222060883 | H5: 9554449402 | I5: 5124448103 | J5: 8545005597 | K5: 499336750 | L5: =VLOOKUP(A5,Sheet1!$A$1:$E$2000,5,FALSE) -> 490938501 | M5: =(H5-D5)/ABS(D5) -> 3.4970853 | N5: =(I5-E5)/ABS(E5) -> 2.7006295 | O5: =(J5-F5)/ABS(F5) -> 2.5856459 | P5: =(K5-G5)/ABS(G5) -> 1.028994 | Q5: =(L5-H5)/ABS(H5) -> -0.94861677 | R5: =(SUM(J5:L5)-SUM(F5:H5))/ABS(SUM(F5:H5)) -> 2.8043877 | S5: =SUM(I5:L5)/SUM(E5:H5)-1 -> -4.7591493 | T5: =SUM(I5:L5) -> 14659728951
A6: ABR | B6: Đầu tư Nhãn Hiệu Việt | C6: HOSE | D6: 4769015353 | E6: 5469636513 | F6: 3094015192 | G6: 6405236123 | H6: 3676868740 | I6: 3321543329 | J6: 2497751218 | K6: 5404974481 | L6: =VLOOKUP(A6,Sheet1!$A$1:$E$2000,5,FALSE) -> 2370604829 | M6: =(H6-D6)/ABS(D6) -> -0.22900883 | N6: =(I6-E6)/ABS(E6) -> -0.39273052 | O6: =(J6-F6)/ABS(F6) -> -0.19271527 | P6: =(K6-G6)/ABS(G6) -> -0.15616312 | Q6: =(L6-H6)/ABS(H6) -> -0.35526531 | R6: =(SUM(J6:L6)-SUM(F6:H6))/ABS(SUM(F6:H6)) -> -0.22030685 | S6: =SUM(I6:L6)/SUM(E6:H6)-1 -> -0.27088644 | T6: =SUM(I6:L6) -> 13594873857
A7: ABS | B7: DV Nông nghiệp Bình Thuận | C7: HOSE | D7: 3460566330 | E7: 3388473406 | F7: 259712297 | G7: -4549350892 | H7: -1702820627 | I7: -293175539707 | J7: 1663531866 | K7: -218034521633 | L7: =VLOOKUP(A7,Sheet1!$A$1:$E$2000,5,FALSE) -> -1741076711 | M7: =(H7-D7)/ABS(D7) -> -1.4920641 | N7: =(I7-E7)/ABS(E7) -> -87.521423 | O7: =(J7-F7)/ABS(F7) -> 5.4052873 | P7: =(K7-G7)/ABS(G7) -> -46.926512 | Q7: =(L7-H7)/ABS(H7) -> -0.022466303 | R7: =(SUM(J7:L7)-SUM(F7:H7))/ABS(SUM(F7:H7)) -> -35.397756 | S7: =SUM(I7:L7)/SUM(E7:H7)-1 -> 195.34808 | T7: =SUM(I7:L7) -> -511287606185
A8: ABT | B8: Thủy sản Bến Tre | C8: HOSE | D8: 11171311500 | E8: 33723859148 | F8: 18494999690 | G8: 38098722619 | H8: 22142257722 | I8: 61695732808 | J8: 40250553945 | K8: 33885771947 | L8: =VLOOKUP(A8,Sheet1!$A$1:$E$2000,5,FALSE) -> 22273623047 | M8: =(H8-D8)/ABS(D8) -> 0.9820643 | N8: =(I8-E8)/ABS(E8) -> 0.82943869 | O8: =(J8-F8)/ABS(F8) -> 1.1762938 | P8: =(K8-G8)/ABS(G8) -> -0.11057984 | Q8: =(L8-H8)/ABS(H8) -> 0.0059327882 | R8: =(SUM(J8:L8)-SUM(F8:H8))/ABS(SUM(F8:H8)) -> 0.22447131 | S8: =SUM(I8:L8)/SUM(E8:H8)-1 -> 0.40588572 | T8: =SUM(I8:L8) -> 158105681747
A9: ACB | B9: ACB | C9: HOSE | D9: 3905419000000 | E9: 4468590000000 | F9: 3870395000000 | G9: 4545364000000 | H9: 3678266000000 | I9: 4881159000000 | J9: 4280589000000 | K9: 2784685000000 | L9: =VLOOKUP(A9,Sheet1!$A$1:$E$2000,5,FALSE) -> 4320388000000 | M9: =(H9-D9)/ABS(D9) -> -0.058163541 | N9: =(I9-E9)/ABS(E9) -> 0.092326439 | O9: =(J9-F9)/ABS(F9) -> 0.10598246 | P9: =(K9-G9)/ABS(G9) -> -0.3873571 | Q9: =(L9-H9)/ABS(H9) -> 0.17457193 | R9: =(SUM(J9:L9)-SUM(F9:H9))/ABS(SUM(F9:H9)) -> -0.058571319 | S9: =SUM(I9:L9)/SUM(E9:H9)-1 -> -0.017859136 | T9: =SUM(I9:L9) -> 16266821000000
A10: ACC | B10: Đầu tư và XD Bình Dương ACC | C10: HOSE | D10: 10263379944 | E10: 7509069684 | F10: 19862872999 | G10: 14654868394 | H10: 8923367707 | I10: 8189276245 | J10: 24554035346 | K10: 10389524464 | L10: =VLOOKUP(A10,Sheet1!$A$1:$E$2000,5,FALSE) -> 5708706572 | M10: =(H10-D10)/ABS(D10) -> -0.13056247 | N10: =(I10-E10)/ABS(E10) -> 0.090584665 | O10: =(J10-F10)/ABS(F10) -> 0.23617743 | P10: =(K10-G10)/ABS(G10) -> -0.29105304 | Q10: =(L10-H10)/ABS(H10) -> -0.36025201 | R10: =(SUM(J10:L10)-SUM(F10:H10))/ABS(SUM(F10:H10)) -> -0.064198239 | S10: =SUM(I10:L10)/SUM(E10:H10)-1 -> -0.041386237 | T10: =SUM(I10:L10) -> 48841542627
A11: ACG | B11: Gỗ An Cường | C11: HOSE | D11: 81419524081 | E11: 118128861982 | F11: 130420988660 | G11: 90002611157 | H11: 85008966539 | I11: 137937351417 | J11: 135353838052 | K11: 145688868370 | L11: =VLOOKUP(A11,Sheet1!$A$1:$E$2000,5,FALSE) -> 111902787167 | M11: =(H11-D11)/ABS(D11) -> 0.044085771 | N11: =(I11-E11)/ABS(E11) -> 0.16768543 | O11: =(J11-F11)/ABS(F11) -> 0.037822512 | P11: =(K11-G11)/ABS(G11) -> 0.61871824 | Q11: =(L11-H11)/ABS(H11) -> 0.31636452 | R11: =(SUM(J11:L11)-SUM(F11:H11))/ABS(SUM(F11:H11)) -> 0.28652127 | S11: =SUM(I11:L11)/SUM(E11:H11)-1 -> 0.25337864 | T11: =SUM(I11:L11) -> 530882845006
A12: ACL | B12: Thủy sản CL An Giang | C12: HOSE | D12: 2274571084 | E12: 2780676755 | F12: 3353366474 | G12: 2356628868 | H12: 2590594007 | I12: 6466449988 | J12: 13967390002 | K12: 11311980638 | L12: =VLOOKUP(A12,Sheet1!$A$1:$E$2000,5,FALSE) -> 3439078053 | M12: =(H12-D12)/ABS(D12) -> 0.13893737 | N12: =(I12-E12)/ABS(E12) -> 1.325495 | O12: =(J12-F12)/ABS(F12) -> 3.1651845 | P12: =(K12-G12)/ABS(G12) -> 3.8000688 | Q12: =(L12-H12)/ABS(H12) -> 0.3275249 | R12: =(SUM(J12:L12)-SUM(F12:H12))/ABS(SUM(F12:H12)) -> 2.4598084 | S12: =SUM(I12:L12)/SUM(E12:H12)-1 -> 2.1751695 | T12: =SUM(I12:L12) -> 35184898681
A13: ADG | B13: Clever Group | C13: HOSE | D13: -3285481898 | E13: 10710958142 | F13: -4568301656 | G13: 14936070274 | H13: -4973640619 | I13: 5013562564 | J13: 31660653 | K13: 18720935018 | L13: =VLOOKUP(A13,Sheet1!$A$1:$E$2000,5,FALSE) -> 0 | M13: =(H13-D13)/ABS(D13) -> -0.51382378 | N13: =(I13-E13)/ABS(E13) -> -0.53192212 | O13: =(J13-F13)/ABS(F13) -> 1.0069305 | P13: =(K13-G13)/ABS(G13) -> 0.25340432 | Q13: =(L13-H13)/ABS(H13) -> 1 | R13: =(SUM(J13:L13)-SUM(F13:H13))/ABS(SUM(F13:H13)) -> 2.4764833 | S13: =SUM(I13:L13)/SUM(E13:H13)-1 -> 0.47569271 | T13: =SUM(I13:L13) -> 23766158235
A14: ADP | B14: Sơn Á Đông | C14: HOSE | D14: 22523954117 | E14: 27732271023 | F14: 18423800383 | G14: 16633957477 | H14: 22038189566 | I14: 22597878540 | J14: 12780298221 | K14: 19044171289 | L14: =VLOOKUP(A14,Sheet1!$A$1:$E$2000,5,FALSE) -> 15837757005 | M14: =(H14-D14)/ABS(D14) -> -0.021566575 | N14: =(I14-E14)/ABS(E14) -> -0.18514144 | O14: =(J14-F14)/ABS(F14) -> -0.30631585 | P14: =(K14-G14)/ABS(G14) -> 0.1448972 | Q14: =(L14-H14)/ABS(H14) -> -0.28134945 | R14: =(SUM(J14:L14)-SUM(F14:H14))/ABS(SUM(F14:H14)) -> -0.16522575 | S14: =SUM(I14:L14)/SUM(E14:H14)-1 -> -0.17173664 | T14: =SUM(I14:L14) -> 70260105055
... A26: AST | B26: Dịch vụ Hàng không Taseco | C26: HOSE | D26: 34931983132 | E26: 32631112035 | F26: 38911653043 | G26: 42146310230 | H26: 54663465814 | I26: 62553199290 | J26: 69077871933 | K26: 63875739677 | L26: =VLOOKUP(A26,Sheet1!$A$1:$E$2000,5,FALSE) -> 100919143835 | M26: =(H26-D26)/ABS(D26) -> 0.56485435 | N26: =(I26-E26)/ABS(E26) -> 0.91698031 | O26: =(J26-F26)/ABS(F26) -> 0.77524897 | P26: =(K26-G26)/ABS(G26) -> 0.51557134 | Q26: =(L26-H26)/ABS(H26) -> 0.84619 | R26: =(SUM(J26:L26)-SUM(F26:H26))/ABS(SUM(F26:H26)) -> 0.72318223 | S26: =SUM(I26:L26)/SUM(E26:H26)-1 -> 0.76074535 | T26: =SUM(I26:L26) -> 296425954735
A27: ATP | B27: T.Mại và DV An Thành | C27: HOSE | L27: =VLOOKUP(A27,Sheet1!$A$1:$E$2000,5,FALSE) -> 0 | M27: =(H27-D27)/ABS(D27) -> #DIV/0! | N27: =(I27-E27)/ABS(E27) -> #DIV/0! | O27: =(J27-F27)/ABS(F27) -> #DIV/0! | P27: =(K27-G27)/ABS(G27) -> #DIV/0! | Q27: =(L27-H27)/ABS(H27) -> #DIV/0! | R27: =(SUM(J27:L27)-SUM(F27:H27))/ABS(SUM(F27:H27)) -> #DIV/0! | S27: =SUM(I27:L27)/SUM(E27:H27)-1 -> #DIV/0! | T27: =SUM(I27:L27) -> 0
A28: BAF | B28: Nông nghiệp BAF Việt Nam | C28: HOSE | D28: 119523556707 | E28: 34442878688 | F28: 60366065297 | G28: 102715019494 | H28: 132447048246 | I28: 210069572013 | J28: 20640704588 | K28: -236536147824 | L28: =VLOOKUP(A28,Sheet1!$A$1:$E$2000,5,FALSE) -> 206000611406 | M28: =(H28-D28)/ABS(D28) -> 0.10812506 | N28: =(I28-E28)/ABS(E28) -> 5.0990713 | O28: =(J28-F28)/ABS(F28) -> -0.65807438 | P28: =(K28-G28)/ABS(G28) -> -3.302839 | Q28: =(L28-H28)/ABS(H28) -> 0.55534317 | R28: =(SUM(J28:L28)-SUM(F28:H28))/ABS(SUM(F28:H28)) -> -1.0334819 | S28: =SUM(I28:L28)/SUM(E28:H28)-1 -> -0.39335659 | T28: =SUM(I28:L28) -> 200174740183
A29: BCE | B29: XD và GT Bình Dương | C29: HOSE | D29: -4712977951 | E29: -11814035796 | F29: -9666591352 | G29: 100580947209 | H29: -5099003781 | I29: 5565764350 | J29: 3086545624 | K29: 98186900087 | L29: =VLOOKUP(A29,Sheet1!$A$1:$E$2000,5,FALSE) -> -21356676077 | M29: =(H29-D29)/ABS(D29) -> -0.081906988 | N29: =(I29-E29)/ABS(E29) -> 1.4711146 | O29: =(J29-F29)/ABS(F29) -> 1.3193003 | P29: =(K29-G29)/ABS(G29) -> -0.023802193 | Q29: =(L29-H29)/ABS(H29) -> -3.1884017 | R29: =(SUM(J29:L29)-SUM(F29:H29))/ABS(SUM(F29:H29)) -> -0.068735748 | S29: =SUM(I29:L29)/SUM(E29:H29)-1 -> 0.15514883 | T29: =SUM(I29:L29) -> 85482533984
A30: BCG | B30: Bamboo Capital | C30: HOSE | D30: 13634044335 | E30: 131908086830 | F30: 131526669847 | G30: 126944657704 | L30: =VLOOKUP(A30,Sheet1!$A$1:$E$2000,5,FALSE) -> 0 | M30: =(H30-D30)/ABS(D30) -> -1 | N30: =(I30-E30)/ABS(E30) -> -1 | O30: =(J30-F30)/ABS(F30) -> -1 | P30: =(K30-G30)/ABS(G30) -> -1 | Q30: =(L30-H30)/ABS(H30) -> #DIV/0! | R30: =(SUM(J30:L30)-SUM(F30:H30))/ABS(SUM(F30:H30)) -> -1 | S30: =SUM(I30:L30)/SUM(E30:H30)-1 -> -1 | T30: =SUM(I30:L30) -> 0
A31: BCM | B31: Becamex Group | C31: HOSE | D31: 118116106443 | E31: 273356050769 | F31: 344394978084 | G31: 1451224034015 | H31: 358265688293 | I31: 1475637440340 | J31: 415683449300 | K31: 1238878137592 | L31: =VLOOKUP(A31,Sheet1!$A$1:$E$2000,5,FALSE) -> 279562828161 | M31: =(H31-D31)/ABS(D31) -> 2.0331654 | N31: =(I31-E31)/ABS(E31) -> 4.3982249 | O31: =(J31-F31)/ABS(F31) -> 0.20699626 | P31: =(K31-G31)/ABS(G31) -> -0.14632193 | Q31: =(L31-H31)/ABS(H31) -> -0.21967736 | R31: =(SUM(J31:L31)-SUM(F31:H31))/ABS(SUM(F31:H31)) -> -0.10202974 | S31: =SUM(I31:L31)/SUM(E31:H31)-1 -> 0.40478931 | T31: =SUM(I31:L31) -> 3409761855393
A32: BFC | B32: Phân bón Bình Điền | C32: HOSE | D32: 64816208445 | E32: 167638856983 | F32: 52678365892 | G32: 71872920058 | H32: 92613952907 | I32: 115702421755 | J32: 61172285525 | K32: 40387581258 | L32: =VLOOKUP(A32,Sheet1!$A$1:$E$2000,5,FALSE) -> 124201533146 | M32: =(H32-D32)/ABS(D32) -> 0.42887026 | N32: =(I32-E32)/ABS(E32) -> -0.30981144 | O32: =(J32-F32)/ABS(F32) -> 0.16124114 | P32: =(K32-G32)/ABS(G32) -> -0.43806956 | Q32: =(L32-H32)/ABS(H32) -> 0.34106719 | R32: =(SUM(J32:L32)-SUM(F32:H32))/ABS(SUM(F32:H32)) -> 0.039583504 | S32: =SUM(I32:L32)/SUM(E32:H32)-1 -> -0.11262945 | T32: =SUM(I32:L32) -> 341463821684
A33: BHN | B33: HABECO | C33: HOSE | D33: -5236096891 | E33: 153848022623 | F33: 124086518728 | G33: 109496209431 | H33: 32842643756 | I33: 143011122629 | J33: 221041322040 | K33: 71621671782 | L33: =VLOOKUP(A33,Sheet1!$A$1:$E$2000,5,FALSE) -> 77222524813 | M33: =(H33-D33)/ABS(D33) -> 7.2723522 | N33: =(I33-E33)/ABS(E33) -> -0.070438994 | O33: =(J33-F33)/ABS(F33) -> 0.7813484 | P33: =(K33-G33)/ABS(G33) -> -0.34589816 | Q33: =(L33-H33)/ABS(H33) -> 1.3512883 | R33: =(SUM(J33:L33)-SUM(F33:H33))/ABS(SUM(F33:H33)) -> 0.38832693 | S33: =SUM(I33:L33)/SUM(E33:H33)-1 -> 0.22038808 | T33: =SUM(I33:L33) -> 512896641264
A34: BIC | B34: Bảo hiểm BIDV | C34: HOSE | D34: 104970237416 | E34: 167373086527 | F34: 70924609094 | G34: 151417674464 | H34: 154128694295 | I34: 172341774795 | J34: 91033604240 | K34: 122927777632 | L34: =VLOOKUP(A34,Sheet1!$A$1:$E$2000,5,FALSE) -> 87245176382 | M34: =(H34-D34)/ABS(D34) -> 0.46830852 | N34: =(I34-E34)/ABS(E34) -> 0.029686304 | O34: =(J34-F34)/ABS(F34) -> 0.28352634 | P34: =(K34-G34)/ABS(G34) -> -0.18815437 | Q34: =(L34-H34)/ABS(H34) -> -0.43394592 | R34: =(SUM(J34:L34)-SUM(F34:H34))/ABS(SUM(F34:H34)) -> -0.19992091 | S34: =SUM(I34:L34)/SUM(E34:H34)-1 -> -0.12925715 | T34: =SUM(I34:L34) -> 473548333049
A35: BID | B35: BIDV | C35: HOSE | D35: 5812648000000 | E35: 6365954000000 | F35: 5151318000000 | G35: 7810117000000 | H35: 5840373000000 | I35: 6755001000000 | J35: 5952964000000 | K35: 11355926000000 | L35: =VLOOKUP(A35,Sheet1!$A$1:$E$2000,5,FALSE) -> 6800834000000 | M35: =(H35-D35)/ABS(D35) -> 0.004769771 | N35: =(I35-E35)/ABS(E35) -> 0.0611137 | O35: =(J35-F35)/ABS(F35) -> 0.15561959 | P35: =(K35-G35)/ABS(G35) -> 0.45400203 | Q35: =(L35-H35)/ABS(H35) -> 0.164452 | R35: =(SUM(J35:L35)-SUM(F35:H35))/ABS(SUM(F35:H35)) -> 0.28230881 | S35: =SUM(I35:L35)/SUM(E35:H35)-1 -> 0.22635954 | T35: =SUM(I35:L35) -> 30864725000000
A36: BKG | B36: Đầu tư BKG Việt Nam | C36: HOSE | D36: 4017323438 | E36: 4254574626 | F36: 2708878812 | G36: 3578475140 | H36: 2696445314 | I36: 3422584599 | J36: 1316318299 | K36: 2673409534 | L36: =VLOOKUP(A36,Sheet1!$A$1:$E$2000,5,FALSE) -> 1648718602 | M36: =(H36-D36)/ABS(D36) -> -0.32879556 | N36: =(I36-E36)/ABS(E36) -> -0.19555187 | O36: =(J36-F36)/ABS(F36) -> -0.51407265 | P36: =(K36-G36)/ABS(G36) -> -0.25291935 | Q36: =(L36-H36)/ABS(H36) -> -0.38855849 | R36: =(SUM(J36:L36)-SUM(F36:H36))/ABS(SUM(F36:H36)) -> -0.37237618 | S36: =SUM(I36:L36)/SUM(E36:H36)-1 -> -0.31554803 | T36: =SUM(I36:L36) -> 9061031034
A37: BMC | B37: Khoáng sản Bình Định | C37: HOSE | D37: 4762071361 | E37: 6748284381 | F37: 6119439311 | G37: 7911643781 | H37: 897347845 | I37: 3774810543 | J37: 4262062451 | K37: 2582615142 | L37: =VLOOKUP(A37,Sheet1!$A$1:$E$2000,5,FALSE) -> 1481978528 | M37: =(H37-D37)/ABS(D37) -> -0.81156355 | N37: =(I37-E37)/ABS(E37) -> -0.44062663 | O37: =(J37-F37)/ABS(F37) -> -0.30352076 | P37: =(K37-G37)/ABS(G37) -> -0.67356782 | Q37: =(L37-H37)/ABS(H37) -> 0.65150954 | R37: =(SUM(J37:L37)-SUM(F37:H37))/ABS(SUM(F37:H37)) -> -0.44222831 | S37: =SUM(I37:L37)/SUM(E37:H37)-1 -> -0.44172969 | T37: =SUM(I37:L37) -> 12101466664
A38: BMI | B38: Bảo hiểm Bảo Minh | C38: HOSE | D38: 72723951668 | E38: 70694000582 | F38: 51168094654 | G38: 43087995325 | H38: 63059823482 | I38: 80431469454 | J38: 112712232202 | K38: 3583116939 | L38: =VLOOKUP(A38,Sheet1!$A$1:$E$2000,5,FALSE) -> 55556275286 | M38: =(H38-D38)/ABS(D38) -> -0.13288783 | N38: =(I38-E38)/ABS(E38) -> 0.13774109 | O38: =(J38-F38)/ABS(F38) -> 1.2027835 | P38: =(K38-G38)/ABS(G38) -> -0.91684187 | Q38: =(L38-H38)/ABS(H38) -> -0.11899095 | R38: =(SUM(J38:L38)-SUM(F38:H38))/ABS(SUM(F38:H38)) -> 0.092398224 | S38: =SUM(I38:L38)/SUM(E38:H38)-1 -> 0.10645669 | T38: =SUM(I38:L38) -> 252283093881
A39: BMP | B39: Nhựa Bình Minh | C39: HOSE | D39: 189875059628 | E39: 280300515276 | F39: 289630912189 | G39: 230955242045 | H39: 286910617568 | I39: 329900327324 | J39: 350581005736 | K39: 261343222934 | L39: =VLOOKUP(A39,Sheet1!$A$1:$E$2000,5,FALSE) -> 303956059754 | M39: =(H39-D39)/ABS(D39) -> 0.51104952 | N39: =(I39-E39)/ABS(E39) -> 0.17695227 | O39: =(J39-F39)/ABS(F39) -> 0.21044057 | P39: =(K39-G39)/ABS(G39) -> 0.13157519 | Q39: =(L39-H39)/ABS(H39) -> 0.059410287 | R39: =(SUM(J39:L39)-SUM(F39:H39))/ABS(SUM(F39:H39)) -> 0.13422161 | S39: =SUM(I39:L39)/SUM(E39:H39)-1 -> 0.14523232 | T39: =SUM(I39:L39) -> 1245780615748
A40: BRC | B40: Cao su Bến Thành | C40: HOSE | D40: 4364945131 | E40: 5571877885 | F40: 7749076520 | G40: 4065343959 | H40: 4204050002 | I40: 6394009821 | J40: 5493847925 | K40: 4702086183 | L40: =VLOOKUP(A40,Sheet1!$A$1:$E$2000,5,FALSE) -> 4646531336 | M40: =(H40-D40)/ABS(D40) -> -0.036860745 | N40: =(I40-E40)/ABS(E40) -> 0.14755024 | O40: =(J40-F40)/ABS(F40) -> -0.29103192 | P40: =(K40-G40)/ABS(G40) -> 0.1566269 | Q40: =(L40-H40)/ABS(H40) -> 0.10525121 | R40: =(SUM(J40:L40)-SUM(F40:H40))/ABS(SUM(F40:H40)) -> -0.073415564 | S40: =SUM(I40:L40)/SUM(E40:H40)-1 -> -0.016390338 | T40: =SUM(I40:L40) -> 21236475265
A41: BSI | B41: Chứng khoán BIDV | C41: HOSE | D41: 137148427862 | E41: 114779704952 | F41: 70008539857 | G41: 91152423672 | H41: 81115038976 | I41: 101899940357 | J41: 215588496422 | K41: 95062757764 | L41: =VLOOKUP(A41,Sheet1!$A$1:$E$2000,5,FALSE) -> 88819056890 | M41: =(H41-D41)/ABS(D41) -> -0.4085602 | N41: =(I41-E41)/ABS(E41) -> -0.11221291 | O41: =(J41-F41)/ABS(F41) -> 2.07946 | P41: =(K41-G41)/ABS(G41) -> 0.042898849 | Q41: =(L41-H41)/ABS(H41) -> 0.094976443 | R41: =(SUM(J41:L41)-SUM(F41:H41))/ABS(SUM(F41:H41)) -> 0.64882327 | S41: =SUM(I41:L41)/SUM(E41:H41)-1 -> 0.40417935 | T41: =SUM(I41:L41) -> 501370251433
A42: BSR | B42: Lọc Hóa dầu Bình Sơn | C42: HOSE | D42: 1143819690777 | E42: 781568179382 | F42: -1210167499868 | G42: -84089620987 | H42: 398719235293 | I42: 845664137644 | J42: 907545618973 | K42: 3061683071313 | L42: =VLOOKUP(A42,Sheet1!$A$1:$E$2000,5,FALSE) -> 8264713781616 | M42: =(H42-D42)/ABS(D42) -> -0.65141426 | N42: =(I42-E42)/ABS(E42) -> 0.082009427 | O42: =(J42-F42)/ABS(F42) -> 1.7499339 | P42: =(K42-G42)/ABS(G42) -> 37.409762 | Q42: =(L42-H42)/ABS(H42) -> 19.728154 | R42: =(SUM(J42:L42)-SUM(F42:H42))/ABS(SUM(F42:H42)) -> 14.660999 | S42: =SUM(I42:L42)/SUM(E42:H42)-1 -> -115.76389 | T42: =SUM(I42:L42) -> 13079606609546
... A111: DXV | B111: Vật liệu Xây dựng Đà Nẵng | C111: HOSE | D111: -660364239 | E111: -1526677032 | F111: -1585578523 | G111: -1888731317 | H111: 33100236 | I111: 425079747 | J111: 218938382 | K111: 137097207 | L111: =VLOOKUP(A111,Sheet1!$A$1:$E$2000,5,FALSE) -> 148132891 | M111: =(H111-D111)/ABS(D111) -> 1.0501242 | N111: =(I111-E111)/ABS(E111) -> 1.2784346 | O111: =(J111-F111)/ABS(F111) -> 1.1380811 | P111: =(K111-G111)/ABS(G111) -> 1.0725869 | Q111: =(L111-H111)/ABS(H111) -> 3.475282 | R111: =(SUM(J111:L111)-SUM(F111:H111))/ABS(SUM(F111:H111)) -> 1.1465091 | S111: =SUM(I111:L111)/SUM(E111:H111)-1 -> -1.187051 | T111: =SUM(I111:L111) -> 929248227
A112: E1VFVN30 | B112: Quỹ ETF DCVFMVN30 | C112: HOSE | L112: =VLOOKUP(A112,Sheet1!$A$1:$E$2000,5,FALSE) -> 0 | M112: =(H112-D112)/ABS(D112) -> #DIV/0! | N112: =(I112-E112)/ABS(E112) -> #DIV/0! | O112: =(J112-F112)/ABS(F112) -> #DIV/0! | P112: =(K112-G112)/ABS(G112) -> #DIV/0! | Q112: =(L112-H112)/ABS(H112) -> #DIV/0! | R112: =(SUM(J112:L112)-SUM(F112:H112))/ABS(SUM(F112:H112)) -> #DIV/0! | S112: =SUM(I112:L112)/SUM(E112:H112)-1 -> #DIV/0! | T112: =SUM(I112:L112) -> 0
A113: EIB | B113: Eximbank | C113: HOSE | D113: 527251000000 | E113: 642838000000 | F113: 721211000000 | G113: 1435504000000 | H113: 658489000000 | I113: 506244000000 | J113: 444688000000 | K113: -472482000000 | L113: =VLOOKUP(A113,Sheet1!$A$1:$E$2000,5,FALSE) -> 269160000000 | M113: =(H113-D113)/ABS(D113) -> 0.24890991 | N113: =(I113-E113)/ABS(E113) -> -0.21248588 | O113: =(J113-F113)/ABS(F113) -> -0.38341484 | P113: =(K113-G113)/ABS(G113) -> -1.3291401 | Q113: =(L113-H113)/ABS(H113) -> -0.59124602 | R113: =(SUM(J113:L113)-SUM(F113:H113))/ABS(SUM(F113:H113)) -> -0.91426341 | S113: =SUM(I113:L113)/SUM(E113:H113)-1 -> -0.7838054 | T113: =SUM(I113:L113) -> 747610000000
A114: ELC | B114: ELCOM | C114: HOSE | D114: 7233556497 | E114: 4185825253 | F114: 9115863591 | G114: 74912430519 | H114: 4775083433 | I114: 14692059584 | J114: 39005431111 | K114: 69174357247 | L114: =VLOOKUP(A114,Sheet1!$A$1:$E$2000,5,FALSE) -> 2653995651 | M114: =(H114-D114)/ABS(D114) -> -0.33987058 | N114: =(I114-E114)/ABS(E114) -> 2.5099553 | O114: =(J114-F114)/ABS(F114) -> 3.278852 | P114: =(K114-G114)/ABS(G114) -> -0.076597078 | Q114: =(L114-H114)/ABS(H114) -> -0.4441991 | R114: =(SUM(J114:L114)-SUM(F114:H114))/ABS(SUM(F114:H114)) -> 0.24808073 | S114: =SUM(I114:L114)/SUM(E114:H114)-1 -> 0.34989698 | T114: =SUM(I114:L114) -> 125525843593
A115: EVE | B115: Everpia | C115: HOSE | D115: 1114824859 | E115: -9378073463 | F115: -29484980365 | G115: 7562164052 | H115: 720558457 | I115: 11626833405 | J115: 18303353419 | K115: 8565390560 | L115: =VLOOKUP(A115,Sheet1!$A$1:$E$2000,5,FALSE) -> 770203562 | M115: =(H115-D115)/ABS(D115) -> -0.35365771 | N115: =(I115-E115)/ABS(E115) -> 2.2397891 | O115: =(J115-F115)/ABS(F115) -> 1.6207687 | P115: =(K115-G115)/ABS(G115) -> 0.13266394 | Q115: =(L115-H115)/ABS(H115) -> 0.068898095 | R115: =(SUM(J115:L115)-SUM(F115:H115))/ABS(SUM(F115:H115)) -> 2.3035851 | S115: =SUM(I115:L115)/SUM(E115:H115)-1 -> -2.2840208 | T115: =SUM(I115:L115) -> 39265780946
A116: EVF | B116: Tài chính Tổng hợp Điện lực | C116: HOSE | D116: 131126000000 | E116: 117887000000 | F116: 180800000000 | G116: 131008000000 | H116: 240480000000 | I116: 241944000000 | J116: 253789000000 | K116: 158124000000 | L116: =VLOOKUP(A116,Sheet1!$A$1:$E$2000,5,FALSE) -> 266631000000 | M116: =(H116-D116)/ABS(D116) -> 0.83396123 | N116: =(I116-E116)/ABS(E116) -> 1.0523383 | O116: =(J116-F116)/ABS(F116) -> 0.40370022 | P116: =(K116-G116)/ABS(G116) -> 0.20697973 | Q116: =(L116-H116)/ABS(H116) -> 0.10874501 | R116: =(SUM(J116:L116)-SUM(F116:H116))/ABS(SUM(F116:H116)) -> 0.22860537 | S116: =SUM(I116:L116)/SUM(E116:H116)-1 -> 0.37350394 | T116: =SUM(I116:L116) -> 920488000000
A117: EVG | B117: Tập đoàn Everland | C117: HOSE | D117: -3117579661 | E117: 30154266753 | F117: 8211327351 | G117: -3829357620 | H117: 10862534485 | I117: 9854229183 | J117: 15013887962 | K117: 42010050458 | L117: =VLOOKUP(A117,Sheet1!$A$1:$E$2000,5,FALSE) -> 18956399299 | M117: =(H117-D117)/ABS(D117) -> 4.4842845 | N117: =(I117-E117)/ABS(E117) -> -0.67320614 | O117: =(J117-F117)/ABS(F117) -> 0.82843617 | P117: =(K117-G117)/ABS(G117) -> 11.970522 | Q117: =(L117-H117)/ABS(H117) -> 0.74511753 | R117: =(SUM(J117:L117)-SUM(F117:H117))/ABS(SUM(F117:H117)) -> 3.9841134 | S117: =SUM(I117:L117)/SUM(E117:H117)-1 -> 0.89068041 | T117: =SUM(I117:L117) -> 85834566902
A118: FCM | B118: Bê tông Phan Vũ Hà Nam | C118: HOSE | D118: 945007431 | E118: -10352427675 | F118: 4360104649 | G118: 6586842182 | H118: 4403581361 | I118: 4359293246 | J118: 3603589240 | K118: 6404312226 | L118: =VLOOKUP(A118,Sheet1!$A$1:$E$2000,5,FALSE) -> 4275275637 | M118: =(H118-D118)/ABS(D118) -> 3.6598378 | N118: =(I118-E118)/ABS(E118) -> 1.421089 | O118: =(J118-F118)/ABS(F118) -> -0.17350854 | P118: =(K118-G118)/ABS(G118) -> -0.027711299 | Q118: =(L118-H118)/ABS(H118) -> -0.029136676 | R118: =(SUM(J118:L118)-SUM(F118:H118))/ABS(SUM(F118:H118)) -> -0.06953188 | S118: =SUM(I118:L118)/SUM(E118:H118)-1 -> 2.7299111 | T118: =SUM(I118:L118) -> 18642470349
A119: FCN | B119: FECON CORP | C119: HOSE | D119: -7327261497 | E119: 11579911025 | F119: 7147180693 | G119: -2130821338 | H119: -6567397288 | I119: 21680880146 | J119: 14617349417 | K119: 2613208704 | L119: =VLOOKUP(A119,Sheet1!$A$1:$E$2000,5,FALSE) -> 31326328494 | M119: =(H119-D119)/ABS(D119) -> 0.10370371 | N119: =(I119-E119)/ABS(E119) -> 0.87228383 | O119: =(J119-F119)/ABS(F119) -> 1.045191 | P119: =(K119-G119)/ABS(G119) -> 2.2263856 | Q119: =(L119-H119)/ABS(H119) -> 5.7699762 | R119: =(SUM(J119:L119)-SUM(F119:H119))/ABS(SUM(F119:H119)) -> 32.30606 | S119: =SUM(I119:L119)/SUM(E119:H119)-1 -> 6.0035552 | T119: =SUM(I119:L119) -> 70237766761
A120: FDC | B120: FIDECO | C120: HOSE | D120: 365135603 | E120: -1558669339 | F120: 2425359114 | G120: 3830222105 | H120: 10968434787 | I120: 11269831134 | J120: 9410799609 | K120: 182569500635 | L120: =VLOOKUP(A120,Sheet1!$A$1:$E$2000,5,FALSE) -> 6779596455 | M120: =(H120-D120)/ABS(D120) -> 29.039346 | N120: =(I120-E120)/ABS(E120) -> 8.2304182 | O120: =(J120-F120)/ABS(F120) -> 2.8801675 | P120: =(K120-G120)/ABS(G120) -> 46.665513 | Q120: =(L120-H120)/ABS(H120) -> -0.38189937 | R120: =(SUM(J120:L120)-SUM(F120:H120))/ABS(SUM(F120:H120)) -> 10.539695 | S120: =SUM(I120:L120)/SUM(E120:H120)-1 -> 12.407282 | T120: =SUM(I120:L120) -> 210029727833
A121: FIR | B121: Địa ốc First Real | C121: HOSE | D121: 1148465515 | E121: 1207860082 | F121: -10075310907 | G121: -13280597879 | H121: 16144611587 | I121: 14964523924 | J121: -15860146552 | K121: 721380659 | L121: =VLOOKUP(A121,Sheet1!$A$1:$E$2000,5,FALSE) -> 0 | M121: =(H121-D121)/ABS(D121) -> 13.05755 | N121: =(I121-E121)/ABS(E121) -> 11.389286 | O121: =(J121-F121)/ABS(F121) -> -0.57415952 | P121: =(K121-G121)/ABS(G121) -> 1.0543184 | Q121: =(L121-H121)/ABS(H121) -> -1 | R121: =(SUM(J121:L121)-SUM(F121:H121))/ABS(SUM(F121:H121)) -> -1.0993124 | S121: =SUM(I121:L121)/SUM(E121:H121)-1 -> -0.9709763 | T121: =SUM(I121:L121) -> -174241969
A122: FIT | B122: Tập đoàn F.I.T | C122: HOSE | D122: 54232108257 | E122: 35968141574 | F122: 23654300538 | G122: 5409030979 | H122: 16191638766 | I122: 12969252926 | J122: 16007567525 | K122: -5184668609 | L122: =VLOOKUP(A122,Sheet1!$A$1:$E$2000,5,FALSE) -> 0 | M122: =(H122-D122)/ABS(D122) -> -0.70143815 | N122: =(I122-E122)/ABS(E122) -> -0.63942388 | O122: =(J122-F122)/ABS(F122) -> -0.32327031 | P122: =(K122-G122)/ABS(G122) -> -1.9585208 | Q122: =(L122-H122)/ABS(H122) -> -1 | R122: =(SUM(J122:L122)-SUM(F122:H122))/ABS(SUM(F122:H122)) -> -0.76084618 | S122: =SUM(I122:L122)/SUM(E122:H122)-1 -> -0.70707658 | T122: =SUM(I122:L122) -> 23792151842
A123: FMC | B123: Thực phẩm Sao Ta | C123: HOSE | D123: 49697873883 | E123: 66283887501 | F123: 79628088451 | G123: 110090662579 | H123: 29615681550 | I123: 80440807863 | J123: 97164218054 | K123: 141439902499 | L123: =VLOOKUP(A123,Sheet1!$A$1:$E$2000,5,FALSE) -> 40852316596 | M123: =(H123-D123)/ABS(D123) -> -0.40408554 | N123: =(I123-E123)/ABS(E123) -> 0.21358012 | O123: =(J123-F123)/ABS(F123) -> 0.22022542 | P123: =(K123-G123)/ABS(G123) -> 0.28475839 | Q123: =(L123-H123)/ABS(H123) -> 0.37941504 | R123: =(SUM(J123:L123)-SUM(F123:H123))/ABS(SUM(F123:H123)) -> 0.27411111 | S123: =SUM(I123:L123)/SUM(E123:H123)-1 -> 0.26006359 | T123: =SUM(I123:L123) -> 359897245012
A124: FPT | B124: FPT Corp | C124: HOSE | D124: 1798030863528 | E124: 1875158768537 | F124: 2088852212408 | G124: 2094725967705 | H124: 2174301386525 | I124: 2257462588123 | J124: 2434841434732 | K124: 2509522220120 | L124: =VLOOKUP(A124,Sheet1!$A$1:$E$2000,5,FALSE) -> 2487371587099 | M124: =(H124-D124)/ABS(D124) -> 0.20926811 | N124: =(I124-E124)/ABS(E124) -> 0.20387811 | O124: =(J124-F124)/ABS(F124) -> 0.16563605 | P124: =(K124-G124)/ABS(G124) -> 0.19801934 | Q124: =(L124-H124)/ABS(H124) -> 0.14398657 | R124: =(SUM(J124:L124)-SUM(F124:H124))/ABS(SUM(F124:H124)) -> 0.16890154 | S124: =SUM(I124:L124)/SUM(E124:H124)-1 -> 0.17686781 | T124: =SUM(I124:L124) -> 9689197830074
... A126: FTS | B126: Chứng khoán FPT | C126: HOSE | D126: 166626409385 | E126: 160499112951 | F126: 80679298426 | G126: 159512673575 | H126: 152966608704 | I126: 60616673458 | J126: 55114069962 | K126: 128056922698 | L126: =VLOOKUP(A126,Sheet1!$A$1:$E$2000,5,FALSE) -> 159915055919 | M126: =(H126-D126)/ABS(D126) -> -0.081978606 | N126: =(I126-E126)/ABS(E126) -> -0.62232393 | O126: =(J126-F126)/ABS(F126) -> -0.3168747 | P126: =(K126-G126)/ABS(G126) -> -0.19719907 | Q126: =(L126-H126)/ABS(H126) -> 0.045424601 | R126: =(SUM(J126:L126)-SUM(F126:H126))/ABS(SUM(F126:H126)) -> -0.12735963 | S126: =SUM(I126:L126)/SUM(E126:H126)-1 -> -0.27084419 | T126: =SUM(I126:L126) -> 403702722037
A127: FUCTVGF3 | B127: Quỹ Đầu tư Tăng trưởng Thiên Việt 3 | C127: HOSE | L127: =VLOOKUP(A127,Sheet1!$A$1:$E$2000,5,FALSE) -> 0 | M127: =(H127-D127)/ABS(D127) -> #DIV/0! | N127: =(I127-E127)/ABS(E127) -> #DIV/0! | O127: =(J127-F127)/ABS(F127) -> #DIV/0! | P127: =(K127-G127)/ABS(G127) -> #DIV/0! | Q127: =(L127-H127)/ABS(H127) -> #DIV/0! | R127: =(SUM(J127:L127)-SUM(F127:H127))/ABS(SUM(F127:H127)) -> #DIV/0! | S127: =SUM(I127:L127)/SUM(E127:H127)-1 -> #DIV/0! | T127: =SUM(I127:L127) -> 0
A128: FUCTVGF4 | B128: Quỹ Đầu tư Tăng trưởng Thiên Việt 4 | C128: HOSE | L128: =VLOOKUP(A128,Sheet1!$A$1:$E$2000,5,FALSE) -> 0 | M128: =(H128-D128)/ABS(D128) -> #DIV/0! | N128: =(I128-E128)/ABS(E128) -> #DIV/0! | O128: =(J128-F128)/ABS(F128) -> #DIV/0! | P128: =(K128-G128)/ABS(G128) -> #DIV/0! | Q128: =(L128-H128)/ABS(H128) -> #DIV/0! | R128: =(SUM(J128:L128)-SUM(F128:H128))/ABS(SUM(F128:H128)) -> #DIV/0! | S128: =SUM(I128:L128)/SUM(E128:H128)-1 -> #DIV/0! | T128: =SUM(I128:L128) -> 0
A129: FUCTVGF5 | B129: Quỹ Đầu tư Tăng trưởng Thiên Việt 5 | C129: HOSE | L129: =VLOOKUP(A129,Sheet1!$A$1:$E$2000,5,FALSE) -> 0 | M129: =(H129-D129)/ABS(D129) -> #DIV/0! | N129: =(I129-E129)/ABS(E129) -> #DIV/0! | O129: =(J129-F129)/ABS(F129) -> #DIV/0! | P129: =(K129-G129)/ABS(G129) -> #DIV/0! | Q129: =(L129-H129)/ABS(H129) -> #DIV/0! | R129: =(SUM(J129:L129)-SUM(F129:H129))/ABS(SUM(F129:H129)) -> #DIV/0! | S129: =SUM(I129:L129)/SUM(E129:H129)-1 -> #DIV/0! | T129: =SUM(I129:L129) -> 0
A130: FUCVREIT | B130: Quỹ Đầu tư BĐS Techcom Việt Nam | C130: HOSE | L130: =VLOOKUP(A130,Sheet1!$A$1:$E$2000,5,FALSE) -> 0 | M130: =(H130-D130)/ABS(D130) -> #DIV/0! | N130: =(I130-E130)/ABS(E130) -> #DIV/0! | O130: =(J130-F130)/ABS(F130) -> #DIV/0! | P130: =(K130-G130)/ABS(G130) -> #DIV/0! | Q130: =(L130-H130)/ABS(H130) -> #DIV/0! | R130: =(SUM(J130:L130)-SUM(F130:H130))/ABS(SUM(F130:H130)) -> #DIV/0! | S130: =SUM(I130:L130)/SUM(E130:H130)-1 -> #DIV/0! | T130: =SUM(I130:L130) -> 0
A131: FUEABVND | B131: Quỹ ETF ABFVN DIAMOND | C131: HOSE | L131: =VLOOKUP(A131,Sheet1!$A$1:$E$2000,5,FALSE) -> 0 | M131: =(H131-D131)/ABS(D131) -> #DIV/0! | N131: =(I131-E131)/ABS(E131) -> #DIV/0! | O131: =(J131-F131)/ABS(F131) -> #DIV/0! | P131: =(K131-G131)/ABS(G131) -> #DIV/0! | Q131: =(L131-H131)/ABS(H131) -> #DIV/0! | R131: =(SUM(J131:L131)-SUM(F131:H131))/ABS(SUM(F131:H131)) -> #DIV/0! | S131: =SUM(I131:L131)/SUM(E131:H131)-1 -> #DIV/0! | T131: =SUM(I131:L131) -> 0
A132: FUEBFVND | B132: Quỹ ETF BVFVN DIAMOND | C132: HOSE | L132: =VLOOKUP(A132,Sheet1!$A$1:$E$2000,5,FALSE) -> 0 | M132: =(H132-D132)/ABS(D132) -> #DIV/0! | N132: =(I132-E132)/ABS(E132) -> #DIV/0! | O132: =(J132-F132)/ABS(F132) -> #DIV/0! | P132: =(K132-G132)/ABS(G132) -> #DIV/0! | Q132: =(L132-H132)/ABS(H132) -> #DIV/0! | R132: =(SUM(J132:L132)-SUM(F132:H132))/ABS(SUM(F132:H132)) -> #DIV/0! | S132: =SUM(I132:L132)/SUM(E132:H132)-1 -> #DIV/0! | T132: =SUM(I132:L132) -> 0
A133: FUEDCMID | B133: Quỹ ETF DCVFMVNMIDCAP | C133: HOSE | L133: =VLOOKUP(A133,Sheet1!$A$1:$E$2000,5,FALSE) -> 0 | M133: =(H133-D133)/ABS(D133) -> #DIV/0! | N133: =(I133-E133)/ABS(E133) -> #DIV/0! | O133: =(J133-F133)/ABS(F133) -> #DIV/0! | P133: =(K133-G133)/ABS(G133) -> #DIV/0! | Q133: =(L133-H133)/ABS(H133) -> #DIV/0! | R133: =(SUM(J133:L133)-SUM(F133:H133))/ABS(SUM(F133:H133)) -> #DIV/0! | S133: =SUM(I133:L133)/SUM(E133:H133)-1 -> #DIV/0! | T133: =SUM(I133:L133) -> 0
A134: FUEFCV50 | B134: Quỹ ETF FPT CAPITAL VNX50 | C134: HOSE | L134: =VLOOKUP(A134,Sheet1!$A$1:$E$2000,5,FALSE) -> 0 | M134: =(H134-D134)/ABS(D134) -> #DIV/0! | N134: =(I134-E134)/ABS(E134) -> #DIV/0! | O134: =(J134-F134)/ABS(F134) -> #DIV/0! | P134: =(K134-G134)/ABS(G134) -> #DIV/0! | Q134: =(L134-H134)/ABS(H134) -> #DIV/0! | R134: =(SUM(J134:L134)-SUM(F134:H134))/ABS(SUM(F134:H134)) -> #DIV/0! | S134: =SUM(I134:L134)/SUM(E134:H134)-1 -> #DIV/0! | T134: =SUM(I134:L134) -> 0
A135: FUEIP100 | B135: Quỹ ETF IPAAM VN100 | C135: HOSE | L135: =VLOOKUP(A135,Sheet1!$A$1:$E$2000,5,FALSE) -> 0 | M135: =(H135-D135)/ABS(D135) -> #DIV/0! | N135: =(I135-E135)/ABS(E135) -> #DIV/0! | O135: =(J135-F135)/ABS(F135) -> #DIV/0! | P135: =(K135-G135)/ABS(G135) -> #DIV/0! | Q135: =(L135-H135)/ABS(H135) -> #DIV/0! | R135: =(SUM(J135:L135)-SUM(F135:H135))/ABS(SUM(F135:H135)) -> #DIV/0! | S135: =SUM(I135:L135)/SUM(E135:H135)-1 -> #DIV/0! | T135: =SUM(I135:L135) -> 0
A136: FUEKIV30 | B136: KIM GROWTH VN30 ETF | C136: HOSE | L136: =VLOOKUP(A136,Sheet1!$A$1:$E$2000,5,FALSE) -> 0 | M136: =(H136-D136)/ABS(D136) -> #DIV/0! | N136: =(I136-E136)/ABS(E136) -> #DIV/0! | O136: =(J136-F136)/ABS(F136) -> #DIV/0! | P136: =(K136-G136)/ABS(G136) -> #DIV/0! | Q136: =(L136-H136)/ABS(H136) -> #DIV/0! | R136: =(SUM(J136:L136)-SUM(F136:H136))/ABS(SUM(F136:H136)) -> #DIV/0! | S136: =SUM(I136:L136)/SUM(E136:H136)-1 -> #DIV/0! | T136: =SUM(I136:L136) -> 0
A137: FUEKIVFS | B137: KIM GROWTH VNFINSELECT ETF | C137: HOSE | L137: =VLOOKUP(A137,Sheet1!$A$1:$E$2000,5,FALSE) -> 0 | M137: =(H137-D137)/ABS(D137) -> #DIV/0! | N137: =(I137-E137)/ABS(E137) -> #DIV/0! | O137: =(J137-F137)/ABS(F137) -> #DIV/0! | P137: =(K137-G137)/ABS(G137) -> #DIV/0! | Q137: =(L137-H137)/ABS(H137) -> #DIV/0! | R137: =(SUM(J137:L137)-SUM(F137:H137))/ABS(SUM(F137:H137)) -> #DIV/0! | S137: =SUM(I137:L137)/SUM(E137:H137)-1 -> #DIV/0! | T137: =SUM(I137:L137) -> 0
A138: FUEKIVND | B138: Quỹ ETF KIM GROWTH VN DIAMOND | C138: HOSE | L138: =VLOOKUP(A138,Sheet1!$A$1:$E$2000,5,FALSE) -> 0 | M138: =(H138-D138)/ABS(D138) -> #DIV/0! | N138: =(I138-E138)/ABS(E138) -> #DIV/0! | O138: =(J138-F138)/ABS(F138) -> #DIV/0! | P138: =(K138-G138)/ABS(G138) -> #DIV/0! | Q138: =(L138-H138)/ABS(H138) -> #DIV/0! | R138: =(SUM(J138:L138)-SUM(F138:H138))/ABS(SUM(F138:H138)) -> #DIV/0! | S138: =SUM(I138:L138)/SUM(E138:H138)-1 -> #DIV/0! | T138: =SUM(I138:L138) -> 0
... A147: FUEVN100 | B147: Quỹ ETF VINACAPITAL VN100 | C147: HOSE | L147: =VLOOKUP(A147,Sheet1!$A$1:$E$2000,5,FALSE) -> 0 | M147: =(H147-D147)/ABS(D147) -> #DIV/0! | N147: =(I147-E147)/ABS(E147) -> #DIV/0! | O147: =(J147-F147)/ABS(F147) -> #DIV/0! | P147: =(K147-G147)/ABS(G147) -> #DIV/0! | Q147: =(L147-H147)/ABS(H147) -> #DIV/0! | R147: =(SUM(J147:L147)-SUM(F147:H147))/ABS(SUM(F147:H147)) -> #DIV/0! | S147: =SUM(I147:L147)/SUM(E147:H147)-1 -> #DIV/0! | T147: =SUM(I147:L147) -> 0
A148: GAS | B148: PV Gas | C148: HOSE | D148: 2511656345896 | E148: 3320816772236 | F148: 2521794493538 | G148: 2044102438055 | H148: 2756531237258 | I148: 4747605078583 | J148: 2549118933504 | K148: 1361084899485 | L148: =VLOOKUP(A148,Sheet1!$A$1:$E$2000,5,FALSE) -> 2944603136328 | M148: =(H148-D148)/ABS(D148) -> 0.097495381 | N148: =(I148-E148)/ABS(E148) -> 0.42964981 | O148: =(J148-F148)/ABS(F148) -> 0.010835316 | P148: =(K148-G148)/ABS(G148) -> -0.33414056 | Q148: =(L148-H148)/ABS(H148) -> 0.068227741 | R148: =(SUM(J148:L148)-SUM(F148:H148))/ABS(SUM(F148:H148)) -> -0.063861494 | S148: =SUM(I148:L148)/SUM(E148:H148)-1 -> 0.0901198 | T148: =SUM(I148:L148) -> 11602412047900
A149: GDT | B149: Gỗ Đức Thành | C149: HOSE | D149: 9518631896 | E149: 13198660942 | F149: 15809873009 | G149: 16210564299 | H149: 15762626381 | I149: 16164774865 | J149: 20627267262 | K149: 20949672542 | L149: =VLOOKUP(A149,Sheet1!$A$1:$E$2000,5,FALSE) -> 17175973951 | M149: =(H149-D149)/ABS(D149) -> 0.65597604 | N149: =(I149-E149)/ABS(E149) -> 0.2247284 | O149: =(J149-F149)/ABS(F149) -> 0.30470797 | P149: =(K149-G149)/ABS(G149) -> 0.2923469 | Q149: =(L149-H149)/ABS(H149) -> 0.089664472 | R149: =(SUM(J149:L149)-SUM(F149:H149))/ABS(SUM(F149:H149)) -> 0.22957611 | S149: =SUM(I149:L149)/SUM(E149:H149)-1 -> 0.22852689 | T149: =SUM(I149:L149) -> 74917688620
A150: GEE | B150: Thiết bị điện GELEX | C150: HOSE | D150: 104587813380 | E150: 516269394537 | F150: 388207174441 | G150: 586545613629 | H150: 451822818434 | I150: 528143582281 | J150: 1744031192174 | K150: 533381909940 | L150: =VLOOKUP(A150,Sheet1!$A$1:$E$2000,5,FALSE) -> 579385955223 | M150: =(H150-D150)/ABS(D150) -> 3.3200331 | N150: =(I150-E150)/ABS(E150) -> 0.022999984 | O150: =(J150-F150)/ABS(F150) -> 3.4925269 | P150: =(K150-G150)/ABS(G150) -> -0.090638652 | Q150: =(L150-H150)/ABS(H150) -> 0.28233 | R150: =(SUM(J150:L150)-SUM(F150:H150))/ABS(SUM(F150:H150)) -> 1.0025571 | S150: =SUM(I150:L150)/SUM(E150:H150)-1 -> 0.74226078 | T150: =SUM(I150:L150) -> 3384942639618
A151: GEG | B151: Điện Gia Lai | C151: HOSE | D151: 89662202743 | E151: 21460036310 | F151: -27338001098 | G151: 31038790590 | H151: 378240835561 | I151: 165820759376 | J151: 74645813663 | K151: 89814403200 | L151: =VLOOKUP(A151,Sheet1!$A$1:$E$2000,5,FALSE) -> 206675501563 | M151: =(H151-D151)/ABS(D151) -> 3.2185093 | N151: =(I151-E151)/ABS(E151) -> 6.7269561 | O151: =(J151-F151)/ABS(F151) -> 3.7304781 | P151: =(K151-G151)/ABS(G151) -> 1.893618 | Q151: =(L151-H151)/ABS(H151) -> -0.45358755 | R151: =(SUM(J151:L151)-SUM(F151:H151))/ABS(SUM(F151:H151)) -> -0.028292037 | S151: =SUM(I151:L151)/SUM(E151:H151)-1 -> 0.33107156 | T151: =SUM(I151:L151) -> 536956477802
A152: GEL | B152: Hạ tầng GELEX | C152: HOSE | H152: 91031680552 | I152: 319132898981 | J152: 27185549462 | K152: 43174332438 | L152: =VLOOKUP(A152,Sheet1!$A$1:$E$2000,5,FALSE) -> -199953913974 | M152: =(H152-D152)/ABS(D152) -> #DIV/0! | N152: =(I152-E152)/ABS(E152) -> #DIV/0! | O152: =(J152-F152)/ABS(F152) -> #DIV/0! | P152: =(K152-G152)/ABS(G152) -> #DIV/0! | Q152: =(L152-H152)/ABS(H152) -> -3.1965311 | R152: =(SUM(J152:L152)-SUM(F152:H152))/ABS(SUM(F152:H152)) -> -2.4236146 | S152: =SUM(I152:L152)/SUM(E152:H152)-1 -> 1.0821198 | T152: =SUM(I152:L152) -> 189538866907
A153: GEX | B153: Tập đoàn Gelex | C153: HOSE | D153: 108549790946 | E153: 849410458792 | F153: 98863822710 | G153: 574473871468 | H153: 233741873119 | I153: 656870926449 | J153: 621931709410 | K153: -34652979800 | L153: =VLOOKUP(A153,Sheet1!$A$1:$E$2000,5,FALSE) -> 245633005037 | M153: =(H153-D153)/ABS(D153) -> 1.1533148 | N153: =(I153-E153)/ABS(E153) -> -0.22667431 | O153: =(J153-F153)/ABS(F153) -> 5.2907916 | P153: =(K153-G153)/ABS(G153) -> -1.0603212 | Q153: =(L153-H153)/ABS(H153) -> 0.050872921 | R153: =(SUM(J153:L153)-SUM(F153:H153))/ABS(SUM(F153:H153)) -> -0.08176552 | S153: =SUM(I153:L153)/SUM(E153:H153)-1 -> -0.15184109 | T153: =SUM(I153:L153) -> 1489782661096
A154: GHC | B154: Thủy điện Gia Lai | C154: HOSE | D154: 31846575922 | E154: 32193811041 | F154: 48853149265 | G154: 68593675961 | H154: 51544150788 | I154: 32819010356 | J154: 39561650893 | K154: 44991958363 | L154: =VLOOKUP(A154,Sheet1!$A$1:$E$2000,5,FALSE) -> 48329465555 | M154: =(H154-D154)/ABS(D154) -> 0.61851468 | N154: =(I154-E154)/ABS(E154) -> 0.01941986 | O154: =(J154-F154)/ABS(F154) -> -0.19019241 | P154: =(K154-G154)/ABS(G154) -> -0.34408008 | Q154: =(L154-H154)/ABS(H154) -> -0.062367605 | R154: =(SUM(J154:L154)-SUM(F154:H154))/ABS(SUM(F154:H154)) -> -0.21366763 | S154: =SUM(I154:L154)/SUM(E154:H154)-1 -> -0.17636871 | T154: =SUM(I154:L154) -> 165702085167
A155: GIL | B155: XNK Bình Thạnh | C155: HOSE | D155: 5185964640 | E155: 3650321792 | F155: 2961041712 | G155: 14269833943 | H155: 2867000258 | I155: -70714915861 | J155: -32335610556 | K155: 131576065636 | L155: =VLOOKUP(A155,Sheet1!$A$1:$E$2000,5,FALSE) -> 10312986589 | M155: =(H155-D155)/ABS(D155) -> -0.44716163 | N155: =(I155-E155)/ABS(E155) -> -20.372242 | O155: =(J155-F155)/ABS(F155) -> -11.92035 | P155: =(K155-G155)/ABS(G155) -> 8.2205744 | Q155: =(L155-H155)/ABS(H155) -> 2.5971349 | R155: =(SUM(J155:L155)-SUM(F155:H155))/ABS(SUM(F155:H155)) -> 4.450996 | S155: =SUM(I155:L155)/SUM(E155:H155)-1 -> 0.63543046 | T155: =SUM(I155:L155) -> 38838525808
A156: GMD | B156: Gemadept | C156: HOSE | D156: 559415059763 | E156: 330356887390 | F156: 335047467056 | G156: 230660181393 | H156: 402975060813 | I156: 445261803844 | J156: 315208520917 | K156: 592184439722 | L156: =VLOOKUP(A156,Sheet1!$A$1:$E$2000,5,FALSE) -> 534243825954 | M156: =(H156-D156)/ABS(D156) -> -0.27964924 | N156: =(I156-E156)/ABS(E156) -> 0.34782056 | O156: =(J156-F156)/ABS(F156) -> -0.059212345 | P156: =(K156-G156)/ABS(G156) -> 1.5673458 | Q156: =(L156-H156)/ABS(H156) -> 0.3257491 | R156: =(SUM(J156:L156)-SUM(F156:H156))/ABS(SUM(F156:H156)) -> 0.48824457 | S156: =SUM(I156:L156)/SUM(E156:H156)-1 -> 0.45253355 | T156: =SUM(I156:L156) -> 1886898590437
A157: GMH | B157: Minh Hưng Quảng Trị | C157: HOSE | D157: 98837334 | E157: 1103794595 | F157: 2764772789 | G157: 1988279652 | H157: 2006724950 | I157: 5887477412 | J157: 5326410042 | K157: 4599758168 | L157: =VLOOKUP(A157,Sheet1!$A$1:$E$2000,5,FALSE) -> 2361195397 | M157: =(H157-D157)/ABS(D157) -> 19.303309 | N157: =(I157-E157)/ABS(E157) -> 4.3338524 | O157: =(J157-F157)/ABS(F157) -> 0.92652722 | P157: =(K157-G157)/ABS(G157) -> 1.3134362 | Q157: =(L157-H157)/ABS(H157) -> 0.17664127 | R157: =(SUM(J157:L157)-SUM(F157:H157))/ABS(SUM(F157:H157)) -> 0.8177172 | S157: =SUM(I157:L157)/SUM(E157:H157)-1 -> 1.3112704 | T157: =SUM(I157:L157) -> 18174841019
A158: GSP | B158: Vận tải Sản phẩm Khí Quốc tế | C158: HOSE | D158: 28829736426 | E158: 31141529483 | F158: 27611968079 | G158: 13084898011 | H158: 29628785414 | I158: 26794089799 | J158: 2852501225 | K158: 37647023487 | L158: =VLOOKUP(A158,Sheet1!$A$1:$E$2000,5,FALSE) -> 26370541110 | M158: =(H158-D158)/ABS(D158) -> 0.027716139 | N158: =(I158-E158)/ABS(E158) -> -0.13960264 | O158: =(J158-F158)/ABS(F158) -> -0.8966933 | P158: =(K158-G158)/ABS(G158) -> 1.8771354 | Q158: =(L158-H158)/ABS(H158) -> -0.10996888 | R158: =(SUM(J158:L158)-SUM(F158:H158))/ABS(SUM(F158:H158)) -> -0.049136917 | S158: =SUM(I158:L158)/SUM(E158:H158)-1 -> -0.076901963 | T158: =SUM(I158:L158) -> 93664155621
A159: GTA | B159: Gỗ Thuận An | C159: HOSE | D159: 1697525663 | E159: 2071818630 | F159: 2283488732 | G159: 2501984275 | H159: 1281050903 | I159: 1279895546 | J159: 1851558617 | K159: 1540749566 | L159: =VLOOKUP(A159,Sheet1!$A$1:$E$2000,5,FALSE) -> 1830907382 | M159: =(H159-D159)/ABS(D159) -> -0.24534225 | N159: =(I159-E159)/ABS(E159) -> -0.38223572 | O159: =(J159-F159)/ABS(F159) -> -0.1891536 | P159: =(K159-G159)/ABS(G159) -> -0.38418895 | Q159: =(L159-H159)/ABS(H159) -> 0.42922297 | R159: =(SUM(J159:L159)-SUM(F159:H159))/ABS(SUM(F159:H159)) -> -0.13901014 | S159: =SUM(I159:L159)/SUM(E159:H159)-1 -> -0.20092929 | T159: =SUM(I159:L159) -> 6503111111
A160: GVR | B160: Tập đoàn CN Cao su VN | C160: HOSE | D160: 475562877828 | E160: 820840325114 | F160: 943784293874 | G160: 1748529121666 | H160: 1184647986486 | I160: 1446811095857 | J160: 1897263225431 | K160: 694400435899 | L160: =VLOOKUP(A160,Sheet1!$A$1:$E$2000,5,FALSE) -> 2250751648382 | M160: =(H160-D160)/ABS(D160) -> 1.4910439 | N160: =(I160-E160)/ABS(E160) -> 0.76259749 | O160: =(J160-F160)/ABS(F160) -> 1.0102721 | P160: =(K160-G160)/ABS(G160) -> -0.60286596 | Q160: =(L160-H160)/ABS(H160) -> 0.89993287 | R160: =(SUM(J160:L160)-SUM(F160:H160))/ABS(SUM(F160:H160)) -> 0.24902335 | S160: =SUM(I160:L160)/SUM(E160:H160)-1 -> 0.33875944 | T160: =SUM(I160:L160) -> 6289226405569
A161: HAG | B161: Hoàng Anh Gia Lai | C161: HOSE | D161: 214881967000 | E161: 262667182000 | F161: 331598452000 | G161: 204285482000 | H161: 340703653000 | I161: 492902796000 | J161: 415963585000 | K161: 873238738000 | L161: =VLOOKUP(A161,Sheet1!$A$1:$E$2000,5,FALSE) -> 1125563507000 | M161: =(H161-D161)/ABS(D161) -> 0.5855386 | N161: =(I161-E161)/ABS(E161) -> 0.87652981 | O161: =(J161-F161)/ABS(F161) -> 0.25441956 | P161: =(K161-G161)/ABS(G161) -> 3.2746001 | Q161: =(L161-H161)/ABS(H161) -> 2.3036438 | R161: =(SUM(J161:L161)-SUM(F161:H161))/ABS(SUM(F161:H161)) -> 1.7547342 | S161: =SUM(I161:L161)/SUM(E161:H161)-1 -> 1.552255 | T161: =SUM(I161:L161) -> 2907668626000
A162: HAH | B162: Vận tải và Xếp dỡ Hải An | C162: HOSE | D162: 59241900591 | E162: 111818835524 | F162: 199250186229 | G162: 280188389723 | H162: 233230747605 | I162: 361617919453 | J162: 304048751153 | K162: 307615382771 | L162: =VLOOKUP(A162,Sheet1!$A$1:$E$2000,5,FALSE) -> 299995432719 | M162: =(H162-D162)/ABS(D162) -> 2.9369221 | N162: =(I162-E162)/ABS(E162) -> 2.2339625 | O162: =(J162-F162)/ABS(F162) -> 0.5259647 | P162: =(K162-G162)/ABS(G162) -> 0.097887686 | Q162: =(L162-H162)/ABS(H162) -> 0.28626022 | R162: =(SUM(J162:L162)-SUM(F162:H162))/ABS(SUM(F162:H162)) -> 0.2792182 | S162: =SUM(I162:L162)/SUM(E162:H162)-1 -> 0.54432477 | T162: =SUM(I162:L162) -> 1273277486096
A163: HAP | B163: Tập đoàn Hapaco | C163: HOSE | D163: 2281842327 | E163: 2887356312 | F163: -73529623 | G163: 96654825810 | H163: -8704166972 | I163: -4741275483 | J163: 3154927816 | K163: -95522269845 | L163: =VLOOKUP(A163,Sheet1!$A$1:$E$2000,5,FALSE) -> 4144854525 | M163: =(H163-D163)/ABS(D163) -> -4.8145348 | N163: =(I163-E163)/ABS(E163) -> -2.6420819 | O163: =(J163-F163)/ABS(F163) -> 43.906895 | P163: =(K163-G163)/ABS(G163) -> -1.9882825 | Q163: =(L163-H163)/ABS(H163) -> 1.476192 | R163: =(SUM(J163:L163)-SUM(F163:H163))/ABS(SUM(F163:H163)) -> -2.00393 | S163: =SUM(I163:L163)/SUM(E163:H163)-1 -> -2.0242306 | T163: =SUM(I163:L163) -> -92963762987
A164: HAR | B164: BĐS An Dương Thảo Điền | C164: HOSE | D164: 3160976506 | E164: 1999261188 | F164: 2355633115 | G164: 2341418861 | H164: 7175188643 | I164: 2800360746 | J164: 5768862239 | K164: 1407426936 | L164: =VLOOKUP(A164,Sheet1!$A$1:$E$2000,5,FALSE) -> 1919194563 | M164: =(H164-D164)/ABS(D164) -> 1.2699279 | N164: =(I164-E164)/ABS(E164) -> 0.4006978 | O164: =(J164-F164)/ABS(F164) -> 1.4489647 | P164: =(K164-G164)/ABS(G164) -> -0.39889997 | Q164: =(L164-H164)/ABS(H164) -> -0.73252347 | R164: =(SUM(J164:L164)-SUM(F164:H164))/ABS(SUM(F164:H164)) -> -0.23388651 | S164: =SUM(I164:L164)/SUM(E164:H164)-1 -> -0.14242563 | T164: =SUM(I164:L164) -> 11895844484
... A178: HNA | B178: Thủy điện Hủa Na | C178: HOSE | D178: -3789910609 | E178: -10084690870 | F178: 184926080205 | G178: 98701253472 | H178: 40540494503 | I178: 92958566505 | J178: 245380980921 | K178: 96933365683 | L178: =VLOOKUP(A178,Sheet1!$A$1:$E$2000,5,FALSE) -> 94808100134 | M178: =(H178-D178)/ABS(D178) -> 11.696953 | N178: =(I178-E178)/ABS(E178) -> 10.21779 | O178: =(J178-F178)/ABS(F178) -> 0.32691387 | P178: =(K178-G178)/ABS(G178) -> -0.017911503 | Q178: =(L178-H178)/ABS(H178) -> 1.3386025 | R178: =(SUM(J178:L178)-SUM(F178:H178))/ABS(SUM(F178:H178)) -> 0.34844488 | S178: =SUM(I178:L178)/SUM(E178:H178)-1 -> 0.68770924 | T178: =SUM(I178:L178) -> 530081013243
A179: HPA | B179: Phát triển Nông nghiệp Hoà Phát | C179: HOSE | J179: 358374771824 | K179: 301886798172 | L179: =VLOOKUP(A179,Sheet1!$A$1:$E$2000,5,FALSE) -> 337072507705 | M179: =(H179-D179)/ABS(D179) -> #DIV/0! | N179: =(I179-E179)/ABS(E179) -> #DIV/0! | O179: =(J179-F179)/ABS(F179) -> #DIV/0! | P179: =(K179-G179)/ABS(G179) -> #DIV/0! | Q179: =(L179-H179)/ABS(H179) -> #DIV/0! | R179: =(SUM(J179:L179)-SUM(F179:H179))/ABS(SUM(F179:H179)) -> #DIV/0! | S179: =SUM(I179:L179)/SUM(E179:H179)-1 -> #DIV/0! | T179: =SUM(I179:L179) -> 997334077701
A180: HPG | B180: Hòa Phát | C180: HOSE | D180: 2870588692991 | E180: 3319263141862 | F180: 3022946632050 | G180: 2808645369171 | H180: 3344284694388 | I180: 4256487211764 | J180: 3988318474539 | K180: 3864083625532 | L180: =VLOOKUP(A180,Sheet1!$A$1:$E$2000,5,FALSE) -> 8994003244142 | M180: =(H180-D180)/ABS(D180) -> 0.16501702 | N180: =(I180-E180)/ABS(E180) -> 0.28235907 | O180: =(J180-F180)/ABS(F180) -> 0.31934796 | P180: =(K180-G180)/ABS(G180) -> 0.37578196 | Q180: =(L180-H180)/ABS(H180) -> 1.6893653 | R180: =(SUM(J180:L180)-SUM(F180:H180))/ABS(SUM(F180:H180)) -> 0.83594504 | S180: =SUM(I180:L180)/SUM(E180:H180)-1 -> 0.68888807 | T180: =SUM(I180:L180) -> 21102892555977
A181: HPX | B181: Đầu tư Hải Phát | C181: HOSE | D181: 16849429188 | E181: 29021973013 | F181: 10540753453 | G181: 1034595619 | H181: 14462552677 | I181: 33071516404 | J181: 5803292158 | K181: 67997394594 | L181: =VLOOKUP(A181,Sheet1!$A$1:$E$2000,5,FALSE) -> 8895921491 | M181: =(H181-D181)/ABS(D181) -> -0.14165919 | N181: =(I181-E181)/ABS(E181) -> 0.1395337 | O181: =(J181-F181)/ABS(F181) -> -0.44944238 | P181: =(K181-G181)/ABS(G181) -> 64.723644 | Q181: =(L181-H181)/ABS(H181) -> -0.38489963 | R181: =(SUM(J181:L181)-SUM(F181:H181))/ABS(SUM(F181:H181)) -> 2.1760089 | S181: =SUM(I181:L181)/SUM(E181:H181)-1 -> 1.1025861 | T181: =SUM(I181:L181) -> 115768124647
A182: HQC | B182: Địa ốc Hoàng Quân | C182: HOSE | D182: 5244660344 | E182: 10207675457 | F182: 11183555726 | G182: 7111930907 | H182: 5156449564 | I182: 4211666572 | J182: 8754354738 | K182: 52114430102 | L182: =VLOOKUP(A182,Sheet1!$A$1:$E$2000,5,FALSE) -> 5397810347 | M182: =(H182-D182)/ABS(D182) -> -0.01681916 | N182: =(I182-E182)/ABS(E182) -> -0.58740199 | O182: =(J182-F182)/ABS(F182) -> -0.21721186 | P182: =(K182-G182)/ABS(G182) -> 6.327747 | Q182: =(L182-H182)/ABS(H182) -> 0.046807552 | R182: =(SUM(J182:L182)-SUM(F182:H182))/ABS(SUM(F182:H182)) -> 1.8256343 | S182: =SUM(I182:L182)/SUM(E182:H182)-1 -> 1.0938525 | T182: =SUM(I182:L182) -> 70478261759
A183: HRC | B183: Cao su Hòa Bình | C183: HOSE | D183: 412118474 | E183: 499192518 | F183: 5961278241 | G183: 54528527102 | H183: 1427631593 | I183: 3322067066 | J183: 22043884065 | K183: 8336134003 | L183: =VLOOKUP(A183,Sheet1!$A$1:$E$2000,5,FALSE) -> 7018919559 | M183: =(H183-D183)/ABS(D183) -> 2.4641291 | N183: =(I183-E183)/ABS(E183) -> 5.6548815 | O183: =(J183-F183)/ABS(F183) -> 2.6978452 | P183: =(K183-G183)/ABS(G183) -> -0.84712343 | Q183: =(L183-H183)/ABS(H183) -> 3.9164782 | R183: =(SUM(J183:L183)-SUM(F183:H183))/ABS(SUM(F183:H183)) -> -0.39598699 | S183: =SUM(I183:L183)/SUM(E183:H183)-1 -> -0.34759366 | T183: =SUM(I183:L183) -> 40721004693
A184: HSG | B184: Tập đoàn Hoa Sen | C184: HOSE | D184: 319216940456 | E184: 273403232357 | F184: -181337615457 | G184: 165527075204 | H184: 207513590553 | I184: 273775396195 | J184: 88202714253 | K184: 62402209404 | L184: =VLOOKUP(A184,Sheet1!$A$1:$E$2000,5,FALSE) -> 118713117160 | M184: =(H184-D184)/ABS(D184) -> -0.34992927 | N184: =(I184-E184)/ABS(E184) -> 0.0013612269 | O184: =(J184-F184)/ABS(F184) -> 1.4864005 | P184: =(K184-G184)/ABS(G184) -> -0.62300905 | Q184: =(L184-H184)/ABS(H184) -> -0.42792606 | R184: =(SUM(J184:L184)-SUM(F184:H184))/ABS(SUM(F184:H184)) -> 0.40487092 | S184: =SUM(I184:L184)/SUM(E184:H184)-1 -> 0.16767599 | T184: =SUM(I184:L184) -> 543093437012
A185: HSL | B185: Thực phẩm Hồng Hà | C185: HOSE | D185: 1939489075 | E185: 2841092386 | F185: 1238232049 | G185: 739266614 | H185: 2881668941 | I185: -1998598565 | J185: 214366938 | K185: -1081825339 | L185: =VLOOKUP(A185,Sheet1!$A$1:$E$2000,5,FALSE) -> 6940580533 | M185: =(H185-D185)/ABS(D185) -> 0.48578766 | N185: =(I185-E185)/ABS(E185) -> -1.7034613 | O185: =(J185-F185)/ABS(F185) -> -0.8268766 | P185: =(K185-G185)/ABS(G185) -> -2.4633764 | Q185: =(L185-H185)/ABS(H185) -> 1.4085281 | R185: =(SUM(J185:L185)-SUM(F185:H185))/ABS(SUM(F185:H185)) -> 0.24982767 | S185: =SUM(I185:L185)/SUM(E185:H185)-1 -> -0.47085896 | T185: =SUM(I185:L185) -> 4074523567
A186: HT1 | B186: VICEM Hà Tiên | C186: HOSE | D186: -24690376381 | E186: 45841083871 | F186: 22548789895 | G186: 16446683084 | H186: -9178231932 | I186: 112331797360 | J186: 85661459262 | K186: 84918592190 | L186: =VLOOKUP(A186,Sheet1!$A$1:$E$2000,5,FALSE) -> 77839942401 | M186: =(H186-D186)/ABS(D186) -> 0.62826683 | N186: =(I186-E186)/ABS(E186) -> 1.4504612 | O186: =(J186-F186)/ABS(F186) -> 2.7989382 | P186: =(K186-G186)/ABS(G186) -> 4.1632656 | Q186: =(L186-H186)/ABS(H186) -> 9.48093 | R186: =(SUM(J186:L186)-SUM(F186:H186))/ABS(SUM(F186:H186)) -> 7.3314212 | S186: =SUM(I186:L186)/SUM(E186:H186)-1 -> 3.7681705 | T186: =SUM(I186:L186) -> 360751791213
A187: HTG | B187: Dệt may Hòa Thọ | C187: HOSE | D187: 45143710261 | E187: 70007357984 | F187: 73396789736 | G187: 92370083399 | H187: 56205479152 | I187: 129014748818 | J187: 78541147325 | K187: 52844870055 | L187: =VLOOKUP(A187,Sheet1!$A$1:$E$2000,5,FALSE) -> 63689186995 | M187: =(H187-D187)/ABS(D187) -> 0.24503455 | N187: =(I187-E187)/ABS(E187) -> 0.84287413 | O187: =(J187-F187)/ABS(F187) -> 0.070089681 | P187: =(K187-G187)/ABS(G187) -> -0.42790059 | Q187: =(L187-H187)/ABS(H187) -> 0.13314908 | R187: =(SUM(J187:L187)-SUM(F187:H187))/ABS(SUM(F187:H187)) -> -0.12117341 | S187: =SUM(I187:L187)/SUM(E187:H187)-1 -> 0.10997423 | T187: =SUM(I187:L187) -> 324089953193
A188: HTI | B188: PT Hạ tầng IDICO | C188: HOSE | D188: 14737199844 | E188: 16689721627 | F188: 16030929366 | G188: 16324622042 | H188: 58889163657 | I188: 37147553496 | J188: 28108853203 | K188: 45282491093 | L188: =VLOOKUP(A188,Sheet1!$A$1:$E$2000,5,FALSE) -> 29903991567 | M188: =(H188-D188)/ABS(D188) -> 2.9959534 | N188: =(I188-E188)/ABS(E188) -> 1.2257743 | O188: =(J188-F188)/ABS(F188) -> 0.75341383 | P188: =(K188-G188)/ABS(G188) -> 1.7738768 | Q188: =(L188-H188)/ABS(H188) -> -0.49219874 | R188: =(SUM(J188:L188)-SUM(F188:H188))/ABS(SUM(F188:H188)) -> 0.13206925 | S188: =SUM(I188:L188)/SUM(E188:H188)-1 -> 0.30118703 | T188: =SUM(I188:L188) -> 140442889359
A189: HTL | B189: Ô tô Trường Long | C189: HOSE | D189: 2603340156 | E189: 10684224855 | F189: 6328632061 | G189: 3558358419 | H189: 3773142555 | I189: 4673904647 | J189: 4906768345 | K189: 11541303663 | L189: =VLOOKUP(A189,Sheet1!$A$1:$E$2000,5,FALSE) -> 6278137017 | M189: =(H189-D189)/ABS(D189) -> 0.44934673 | N189: =(I189-E189)/ABS(E189) -> -0.56254153 | O189: =(J189-F189)/ABS(F189) -> -0.22467157 | P189: =(K189-G189)/ABS(G189) -> 2.2434348 | Q189: =(L189-H189)/ABS(H189) -> 0.66390136 | R189: =(SUM(J189:L189)-SUM(F189:H189))/ABS(SUM(F189:H189)) -> 0.6636887 | S189: =SUM(I189:L189)/SUM(E189:H189)-1 -> 0.12552214 | T189: =SUM(I189:L189) -> 27400113672
A190: HTN | B190: Hưng Thịnh Incons | C190: HOSE | D190: 10267824527 | E190: 2919419842 | F190: 376959760 | G190: 11712322720 | H190: 27354793013 | I190: 16630482225 | J190: 1875571970 | K190: -27460274573 | L190: =VLOOKUP(A190,Sheet1!$A$1:$E$2000,5,FALSE) -> 0 | M190: =(H190-D190)/ABS(D190) -> 1.6641274 | N190: =(I190-E190)/ABS(E190) -> 4.6965024 | O190: =(J190-F190)/ABS(F190) -> 3.975523 | P190: =(K190-G190)/ABS(G190) -> -3.3445627 | Q190: =(L190-H190)/ABS(H190) -> -1 | R190: =(SUM(J190:L190)-SUM(F190:H190))/ABS(SUM(F190:H190)) -> -1.6486323 | S190: =SUM(I190:L190)/SUM(E190:H190)-1 -> -1.2113664 | T190: =SUM(I190:L190) -> -8954220378
A191: HTV | B191: Logistics Vicem | C191: HOSE | D191: -124970624 | E191: 3890008739 | F191: 2695739001 | G191: 2711127636 | H191: 3565040425 | I191: 5442706960 | J191: 4313941362 | K191: 2542614193 | L191: =VLOOKUP(A191,Sheet1!$A$1:$E$2000,5,FALSE) -> 5207112801 | M191: =(H191-D191)/ABS(D191) -> 29.527027 | N191: =(I191-E191)/ABS(E191) -> 0.39915032 | O191: =(J191-F191)/ABS(F191) -> 0.60028154 | P191: =(K191-G191)/ABS(G191) -> -0.062156219 | Q191: =(L191-H191)/ABS(H191) -> 0.46060414 | R191: =(SUM(J191:L191)-SUM(F191:H191))/ABS(SUM(F191:H191)) -> 0.34460469 | S191: =SUM(I191:L191)/SUM(E191:H191)-1 -> 0.36110169 | T191: =SUM(I191:L191) -> 17506375316
... A336: TCB | B336: Techcombank | C336: HOSE | D336: 6220997000000 | E336: 6193361000000 | F336: 5737505000000 | G336: 3371065000000 | H336: 5947960000000 | I336: 6247364000000 | J336: 6419344000000 | K336: 6675562000000 | L336: =VLOOKUP(A336,Sheet1!$A$1:$E$2000,5,FALSE) -> 6671081000000 | M336: =(H336-D336)/ABS(D336) -> -0.043889589 | N336: =(I336-E336)/ABS(E336) -> 0.0087194982 | O336: =(J336-F336)/ABS(F336) -> 0.11883894 | P336: =(K336-G336)/ABS(G336) -> 0.98025312 | Q336: =(L336-H336)/ABS(H336) -> 0.12157462 | R336: =(SUM(J336:L336)-SUM(F336:H336))/ABS(SUM(F336:H336)) -> 0.31278502 | S336: =SUM(I336:L336)/SUM(E336:H336)-1 -> 0.22416397 | T336: =SUM(I336:L336) -> 26013351000000
A337: TCD | B337: Tập đoàn Xây dựng Tracodi | C337: HOSE | D337: 13625350084 | E337: 18204691187 | F337: 10142850935 | G337: 29146813936 | L337: =VLOOKUP(A337,Sheet1!$A$1:$E$2000,5,FALSE) -> 0 | M337: =(H337-D337)/ABS(D337) -> -1 | N337: =(I337-E337)/ABS(E337) -> -1 | O337: =(J337-F337)/ABS(F337) -> -1 | P337: =(K337-G337)/ABS(G337) -> -1 | Q337: =(L337-H337)/ABS(H337) -> #DIV/0! | R337: =(SUM(J337:L337)-SUM(F337:H337))/ABS(SUM(F337:H337)) -> -1 | S337: =SUM(I337:L337)/SUM(E337:H337)-1 -> -1 | T337: =SUM(I337:L337) -> 0
A338: TCH | B338: ĐT DV Tài chính Hoàng Huy | C338: HOSE | D338: 312339857371 | E338: 141007679311 | F338: 219749375038 | G338: 306557624618 | H338: 187679488696 | I338: 37872945883 | J338: 40214422757 | K338: 52425165780 | L338: =VLOOKUP(A338,Sheet1!$A$1:$E$2000,5,FALSE) -> 63858214051 | M338: =(H338-D338)/ABS(D338) -> -0.39911771 | N338: =(I338-E338)/ABS(E338) -> -0.73141218 | O338: =(J338-F338)/ABS(F338) -> -0.81699869 | P338: =(K338-G338)/ABS(G338) -> -0.82898757 | Q338: =(L338-H338)/ABS(H338) -> -0.65974857 | R338: =(SUM(J338:L338)-SUM(F338:H338))/ABS(SUM(F338:H338)) -> -0.78081125 | S338: =SUM(I338:L338)/SUM(E338:H338)-1 -> -0.77266424 | T338: =SUM(I338:L338) -> 194370748471
A339: TCI | B339: Chứng khoán Thành Công | C339: HOSE | D339: 22618976611 | E339: 11664432106 | F339: 21382849789 | G339: 1074314800 | H339: 23536654674 | I339: 17339310075 | J339: 71708080368 | K339: -91807242053 | L339: =VLOOKUP(A339,Sheet1!$A$1:$E$2000,5,FALSE) -> 528572556 | M339: =(H339-D339)/ABS(D339) -> 0.040571158 | N339: =(I339-E339)/ABS(E339) -> 0.48651129 | O339: =(J339-F339)/ABS(F339) -> 2.3535324 | P339: =(K339-G339)/ABS(G339) -> -86.456555 | Q339: =(L339-H339)/ABS(H339) -> -0.97754258 | R339: =(SUM(J339:L339)-SUM(F339:H339))/ABS(SUM(F339:H339)) -> -1.4255048 | S339: =SUM(I339:L339)/SUM(E339:H339)-1 -> -1.0386983 | T339: =SUM(I339:L339) -> -2231279054
A340: TCL | B340: Tan Cang Logistics | C340: HOSE | D340: 19887810110 | E340: 49215783625 | F340: 29746847077 | G340: 44771570306 | H340: 26320893053 | I340: 54790100423 | J340: 33983741150 | K340: 48895880214 | L340: =VLOOKUP(A340,Sheet1!$A$1:$E$2000,5,FALSE) -> 31357668879 | M340: =(H340-D340)/ABS(D340) -> 0.32346864 | N340: =(I340-E340)/ABS(E340) -> 0.11326279 | O340: =(J340-F340)/ABS(F340) -> 0.1424317 | P340: =(K340-G340)/ABS(G340) -> 0.092118947 | Q340: =(L340-H340)/ABS(H340) -> 0.19136037 | R340: =(SUM(J340:L340)-SUM(F340:H340))/ABS(SUM(F340:H340)) -> 0.13286465 | S340: =SUM(I340:L340)/SUM(E340:H340)-1 -> 0.12643554 | T340: =SUM(I340:L340) -> 169027390666
A341: TCM | B341: Dệt may Thành Công | C341: HOSE | D341: 62169419003 | E341: 71882138261 | F341: 81090328840 | G341: 60922402375 | H341: 78305248101 | I341: 81426472945 | J341: 63311718953 | K341: 46019334094 | L341: =VLOOKUP(A341,Sheet1!$A$1:$E$2000,5,FALSE) -> 65790907904 | M341: =(H341-D341)/ABS(D341) -> 0.25954608 | N341: =(I341-E341)/ABS(E341) -> 0.13277756 | O341: =(J341-F341)/ABS(F341) -> -0.21924452 | P341: =(K341-G341)/ABS(G341) -> -0.24462378 | Q341: =(L341-H341)/ABS(H341) -> -0.15981483 | R341: =(SUM(J341:L341)-SUM(F341:H341))/ABS(SUM(F341:H341)) -> -0.20513995 | S341: =SUM(I341:L341)/SUM(E341:H341)-1 -> -0.12201119 | T341: =SUM(I341:L341) -> 256548433896
A342: TCO | B342: Janus Group | C342: HOSE | D342: 8668097769 | E342: 1714906160 | F342: 5298708786 | G342: 5022901131 | H342: 33223371496 | I342: 3554417834 | J342: 563312598 | K342: 172490212 | L342: =VLOOKUP(A342,Sheet1!$A$1:$E$2000,5,FALSE) -> 9446136941 | M342: =(H342-D342)/ABS(D342) -> 2.832833 | N342: =(I342-E342)/ABS(E342) -> 1.0726603 | O342: =(J342-F342)/ABS(F342) -> -0.8936887 | P342: =(K342-G342)/ABS(G342) -> -0.96565925 | Q342: =(L342-H342)/ABS(H342) -> -0.71567795 | R342: =(SUM(J342:L342)-SUM(F342:H342))/ABS(SUM(F342:H342)) -> -0.76617421 | S342: =SUM(I342:L342)/SUM(E342:H342)-1 -> -0.6965004 | T342: =SUM(I342:L342) -> 13736357585
A343: TCR | B343: Gốm sứ TAICERA | C343: HOSE | D343: -17814540694 | E343: -7899129171 | F343: -20008519802 | G343: -15347317265 | H343: -20401991825 | I343: -22306864724 | J343: -2747850407 | K343: 46791811592 | L343: =VLOOKUP(A343,Sheet1!$A$1:$E$2000,5,FALSE) -> -20501349578 | M343: =(H343-D343)/ABS(D343) -> -0.14524377 | N343: =(I343-E343)/ABS(E343) -> -1.8239651 | O343: =(J343-F343)/ABS(F343) -> 0.86266598 | P343: =(K343-G343)/ABS(G343) -> 4.0488593 | Q343: =(L343-H343)/ABS(H343) -> -0.0048700026 | R343: =(SUM(J343:L343)-SUM(F343:H343))/ABS(SUM(F343:H343)) -> 1.4222297 | S343: =SUM(I343:L343)/SUM(E343:H343)-1 -> -1.0194126 | T343: =SUM(I343:L343) -> 1235746883
A344: TCT | B344: Cáp treo Tây Ninh | C344: HOSE | D344: 8426013077 | E344: 2431002187 | F344: 278397834 | G344: -318734206 | H344: 12500247560 | I344: 5540027926 | J344: 5972253970 | K344: 1484024039 | L344: =VLOOKUP(A344,Sheet1!$A$1:$E$2000,5,FALSE) -> 8843522648 | M344: =(H344-D344)/ABS(D344) -> 0.48353052 | N344: =(I344-E344)/ABS(E344) -> 1.278907 | O344: =(J344-F344)/ABS(F344) -> 20.452229 | P344: =(K344-G344)/ABS(G344) -> 5.6559924 | Q344: =(L344-H344)/ABS(H344) -> -0.2925322 | R344: =(SUM(J344:L344)-SUM(F344:H344))/ABS(SUM(F344:H344)) -> 0.30817952 | S344: =SUM(I344:L344)/SUM(E344:H344)-1 -> 0.46665473 | T344: =SUM(I344:L344) -> 21839828583
A345: TCX | B345: Chứng khoán TCBS | C345: HOSE | D345: 928361810305 | E345: 1297455468843 | F345: 877641662378 | G345: 746235982045 | H345: 1010650893521 | I345: 1420073829884 | J345: 1619525402589 | K345: 1633078729114 | L345: =VLOOKUP(A345,Sheet1!$A$1:$E$2000,5,FALSE) -> 1147633429492 | M345: =(H345-D345)/ABS(D345) -> 0.088639022 | N345: =(I345-E345)/ABS(E345) -> 0.094506797 | O345: =(J345-F345)/ABS(F345) -> 0.84531509 | P345: =(K345-G345)/ABS(G345) -> 1.1884213 | Q345: =(L345-H345)/ABS(H345) -> 0.13553893 | R345: =(SUM(J345:L345)-SUM(F345:H345))/ABS(SUM(F345:H345)) -> 0.67021822 | S345: =SUM(I345:L345)/SUM(E345:H345)-1 -> 0.48024798 | T345: =SUM(I345:L345) -> 5820311391079
...

Sheet Sheet1
A1: AAA | B1: An Phát Bioplastics | C1: HOSE | E1: 153668061513
A2: AAM | B2: Thủy sản Mekong | C2: HOSE | E2: 2387603772
A3: AAT | B3: Tập đoàn Tiên Sơn Thanh Hóa | C3: HOSE | E3: 490938501
A4: ABR | B4: Đầu tư Nhãn Hiệu Việt | C4: HOSE | E4: 2370604829
A5: ABS | B5: DV Nông nghiệp Bình Thuận | C5: HOSE | E5: -1741076711
A6: ABT | B6: Thủy sản Bến Tre | C6: HOSE | E6: 22273623047
A7: ACB | B7: ACB | C7: HOSE | E7: 4320388000000
A8: ACC | B8: Đầu tư và XD Bình Dương ACC | C8: HOSE | E8: 5708706572
A9: ACG | B9: Gỗ An Cường | C9: HOSE | E9: 111902787167
A10: ACL | B10: Thủy sản CL An Giang | C10: HOSE | E10: 3439078053
A11: ADG | B11: Clever Group | C11: HOSE
A12: ADP | B12: Sơn Á Đông | C12: HOSE | E12: 15837757005
A13: ADS | B13: Dệt sợi DAMSAN | C13: HOSE | E13: 13692968898
A14: AFX | B14: XNK Nông sản Thực phẩm An Giang | C14: HOSE | E14: 18038047215
A15: AGG | B15: Bất động sản An Gia | C15: HOSE | E15: 5015102306
A16: AGR | B16: Agriseco | C16: HOSE | E16: 43488851532
A17: ANT | B17: Rau quả thực phẩm An Giang | C17: HOSE
A18: ANV | B18: Thủy sản Nam Việt | C18: HOSE | E18: 195357833650
A19: APG | B19: Chứng khoán APG | C19: HOSE | E19: 6491373937
A20: APH | B20: Tập đoàn An Phát Holdings | C20: HOSE | E20: 64953188489
A21: ASG | B21: Tập đoàn ASG | C21: HOSE | E21: 49192870182
A22: ASM | B22: Tập đoàn Sao Mai | C22: HOSE | E22: 84641615013
A23: ASP | B23: Dầu khí An Pha | C23: HOSE | E23: 45797129582
A24: AST | B24: Dịch vụ Hàng không Taseco | C24: HOSE | E24: 100919143835
A25: ATP | B25: T.Mại và DV An Thành | C25: HOSE
A26: BAF | B26: Nông nghiệp BAF Việt Nam | C26: HOSE | E26: 206000611406
A27: BCE | B27: XD và GT Bình Dương | C27: HOSE | E27: -21356676077
A28: BCG | B28: Bamboo Capital | C28: HOSE
A29: BCM | B29: Becamex Group | C29: HOSE | E29: 279562828161
A30: BFC | B30: Phân bón Bình Điền | C30: HOSE | E30: 124201533146
A31: BHN | B31: HABECO | C31: HOSE | E31: 77222524813
A32: BIC | B32: Bảo hiểm BIDV | C32: HOSE | E32: 87245176382
A33: BID | B33: BIDV | C33: HOSE | E33: 6800834000000
A34: BKG | B34: Đầu tư BKG Việt Nam | C34: HOSE | E34: 1648718602
A35: BMC | B35: Khoáng sản Bình Định | C35: HOSE | E35: 1481978528
A36: BMI | B36: Bảo hiểm Bảo Minh | C36: HOSE | E36: 55556275286
A37: BMP | B37: Nhựa Bình Minh | C37: HOSE | E37: 303956059754
A38: BRC | B38: Cao su Bến Thành | C38: HOSE | E38: 4646531336
A39: BSI | B39: Chứng khoán BIDV | C39: HOSE | E39: 88819056890
A40: BSR | B40: Lọc Hóa dầu Bình Sơn | C40: HOSE | E40: 8264713781616
... A44: BWE | B44: Nước - Môi trường Bình Dương | C44: HOSE | E44: 213662794807
A45: C32 | B45: Đầu tư và Xây dựng 3-2 | C45: HOSE
A46: C47 | B46: Xây dựng 47 | C46: HOSE | E46: 16164076490
A47: CCC | B47: Xây Dựng CDC | C47: HOSE | E47: 11444513624
A48: CCI | B48: CIDICO | C48: HOSE | E48: 14654684202
A49: CCL | B49: ĐT & PT Đô thị Dầu khí Cửu Long | C49: HOSE | E49: 8214549517
A50: CDC | B50: Chương Dương Corp | C50: HOSE | E50: 871690063
A51: CHP | B51: Thủy điện Miền Trung | C51: HOSE | E51: 90832409330
A52: CIG | B52: Xây dựng COMA 18 | C52: HOSE | E52: -54387714
A53: CII | B53: Hạ tầng Kỹ thuật TP.HCM | C53: HOSE | E53: 20976186616
A54: CKG | B54: Tập đoàn CIC | C54: HOSE | E54: 7019459850
A55: CLC | B55: Thuốc lá Cát Lợi | C55: HOSE | E55: 35413731499
A56: CLL | B56: Cảng Cát Lái | C56: HOSE | E56: 28160287773
A57: CLW | B57: Cấp nước Chợ Lớn | C57: HOSE | E57: 13846284156
... A109: DXV | B109: Vật liệu Xây dựng Đà Nẵng | C109: HOSE | E109: 148132891
A110: E1VFVN30 | B110: Quỹ ETF DCVFMVN30 | C110: HOSE
A111: EIB | B111: Eximbank | C111: HOSE | E111: 269160000000
A112: ELC | B112: ELCOM | C112: HOSE | E112: 2653995651
A113: EVE | B113: Everpia | C113: HOSE | E113: 770203562
A114: EVF | B114: Tài chính Tổng hợp Điện lực | C114: HOSE | E114: 266631000000
A115: EVG | B115: Tập đoàn Everland | C115: HOSE | E115: 18956399299
A116: FCM | B116: Bê tông Phan Vũ Hà Nam | C116: HOSE | E116: 4275275637
A117: FCN | B117: FECON CORP | C117: HOSE | E117: 31326328494
A118: FDC | B118: FIDECO | C118: HOSE | E118: 6779596455
A119: FIR | B119: Địa ốc First Real | C119: HOSE
A120: FIT | B120: Tập đoàn F.I.T | C120: HOSE
A121: FMC | B121: Thực phẩm Sao Ta | C121: HOSE | E121: 40852316596
A122: FPT | B122: FPT Corp | C122: HOSE | E122: 2487371587099
A123: FRT | B123: Bán lẻ FPT | C123: HOSE | E123: 287351892345
A124: FTS | B124: Chứng khoán FPT | C124: HOSE | E124: 159915055919
A125: FUCTVGF3 | B125: Quỹ Đầu tư Tăng trưởng Thiên Việt 3 | C125: HOSE
A126: FUCTVGF4 | B126: Quỹ Đầu tư Tăng trưởng Thiên Việt 4 | C126: HOSE
A127: FUCTVGF5 | B127: Quỹ Đầu tư Tăng trưởng Thiên Việt 5 | C127: HOSE
A128: FUCVREIT | B128: Quỹ Đầu tư BĐS Techcom Việt Nam | C128: HOSE
A129: FUEABVND | B129: Quỹ ETF ABFVN DIAMOND | C129: HOSE
A130: FUEBFVND | B130: Quỹ ETF BVFVN DIAMOND | C130: HOSE
A131: FUEDCMID | B131: Quỹ ETF DCVFMVNMIDCAP | C131: HOSE
A132: FUEFCV50 | B132: Quỹ ETF FPT CAPITAL VNX50 | C132: HOSE
A133: FUEIP100 | B133: Quỹ ETF IPAAM VN100 | C133: HOSE
A134: FUEKIV30 | B134: KIM GROWTH VN30 ETF | C134: HOSE
A135: FUEKIVFS | B135: KIM GROWTH VNFINSELECT ETF | C135: HOSE
A136: FUEKIVND | B136: Quỹ ETF KIM GROWTH VN DIAMOND | C136: HOSE
... A145: FUEVN100 | B145: Quỹ ETF VINACAPITAL VN100 | C145: HOSE
A146: GAS | B146: PV Gas | C146: HOSE | E146: 2944603136328
A147: GDT | B147: Gỗ Đức Thành | C147: HOSE | E147: 17175973951
A148: GEE | B148: Thiết bị điện GELEX | C148: HOSE | E148: 579385955223
A149: GEG | B149: Điện Gia Lai | C149: HOSE | E149: 206675501563
A150: GEL | B150: Hạ tầng GELEX | C150: HOSE | E150: -199953913974
A151: GEX | B151: Tập đoàn Gelex | C151: HOSE | E151: 245633005037
A152: GHC | B152: Thủy điện Gia Lai | C152: HOSE | E152: 48329465555
A153: GIL | B153: XNK Bình Thạnh | C153: HOSE | E153: 10312986589
A154: GMD | B154: Gemadept | C154: HOSE | E154: 534243825954
A155: GMH | B155: Minh Hưng Quảng Trị | C155: HOSE | E155: 2361195397
A156: GSP | B156: Vận tải Sản phẩm Khí Quốc tế | C156: HOSE | E156: 26370541110
A157: GTA | B157: Gỗ Thuận An | C157: HOSE | E157: 1830907382
... A187: HTL | B187: Ô tô Trường Long | C187: HOSE | E187: 6278137017
A188: HTN | B188: Hưng Thịnh Incons | C188: HOSE
A189: HTV | B189: Logistics Vicem | C189: HOSE | E189: 5207112801
A190: HU1 | B190: Xây dựng HUD1 | C190: HOSE | E190: 5639892
A191: HUB | B191: Xây lắp Huế | C191: HOSE | E191: 13385683872
...

Sheet LNG
A1: Mã CK | B1: Tên | C1: Sàn | D1: =LNST!H2 -> Q1.25 | E1: =LNST!I2 -> Q2.25 | F1: =LNST!J2 -> Q3.25 | G1: =LNST!K2 -> Q4.25 | H1: =LNST!L2 -> Q1.26
A2: AAA | B2: An Phát Bioplastics | C2: HOSE | D2: 463714514499 | E2: 354139506457 | F2: 347608363938 | G2: 327371053455 | H2: =VLOOKUP(A2,Sheet3!$A$1:$E$2000,5,FALSE) -> 359810543946
A3: AAM | B3: Thủy sản Mekong | C3: HOSE | D3: 7430110397 | E3: 8667864796 | F3: 4539269076 | G3: 552257145 | H3: =VLOOKUP(A3,Sheet3!$A$1:$E$2000,5,FALSE) -> 4831508362
A4: AAT | B4: Tập đoàn Tiên Sơn Thanh Hóa | C4: HOSE | D4: 30943441987 | E4: 19022104206 | F4: 14179904885 | G4: 20284354109 | H4: =VLOOKUP(A4,Sheet3!$A$1:$E$2000,5,FALSE) -> 22352686707
A5: ABR | B5: Đầu tư Nhãn Hiệu Việt | C5: HOSE | D5: 5960116877 | E5: 5773601254 | F5: 5643291226 | G5: 6536782944 | H5: =VLOOKUP(A5,Sheet3!$A$1:$E$2000,5,FALSE) -> 6228645959
A6: ABS | B6: DV Nông nghiệp Bình Thuận | C6: HOSE | D6: 1597477127 | E6: 1491551915 | F6: 1870760535 | G6: 1018512394 | H6: =VLOOKUP(A6,Sheet3!$A$1:$E$2000,5,FALSE) -> 1988618406
A7: ABT | B7: Thủy sản Bến Tre | C7: HOSE | D7: 35216800659 | E7: 54612643215 | F7: 56662332031 | G7: 43740342118 | H7: =VLOOKUP(A7,Sheet3!$A$1:$E$2000,5,FALSE) -> 36323708991
A8: ACB | B8: ACB | C8: HOSE | H8: =VLOOKUP(A8,Sheet3!$A$1:$E$2000,5,FALSE) -> 0
A9: ACC | B9: Đầu tư và XD Bình Dương ACC | C9: HOSE | D9: 22481023583 | E9: 22950738873 | F9: 42206288366 | G9: 24349520283 | H9: =VLOOKUP(A9,Sheet3!$A$1:$E$2000,5,FALSE) -> 15838648017
A10: ACG | B10: Gỗ An Cường | C10: HOSE | D10: 235733214602 | E10: 289721724733 | F10: 335318636284 | G10: 484538374455 | H10: =VLOOKUP(A10,Sheet3!$A$1:$E$2000,5,FALSE) -> 308669637516
A11: ACL | B11: Thủy sản CL An Giang | C11: HOSE | D11: 52023624078 | E11: 61229341614 | F11: 69824671139 | G11: 82877744873 | H11: =VLOOKUP(A11,Sheet3!$A$1:$E$2000,5,FALSE) -> 58398982954
A12: ADG | B12: Clever Group | C12: HOSE | D12: 10511242401 | E12: 17083863089 | F12: 14173186604 | G12: 41647583458 | H12: =VLOOKUP(A12,Sheet3!$A$1:$E$2000,5,FALSE) -> 0
A13: ADP | B13: Sơn Á Đông | C13: HOSE | D13: 38815032242 | E13: 34192375843 | F13: 25524742515 | G13: 30190787885 | H13: =VLOOKUP(A13,Sheet3!$A$1:$E$2000,5,FALSE) -> 29470224206
A14: ADS | B14: Dệt sợi DAMSAN | C14: HOSE | D14: 32025212597 | E14: 71371033231 | F14: 46231695839 | G14: 103365910038 | H14: =VLOOKUP(A14,Sheet3!$A$1:$E$2000,5,FALSE) -> 34596475482
A15: AFX | B15: XNK Nông sản Thực phẩm An Giang | C15: HOSE | D15: 7333729419 | E15: 21025339643 | F15: 12922118164 | G15: 20903238672 | H15: =VLOOKUP(A15,Sheet3!$A$1:$E$2000,5,FALSE) -> 29648193663
A16: AGG | B16: Bất động sản An Gia | C16: HOSE | D16: 75449818771 | E16: 165377214686 | F16: 194400269258 | G16: 148114152614 | H16: =VLOOKUP(A16,Sheet3!$A$1:$E$2000,5,FALSE) -> 36987903787
A17: AGR | B17: Agriseco | C17: HOSE | D17: 66112333288 | E17: 36405211985 | F17: 122456875395 | G17: 95209953556 | H17: =VLOOKUP(A17,Sheet3!$A$1:$E$2000,5,FALSE) -> 110266725334
A18: ANT | B18: Rau quả thực phẩm An Giang | C18: HOSE | D18: 126510816367 | E18: 131129598055 | F18: 121034962600 | G18: 71150410384 | H18: =VLOOKUP(A18,Sheet3!$A$1:$E$2000,5,FALSE) -> 0
A19: ANV | B19: Thủy sản Nam Việt | C19: HOSE | D19: 223695010477 | E19: 486365584101 | F19: 487487993857 | G19: 425383718926 | H19: =VLOOKUP(A19,Sheet3!$A$1:$E$2000,5,FALSE) -> 326307508748
A20: APG | B20: Chứng khoán APG | C20: HOSE | D20: 21331125606 | E20: 31903492057 | F20: 72682990145 | G20: 65548419932 | H20: =VLOOKUP(A20,Sheet3!$A$1:$E$2000,5,FALSE) -> 62308770045
... A25: AST | B25: Dịch vụ Hàng không Taseco | C25: HOSE | D25: 242538767927 | E25: 251107984521 | F25: 294214353928 | G25: 308251562281 | H25: =VLOOKUP(A25,Sheet3!$A$1:$E$2000,5,FALSE) -> 364766626709
A26: ATP | B26: T.Mại và DV An Thành | C26: HOSE | H26: =VLOOKUP(A26,Sheet3!$A$1:$E$2000,5,FALSE) -> 0
A27: BAF | B27: Nông nghiệp BAF Việt Nam | C27: HOSE | D27: 290477202814 | E27: 316368245456 | F27: 263908863897 | G27: -188902792286 | H27: =VLOOKUP(A27,Sheet3!$A$1:$E$2000,5,FALSE) -> 451223734791
A28: BCE | B28: XD và GT Bình Dương | C28: HOSE | D28: -230924048 | E28: 14643360031 | F28: 9685531192 | G28: 141600369390 | H28: =VLOOKUP(A28,Sheet3!$A$1:$E$2000,5,FALSE) -> 5125038280
A29: BCG | B29: Bamboo Capital | C29: HOSE | H29: =VLOOKUP(A29,Sheet3!$A$1:$E$2000,5,FALSE) -> 0
A30: BCM | B30: Becamex Group | C30: HOSE | D30: 704150566074 | E30: 1908031502052 | F30: 509907089589 | G30: 1040043428725 | H30: =VLOOKUP(A30,Sheet3!$A$1:$E$2000,5,FALSE) -> 682650522716
A31: BFC | B31: Phân bón Bình Điền | C31: HOSE | D31: 373987535757 | E31: 413479308160 | F31: 220833922394 | G31: 316994742074 | H31: =VLOOKUP(A31,Sheet3!$A$1:$E$2000,5,FALSE) -> 436762921200
A32: BHN | B32: HABECO | C32: HOSE | D32: 354128221979 | E32: 694602778986 | F32: 738892875385 | G32: 631588480745 | H32: =VLOOKUP(A32,Sheet3!$A$1:$E$2000,5,FALSE) -> 499713563284
A33: BIC | B33: Bảo hiểm BIDV | C33: HOSE | D33: 275085830173 | E33: 249484286207 | F33: 278282724089 | G33: 191366129077 | H33: =VLOOKUP(A33,Sheet3!$A$1:$E$2000,5,FALSE) -> 215854269603
A34: BID | B34: BIDV | C34: HOSE | H34: =VLOOKUP(A34,Sheet3!$A$1:$E$2000,5,FALSE) -> 0
A35: BKG | B35: Đầu tư BKG Việt Nam | C35: HOSE | D35: 6363082290 | E35: 8141536104 | F35: 4581713812 | G35: 7123351141 | H35: =VLOOKUP(A35,Sheet3!$A$1:$E$2000,5,FALSE) -> 4402585364
A36: BMC | B36: Khoáng sản Bình Định | C36: HOSE | D36: 3518948114 | E36: 7621815828 | F36: 9224893700 | G36: 6395516396 | H36: =VLOOKUP(A36,Sheet3!$A$1:$E$2000,5,FALSE) -> 4808904818
A37: BMI | B37: Bảo hiểm Bảo Minh | C37: HOSE | D37: 106939229202 | E37: 101431054124 | F37: 91087580024 | G37: 15402806770 | H37: =VLOOKUP(A37,Sheet3!$A$1:$E$2000,5,FALSE) -> 77627559729
A38: BMP | B38: Nhựa Bình Minh | C38: HOSE | D38: 590170242795 | E38: 610817358498 | F38: 734167408150 | G38: 604409167984 | H38: =VLOOKUP(A38,Sheet3!$A$1:$E$2000,5,FALSE) -> 688068276858
A39: BRC | B39: Cao su Bến Thành | C39: HOSE | D39: 15691705746 | E39: 18479938745 | F39: 16854994260 | G39: 17581085655 | H39: =VLOOKUP(A39,Sheet3!$A$1:$E$2000,5,FALSE) -> 17264707509
A40: BSI | B40: Chứng khoán BIDV | C40: HOSE | D40: 197799476351 | E40: 262408393883 | F40: 423157240034 | G40: 316795712858 | H40: =VLOOKUP(A40,Sheet3!$A$1:$E$2000,5,FALSE) -> 351495830024
A41: BSR | B41: Lọc Hóa dầu Bình Sơn | C41: HOSE | D41: 382335094634 | E41: 1016359178961 | F41: 1008526847756 | G41: 3706697454545 | H41: =VLOOKUP(A41,Sheet3!$A$1:$E$2000,5,FALSE) -> 9506578752065
A42: BTP | B42: Nhiệt điện Bà Rịa | C42: HOSE | D42: 15174606700 | E42: 16368714178 | F42: 9997431193 | G42: 5575551066 | H42: =VLOOKUP(A42,Sheet3!$A$1:$E$2000,5,FALSE) -> 16259959066
A43: BTT | B43: TM - DV Bến Thành | C43: HOSE | D43: 35123275751 | E43: 33028998924 | F43: 34214521004 | G43: 37464422419 | H43: =VLOOKUP(A43,Sheet3!$A$1:$E$2000,5,FALSE) -> 37471388802
A44: BVH | B44: Tập đoàn Bảo Việt | C44: HOSE | D44: 577222965394 | E44: 592598316073 | F44: 244838162662 | G44: -176713115188 | H44: =VLOOKUP(A44,Sheet3!$A$1:$E$2000,5,FALSE) -> 307855270823
A45: BWE | B45: Nước - Môi trường Bình Dương | C45: HOSE | D45: 431187909610 | E45: 508614468016 | F45: 502293009626 | G45: 515579798519 | H45: =VLOOKUP(A45,Sheet3!$A$1:$E$2000,5,FALSE) -> 483959198647
A46: C32 | B46: Đầu tư và Xây dựng 3-2 | C46: HOSE | D46: 10929817559 | E46: 19399114046 | F46: 18771955211 | G46: 28405506022 | H46: =VLOOKUP(A46,Sheet3!$A$1:$E$2000,5,FALSE) -> 0
... A70: CTF | B70: City Auto | C70: HOSE | D70: 117675857641 | E70: 127848095737 | F70: 126147139626 | G70: 106704031271 | H70: =VLOOKUP(A70,Sheet3!$A$1:$E$2000,5,FALSE) -> 109865360074
A71: CTG | B71: VietinBank | C71: HOSE | H71: =VLOOKUP(A71,Sheet3!$A$1:$E$2000,5,FALSE) -> 0
A72: CTI | B72: Cường Thuận IDICO | C72: HOSE | D72: 114589535075 | E72: 137004320071 | F72: 133401617604 | G72: 136499825802 | H72: =VLOOKUP(A72,Sheet3!$A$1:$E$2000,5,FALSE) -> 120548683659
A73: CTR | B73: Công trình Viettel | C73: HOSE | D73: 200961127510 | E73: 234832591298 | F73: 247534754432 | G73: 298612100143 | H73: =VLOOKUP(A73,Sheet3!$A$1:$E$2000,5,FALSE) -> 262217201696
A74: CTS | B74: Chứng khoán Vietinbank | C74: HOSE | D74: 237933124116 | E74: 335784785030 | F74: 469165828496 | G74: 203680394758 | H74: =VLOOKUP(A74,Sheet3!$A$1:$E$2000,5,FALSE) -> 250219148053
A75: CVT | B75: CMC JSC | C75: HOSE | D75: 66993226944 | E75: 60075459683 | F75: 77618792015 | G75: 17468358141 | H75: =VLOOKUP(A75,Sheet3!$A$1:$E$2000,5,FALSE) -> 57000622646
A76: D2D | B76: Phát triển Đô thị số 2 | C76: HOSE | D76: 18796979050 | E76: 282453157819 | F76: 44343368691 | G76: 18359601668 | H76: =VLOOKUP(A76,Sheet3!$A$1:$E$2000,5,FALSE) -> 19669738705
A77: DAH | B77: Tập đoàn Khách sạn Đông Á | C77: HOSE | D77: -3852703319 | E77: 2560697029 | F77: -565537090 | G77: 876780090 | H77: =VLOOKUP(A77,Sheet3!$A$1:$E$2000,5,FALSE) -> -956524360
A78: DAT | B78: ĐT Du lịch và PT Thủy sản | C78: HOSE | D78: 13878557264 | E78: 29017445243 | F78: 26162493723 | G78: 32033088089 | H78: =VLOOKUP(A78,Sheet3!$A$1:$E$2000,5,FALSE) -> 26631984305
A79: DBC | B79: Tập đoàn DABACO | C79: HOSE | D79: 817186815727 | E79: 825063690200 | F79: 652166187513 | G79: 452150456084 | H79: =VLOOKUP(A79,Sheet3!$A$1:$E$2000,5,FALSE) -> 690980808074
A80: DBD | B80: Dược - TB Y tế Bình Định | C80: HOSE | D80: 228231261556 | E80: 242391394612 | F80: 187294077914 | G80: 226462060289 | H80: =VLOOKUP(A80,Sheet3!$A$1:$E$2000,5,FALSE) -> 203949096300
A81: DBT | B81: Dược phẩm Bến Tre | C81: HOSE | D81: 78557526536 | E81: 94923840212 | F81: 76740856539 | G81: 88224332178 | H81: =VLOOKUP(A81,Sheet3!$A$1:$E$2000,5,FALSE) -> 80350018360
A82: DC4 | B82: Dicera Holdings | C82: HOSE | D82: 78465870524 | E82: 141761074911 | F82: 123060722255 | G82: 117849977911 | H82: =VLOOKUP(A82,Sheet3!$A$1:$E$2000,5,FALSE) -> 73114797462
A83: DCL | B83: Dược phẩm Cửu Long | C83: HOSE | D83: 80277208394 | E83: 34961803685 | F83: 34653155612 | G83: 54351646417 | H83: =VLOOKUP(A83,Sheet3!$A$1:$E$2000,5,FALSE) -> 38778857578
... A110: DXV | B110: Vật liệu Xây dựng Đà Nẵng | C110: HOSE | D110: 2287383639 | E110: 6074748443 | F110: 4420650982 | G110: 5134629588 | H110: =VLOOKUP(A110,Sheet3!$A$1:$E$2000,5,FALSE) -> 4960149739
A111: E1VFVN30 | B111: Quỹ ETF DCVFMVN30 | C111: HOSE | H111: =VLOOKUP(A111,Sheet3!$A$1:$E$2000,5,FALSE) -> 0
A112: EIB | B112: Eximbank | C112: HOSE | H112: =VLOOKUP(A112,Sheet3!$A$1:$E$2000,5,FALSE) -> 0
A113: ELC | B113: ELCOM | C113: HOSE | D113: 25439777036 | E113: 40705063168 | F113: 77897085515 | G113: 126126446807 | H113: =VLOOKUP(A113,Sheet3!$A$1:$E$2000,5,FALSE) -> 28163989853
A114: EVE | B114: Everpia | C114: HOSE | D114: 56045087521 | E114: 64805869628 | F114: 78724331025 | G114: 78860199565 | H114: =VLOOKUP(A114,Sheet3!$A$1:$E$2000,5,FALSE) -> 55822247402
A115: EVF | B115: Tài chính Tổng hợp Điện lực | C115: HOSE | H115: =VLOOKUP(A115,Sheet3!$A$1:$E$2000,5,FALSE) -> 0
A116: EVG | B116: Tập đoàn Everland | C116: HOSE | D116: 7450221018 | E116: 11816798756 | F116: 17013242542 | G116: 110951303528 | H116: =VLOOKUP(A116,Sheet3!$A$1:$E$2000,5,FALSE) -> 47372122783
A117: FCM | B117: Bê tông Phan Vũ Hà Nam | C117: HOSE | D117: 12024186775 | E117: 13726630833 | F117: 8529494639 | G117: 11127313520 | H117: =VLOOKUP(A117,Sheet3!$A$1:$E$2000,5,FALSE) -> 8708939471
A118: FCN | B118: FECON CORP | C118: HOSE | D118: 131200584621 | E118: 165658566081 | F118: 157203314468 | G118: 250333792634 | H118: =VLOOKUP(A118,Sheet3!$A$1:$E$2000,5,FALSE) -> 180024396935
A119: FDC | B119: FIDECO | C119: HOSE | D119: 14114314398 | E119: 14125984542 | F119: 13071774385 | G119: 12697241397 | H119: =VLOOKUP(A119,Sheet3!$A$1:$E$2000,5,FALSE) -> 13089207598
A120: FIR | B120: Địa ốc First Real | C120: HOSE | D120: 31567764065 | E120: 28336766153 | F120: 2081806562 | G120: 5647953598 | H120: =VLOOKUP(A120,Sheet3!$A$1:$E$2000,5,FALSE) -> 0
A121: FIT | B121: Tập đoàn F.I.T | C121: HOSE | D121: 126578136728 | E121: 99339787939 | F121: 92199137861 | G121: 68691761282 | H121: =VLOOKUP(A121,Sheet3!$A$1:$E$2000,5,FALSE) -> 0
A122: FMC | B122: Thực phẩm Sao Ta | C122: HOSE | D122: 127425023693 | E122: 197273183980 | F122: 418347702879 | G122: 230157403136 | H122: =VLOOKUP(A122,Sheet3!$A$1:$E$2000,5,FALSE) -> 100714862366
A123: FPT | B123: FPT Corp | C123: HOSE | D123: 6301347904266 | E123: 6021040042975 | F123: 6518866479010 | G123: 7047275086162 | H123: =VLOOKUP(A123,Sheet3!$A$1:$E$2000,5,FALSE) -> 4244889890688
A124: FRT | B124: Bán lẻ FPT | C124: HOSE | D124: 2324501283436 | E124: 2271099323500 | F124: 2539435835564 | G124: 2874668015585 | H124: =VLOOKUP(A124,Sheet3!$A$1:$E$2000,5,FALSE) -> 2994927830887
A125: FTS | B125: Chứng khoán FPT | C125: HOSE | D125: 190098487589 | E125: 102235439286 | F125: 107004576064 | G125: 186365997757 | H125: =VLOOKUP(A125,Sheet3!$A$1:$E$2000,5,FALSE) -> 201601479848
A126: FUCTVGF3 | B126: Quỹ Đầu tư Tăng trưởng Thiên Việt 3 | C126: HOSE | H126: =VLOOKUP(A126,Sheet3!$A$1:$E$2000,5,FALSE) -> 0
A127: FUCTVGF4 | B127: Quỹ Đầu tư Tăng trưởng Thiên Việt 4 | C127: HOSE | H127: =VLOOKUP(A127,Sheet3!$A$1:$E$2000,5,FALSE) -> 0
A128: FUCTVGF5 | B128: Quỹ Đầu tư Tăng trưởng Thiên Việt 5 | C128: HOSE | H128: =VLOOKUP(A128,Sheet3!$A$1:$E$2000,5,FALSE) -> 0
A129: FUCVREIT | B129: Quỹ Đầu tư BĐS Techcom Việt Nam | C129: HOSE | H129: =VLOOKUP(A129,Sheet3!$A$1:$E$2000,5,FALSE) -> 0
A130: FUEABVND | B130: Quỹ ETF ABFVN DIAMOND | C130: HOSE | H130: =VLOOKUP(A130,Sheet3!$A$1:$E$2000,5,FALSE) -> 0
A131: FUEBFVND | B131: Quỹ ETF BVFVN DIAMOND | C131: HOSE | H131: =VLOOKUP(A131,Sheet3!$A$1:$E$2000,5,FALSE) -> 0
A132: FUEDCMID | B132: Quỹ ETF DCVFMVNMIDCAP | C132: HOSE | H132: =VLOOKUP(A132,Sheet3!$A$1:$E$2000,5,FALSE) -> 0
A133: FUEFCV50 | B133: Quỹ ETF FPT CAPITAL VNX50 | C133: HOSE | H133: =VLOOKUP(A133,Sheet3!$A$1:$E$2000,5,FALSE) -> 0
A134: FUEIP100 | B134: Quỹ ETF IPAAM VN100 | C134: HOSE | H134: =VLOOKUP(A134,Sheet3!$A$1:$E$2000,5,FALSE) -> 0
A135: FUEKIV30 | B135: KIM GROWTH VN30 ETF | C135: HOSE | H135: =VLOOKUP(A135,Sheet3!$A$1:$E$2000,5,FALSE) -> 0
A136: FUEKIVFS | B136: KIM GROWTH VNFINSELECT ETF | C136: HOSE | H136: =VLOOKUP(A136,Sheet3!$A$1:$E$2000,5,FALSE) -> 0
A137: FUEKIVND | B137: Quỹ ETF KIM GROWTH VN DIAMOND | C137: HOSE | H137: =VLOOKUP(A137,Sheet3!$A$1:$E$2000,5,FALSE) -> 0
... A146: FUEVN100 | B146: Quỹ ETF VINACAPITAL VN100 | C146: HOSE | H146: =VLOOKUP(A146,Sheet3!$A$1:$E$2000,5,FALSE) -> 0
A147: GAS | B147: PV Gas | C147: HOSE | D147: 4089510371416 | E147: 4953952865746 | F147: 4102333886924 | G147: 3904756235579 | H147: =VLOOKUP(A147,Sheet3!$A$1:$E$2000,5,FALSE) -> 4508191324775
A148: GDT | B148: Gỗ Đức Thành | C148: HOSE | D148: 33841820265 | E148: 30707486028 | F148: 34840202733 | G148: 40509226031 | H148: =VLOOKUP(A148,Sheet3!$A$1:$E$2000,5,FALSE) -> 31823595361
A149: GEE | B149: Thiết bị điện GELEX | C149: HOSE | D149: 832443833473 | E149: 1035209154759 | F149: 1069118856059 | G149: 1174010816536 | H149: =VLOOKUP(A149,Sheet3!$A$1:$E$2000,5,FALSE) -> 1015641288378
A150: GEG | B150: Điện Gia Lai | C150: HOSE | D150: 826087364006 | E150: 272891309069 | F150: 322689538843 | G150: 292699484451 | H150: =VLOOKUP(A150,Sheet3!$A$1:$E$2000,5,FALSE) -> 486964564155
A151: GEL | B151: Hạ tầng GELEX | C151: HOSE | D151: 850840584920 | E151: 1276349850352 | F151: 765746756696 | G151: 1434361243976 | H151: =VLOOKUP(A151,Sheet3!$A$1:$E$2000,5,FALSE) -> 950690652398
A152: GEX | B152: Tập đoàn Gelex | C152: HOSE | D152: 1598238462931 | E152: 2338767844404 | F152: 1831629249349 | G152: 2647904434968 | H152: =VLOOKUP(A152,Sheet3!$A$1:$E$2000,5,FALSE) -> 2001820351335
A153: GHC | B153: Thủy điện Gia Lai | C153: HOSE | D153: 42681111771 | E153: 40217536295 | F153: 50848689402 | G153: 56298093522 | H153: =VLOOKUP(A153,Sheet3!$A$1:$E$2000,5,FALSE) -> 59252420358
A154: GIL | B154: XNK Bình Thạnh | C154: HOSE | D154: 22747105864 | E154: 11305648822 | F154: 17077518362 | G154: 111358828799 | H154: =VLOOKUP(A154,Sheet3!$A$1:$E$2000,5,FALSE) -> 41312192059
A155: GMD | B155: Gemadept | C155: HOSE | D155: 561631814693 | E155: 721981500043 | F155: 666241603807 | G155: 789617620387 | H155: =VLOOKUP(A155,Sheet3!$A$1:$E$2000,5,FALSE) -> 636495561398
A156: GMH | B156: Minh Hưng Quảng Trị | C156: HOSE | D156: 4023120987 | E156: 8949055917 | F156: 7519972857 | G156: 6616627137 | H156: =VLOOKUP(A156,Sheet3!$A$1:$E$2000,5,FALSE) -> 3141025360
A157: GSP | B157: Vận tải Sản phẩm Khí Quốc tế | C157: HOSE | D157: 55727146422 | E157: 41078754288 | F157: 12649034165 | G157: 68341723179 | H157: =VLOOKUP(A157,Sheet3!$A$1:$E$2000,5,FALSE) -> 30864896287
A158: GTA | B158: Gỗ Thuận An | C158: HOSE | D158: 6421092278 | E158: 6317127518 | F158: 6681972190 | G158: 3195668584 | H158: =VLOOKUP(A158,Sheet3!$A$1:$E$2000,5,FALSE) -> 6423320649
... A167: HCM | B167: Chứng khoán HSC | C167: HOSE | D167: 386511727702 | E167: 357894689876 | F167: 691174831945 | G167: 548156538144 | H167: =VLOOKUP(A167,Sheet3!$A$1:$E$2000,5,FALSE) -> 489530453264
A168: HDB | B168: HDBank | C168: HOSE | H168: =VLOOKUP(A168,Sheet3!$A$1:$E$2000,5,FALSE) -> 0
A169: HDC | B169: Phát triển Nhà BR-VT | C169: HOSE | D169: 36478718609 | E169: 10664157323 | F169: 17224939698 | G169: 32136981888 | H169: =VLOOKUP(A169,Sheet3!$A$1:$E$2000,5,FALSE) -> 133799421111
...

Sheet Sheet3
A1: AAA | B1: An Phát Bioplastics | C1: HOSE | E1: 359810543946
A2: AAM | B2: Thủy sản Mekong | C2: HOSE | E2: 4831508362
A3: AAT | B3: Tập đoàn Tiên Sơn Thanh Hóa | C3: HOSE | E3: 22352686707
A4: ABR | B4: Đầu tư Nhãn Hiệu Việt | C4: HOSE | E4: 6228645959
A5: ABS | B5: DV Nông nghiệp Bình Thuận | C5: HOSE | E5: 1988618406
A6: ABT | B6: Thủy sản Bến Tre | C6: HOSE | E6: 36323708991
A7: ACB | B7: ACB | C7: HOSE
A8: ACC | B8: Đầu tư và XD Bình Dương ACC | C8: HOSE | E8: 15838648017
A9: ACG | B9: Gỗ An Cường | C9: HOSE | E9: 308669637516
A10: ACL | B10: Thủy sản CL An Giang | C10: HOSE | E10: 58398982954
A11: ADG | B11: Clever Group | C11: HOSE
A12: ADP | B12: Sơn Á Đông | C12: HOSE | E12: 29470224206
A13: ADS | B13: Dệt sợi DAMSAN | C13: HOSE | E13: 34596475482
A14: AFX | B14: XNK Nông sản Thực phẩm An Giang | C14: HOSE | E14: 29648193663
A15: AGG | B15: Bất động sản An Gia | C15: HOSE | E15: 36987903787
A16: AGR | B16: Agriseco | C16: HOSE | E16: 110266725334
A17: ANT | B17: Rau quả thực phẩm An Giang | C17: HOSE
A18: ANV | B18: Thủy sản Nam Việt | C18: HOSE | E18: 326307508748
A19: APG | B19: Chứng khoán APG | C19: HOSE | E19: 62308770045
A20: APH | B20: Tập đoàn An Phát Holdings | C20: HOSE | E20: 360220134446
A21: ASG | B21: Tập đoàn ASG | C21: HOSE | E21: 128360404671
A22: ASM | B22: Tập đoàn Sao Mai | C22: HOSE | E22: 374725884794
A23: ASP | B23: Dầu khí An Pha | C23: HOSE | E23: 118327227424
A24: AST | B24: Dịch vụ Hàng không Taseco | C24: HOSE | E24: 364766626709
A25: ATP | B25: T.Mại và DV An Thành | C25: HOSE
A26: BAF | B26: Nông nghiệp BAF Việt Nam | C26: HOSE | E26: 451223734791
A27: BCE | B27: XD và GT Bình Dương | C27: HOSE | E27: 5125038280
A28: BCG | B28: Bamboo Capital | C28: HOSE
A29: BCM | B29: Becamex Group | C29: HOSE | E29: 682650522716
A30: BFC | B30: Phân bón Bình Điền | C30: HOSE | E30: 436762921200
A31: BHN | B31: HABECO | C31: HOSE | E31: 499713563284
A32: BIC | B32: Bảo hiểm BIDV | C32: HOSE | E32: 215854269603
A33: BID | B33: BIDV | C33: HOSE
A34: BKG | B34: Đầu tư BKG Việt Nam | C34: HOSE | E34: 4402585364
A35: BMC | B35: Khoáng sản Bình Định | C35: HOSE | E35: 4808904818
A36: BMI | B36: Bảo hiểm Bảo Minh | C36: HOSE | E36: 77627559729
A37: BMP | B37: Nhựa Bình Minh | C37: HOSE | E37: 688068276858
A38: BRC | B38: Cao su Bến Thành | C38: HOSE | E38: 17264707509
A39: BSI | B39: Chứng khoán BIDV | C39: HOSE | E39: 351495830024
A40: BSR | B40: Lọc Hóa dầu Bình Sơn | C40: HOSE | E40: 9506578752065
A41: BTP | B41: Nhiệt điện Bà Rịa | C41: HOSE | E41: 16259959066
A42: BTT | B42: TM - DV Bến Thành | C42: HOSE | E42: 37471388802
A43: BVH | B43: Tập đoàn Bảo Việt | C43: HOSE | E43: 307855270823
A44: BWE | B44: Nước - Môi trường Bình Dương | C44: HOSE | E44: 483959198647
A45: C32 | B45: Đầu tư và Xây dựng 3-2 | C45: HOSE
A46: C47 | B46: Xây dựng 47 | C46: HOSE | E46: 45433521742
A47: CCC | B47: Xây Dựng CDC | C47: HOSE | E47: 36039851522
A48: CCI | B48: CIDICO | C48: HOSE | E48: 12618938419
A49: CCL | B49: ĐT & PT Đô thị Dầu khí Cửu Long | C49: HOSE | E49: 22078398970
A50: CDC | B50: Chương Dương Corp | C50: HOSE | E50: 13070809303
A51: CHP | B51: Thủy điện Miền Trung | C51: HOSE | E51: 110613500701
A52: CIG | B52: Xây dựng COMA 18 | C52: HOSE | E52: 2290984257
A53: CII | B53: Hạ tầng Kỹ thuật TP.HCM | C53: HOSE | E53: 448442659662
A54: CKG | B54: Tập đoàn CIC | C54: HOSE | E54: 30007367063
A55: CLC | B55: Thuốc lá Cát Lợi | C55: HOSE | E55: 99552998900
A56: CLL | B56: Cảng Cát Lái | C56: HOSE | E56: 39417657375
A57: CLW | B57: Cấp nước Chợ Lớn | C57: HOSE | E57: 55447018222
... A69: CTF | B69: City Auto | C69: HOSE | E69: 109865360074
A70: CTG | B70: VietinBank | C70: HOSE
A71: CTI | B71: Cường Thuận IDICO | C71: HOSE | E71: 120548683659
A72: CTR | B72: Công trình Viettel | C72: HOSE | E72: 262217201696
A73: CTS | B73: Chứng khoán Vietinbank | C73: HOSE | E73: 250219148053
A74: CVT | B74: CMC JSC | C74: HOSE | E74: 57000622646
A75: D2D | B75: Phát triển Đô thị số 2 | C75: HOSE | E75: 19669738705
A76: DAH | B76: Tập đoàn Khách sạn Đông Á | C76: HOSE | E76: -956524360
A77: DAT | B77: ĐT Du lịch và PT Thủy sản | C77: HOSE | E77: 26631984305
A78: DBC | B78: Tập đoàn DABACO | C78: HOSE | E78: 690980808074
A79: DBD | B79: Dược - TB Y tế Bình Định | C79: HOSE | E79: 203949096300
A80: DBT | B80: Dược phẩm Bến Tre | C80: HOSE | E80: 80350018360
A81: DC4 | B81: Dicera Holdings | C81: HOSE | E81: 73114797462
A82: DCL | B82: Dược phẩm Cửu Long | C82: HOSE | E82: 38778857578
... A109: DXV | B109: Vật liệu Xây dựng Đà Nẵng | C109: HOSE | E109: 4960149739
A110: E1VFVN30 | B110: Quỹ ETF DCVFMVN30 | C110: HOSE
A111: EIB | B111: Eximbank | C111: HOSE
A112: ELC | B112: ELCOM | C112: HOSE | E112: 28163989853
A113: EVE | B113: Everpia | C113: HOSE | E113: 55822247402
A114: EVF | B114: Tài chính Tổng hợp Điện lực | C114: HOSE
A115: EVG | B115: Tập đoàn Everland | C115: HOSE | E115: 47372122783
A116: FCM | B116: Bê tông Phan Vũ Hà Nam | C116: HOSE | E116: 8708939471
A117: FCN | B117: FECON CORP | C117: HOSE | E117: 180024396935
A118: FDC | B118: FIDECO | C118: HOSE | E118: 13089207598
A119: FIR | B119: Địa ốc First Real | C119: HOSE
A120: FIT | B120: Tập đoàn F.I.T | C120: HOSE
A121: FMC | B121: Thực phẩm Sao Ta | C121: HOSE | E121: 100714862366
A122: FPT | B122: FPT Corp | C122: HOSE | E122: 4244889890688
A123: FRT | B123: Bán lẻ FPT | C123: HOSE | E123: 2994927830887
A124: FTS | B124: Chứng khoán FPT | C124: HOSE | E124: 201601479848
A125: FUCTVGF3 | B125: Quỹ Đầu tư Tăng trưởng Thiên Việt 3 | C125: HOSE
A126: FUCTVGF4 | B126: Quỹ Đầu tư Tăng trưởng Thiên Việt 4 | C126: HOSE
A127: FUCTVGF5 | B127: Quỹ Đầu tư Tăng trưởng Thiên Việt 5 | C127: HOSE
A128: FUCVREIT | B128: Quỹ Đầu tư BĐS Techcom Việt Nam | C128: HOSE
A129: FUEABVND | B129: Quỹ ETF ABFVN DIAMOND | C129: HOSE
A130: FUEBFVND | B130: Quỹ ETF BVFVN DIAMOND | C130: HOSE
A131: FUEDCMID | B131: Quỹ ETF DCVFMVNMIDCAP | C131: HOSE
A132: FUEFCV50 | B132: Quỹ ETF FPT CAPITAL VNX50 | C132: HOSE
A133: FUEIP100 | B133: Quỹ ETF IPAAM VN100 | C133: HOSE
A134: FUEKIV30 | B134: KIM GROWTH VN30 ETF | C134: HOSE
A135: FUEKIVFS | B135: KIM GROWTH VNFINSELECT ETF | C135: HOSE
A136: FUEKIVND | B136: Quỹ ETF KIM GROWTH VN DIAMOND | C136: HOSE
... A145: FUEVN100 | B145: Quỹ ETF VINACAPITAL VN100 | C145: HOSE
...

Sheet LNST năm
A1: Mã CK | B1: Tên | C1: Sàn | D1: 2022 | E1: 2023 | F1: 2024 | G1: 2025 | H1: 2025/2024 | I1: bình quân 4 năm
A2: AAA | B2: An Phát Bioplastics | C2: HOSE | D2: 152599331716 | E2: 289410548684 | F2: 368580504091 | G2: 372912597362 | H2: =(G2-F2)/ABS(F2) -> 0.011753452 | I2: =(1+(G2-D2)/ABS(D2))^(1/3)-1 -> 0.34695
A3: AAM | B3: Thủy sản Mekong | C3: HOSE | D3: 16899756334 | E3: 703150885 | F3: -6295683732 | G3: 1849136974 | H3: =(G3-F3)/ABS(F3) -> 1.293715 | I3: =(1+(G3-D3)/ABS(D3))^(1/3)-1 -> -0.52170459
A4: AAT | B4: Tập đoàn Tiên Sơn Thanh Hóa | C4: HOSE | D4: 67633771286 | E4: -2466576299 | F4: -8345961789 | H4: =(G4-F4)/ABS(F4) -> 1 | I4: =(1+(G4-D4)/ABS(D4))^(1/3)-1 -> -1
A5: ABR | B5: Đầu tư Nhãn Hiệu Việt | C5: HOSE | D5: 29390746456 | E5: 30982405215 | F5: 19737903181 | G5: 15505043172 | H5: =(G5-F5)/ABS(F5) -> -0.21445338 | I5: =(1+(G5-D5)/ABS(D5))^(1/3)-1 -> -0.19198246
A6: ABS | B6: DV Nông nghiệp Bình Thuận | C6: HOSE | D6: 22539691244 | E6: 8287009671 | F6: 2435388079 | G6: -511237658742 | H6: =(G6-F6)/ABS(F6) -> -210.92041 | I6: =(1+(G6-D6)/ABS(D6))^(1/3)-1 -> -3.8306855
A7: ABT | B7: Thủy sản Bến Tre | C7: HOSE | D7: 64289101233 | E7: 63871593981 | F7: 101488892957 | H7: =(G7-F7)/ABS(F7) -> -1 | I7: =(1+(G7-D7)/ABS(D7))^(1/3)-1 -> -1
A8: ACB | B8: ACB | C8: HOSE | D8: 13688193000000 | E8: 16044733000000 | F8: 16789768000000 | G8: 15624699000000 | H8: =(G8-F8)/ABS(F8) -> -0.069391608 | I8: =(1+(G8-D8)/ABS(D8))^(1/3)-1 -> 0.04509358
A9: ACC | B9: Đầu tư và XD Bình Dương ACC | C9: HOSE | D9: 82330194473 | E9: 69499477649 | F9: 52290191021 | H9: =(G9-F9)/ABS(F9) -> -1 | I9: =(1+(G9-D9)/ABS(D9))^(1/3)-1 -> -1
A10: ACG | B10: Gỗ An Cường | C10: HOSE | D10: 615581289335 | E10: 411185657186 | F10: 419971985880 | H10: =(G10-F10)/ABS(F10) -> -1 | I10: =(1+(G10-D10)/ABS(D10))^(1/3)-1 -> -1
A11: ACL | B11: Thủy sản CL An Giang | C11: HOSE | D11: 117947830085 | E11: 9852743462 | F11: 10765243181 | G11: 38426324932 | H11: =(G11-F11)/ABS(F11) -> 2.5694804 | I11: =(1+(G11-D11)/ABS(D11))^(1/3)-1 -> -0.31190833
A12: ADG | B12: Clever Group | C12: HOSE | D12: 48956297029 | E12: 20079255644 | F12: 17793244862 | H12: =(G12-F12)/ABS(F12) -> -1 | I12: =(1+(G12-D12)/ABS(D12))^(1/3)-1 -> -1
A13: ADP | B13: Sơn Á Đông | C13: HOSE | D13: 40046140679 | E13: 58934029150 | F13: 85313983000 | G13: 76460537616 | H13: =(G13-F13)/ABS(F13) -> -0.10377485 | I13: =(1+(G13-D13)/ABS(D13))^(1/3)-1 -> 0.24058224
A14: ADS | B14: Dệt sợi DAMSAN | C14: HOSE | D14: 67400984768 | E14: 58427517704 | F14: 50061325983 | G14: 99295485724 | H14: =(G14-F14)/ABS(F14) -> 0.98347694 | I14: =(1+(G14-D14)/ABS(D14))^(1/3)-1 -> 0.13785718
A15: AFX | B15: XNK Nông sản Thực phẩm An Giang | C15: HOSE | D15: 28626004427 | E15: 26515832213 | F15: 28011506150 | G15: 47319704573 | H15: =(G15-F15)/ABS(F15) -> 0.68929526 | I15: =(1+(G15-D15)/ABS(D15))^(1/3)-1 -> 0.18238913
A16: AGG | B16: Bất động sản An Gia | C16: HOSE | D16: 18965726119 | E16: 175358105259 | F16: 297500547919 | G16: 379195499373 | H16: =(G16-F16)/ABS(F16) -> 0.27460437 | I16: =(1+(G16-D16)/ABS(D16))^(1/3)-1 -> 1.7141337
A17: AGR | B17: Agriseco | C17: HOSE | D17: 146342776418 | E17: 148232020043 | F17: 135152065932 | G17: 141886639501 | H17: =(G17-F17)/ABS(F17) -> 0.049829601 | I17: =(1+(G17-D17)/ABS(D17))^(1/3)-1 -> -0.0102548
A18: ANT | B18: Rau quả thực phẩm An Giang | C18: HOSE | D18: 35207324309 | E18: 13624047714 | F18: 73141070582 | H18: =(G18-F18)/ABS(F18) -> -1 | I18: =(1+(G18-D18)/ABS(D18))^(1/3)-1 -> -1
A19: ANV | B19: Thủy sản Nam Việt | C19: HOSE | D19: 673745234347 | E19: 39191645110 | F19: 47832173647 | G19: 999477864573 | H19: =(G19-F19)/ABS(F19) -> 19.895514 | I19: =(1+(G19-D19)/ABS(D19))^(1/3)-1 -> 0.14049265
A20: APG | B20: Chứng khoán APG | C20: HOSE | D20: -190222982007 | E20: 140238801230 | F20: -130485614318 | G20: 5461341162 | H20: =(G20-F20)/ABS(F20) -> 1.041854 | I20: =(1+(G20-D20)/ABS(D20))^(1/3)-1 -> 0.2659212
A21: APH | B21: Tập đoàn An Phát Holdings | C21: HOSE | D21: -19476217687 | E21: 34653893038 | F21: 119051958721 | G21: 163530096565 | H21: =(G21-F21)/ABS(F21) -> 0.37360274 | I21: =(1+(G21-D21)/ABS(D21))^(1/3)-1 -> 1.1825338
A22: ASG | B22: Tập đoàn ASG | C22: HOSE | D22: 89140570807 | E22: 2803624554 | F22: 28009365286 | H22: =(G22-F22)/ABS(F22) -> -1 | I22: =(1+(G22-D22)/ABS(D22))^(1/3)-1 -> -1
A23: ASM | B23: Tập đoàn Sao Mai | C23: HOSE | D23: 628390227095 | E23: 195034280361 | F23: 180853915747 | H23: =(G23-F23)/ABS(F23) -> -1 | I23: =(1+(G23-D23)/ABS(D23))^(1/3)-1 -> -1
A24: ASP | B24: Dầu khí An Pha | C24: HOSE | D24: 1514241102 | E24: -153281822688 | F24: 7129425755 | H24: =(G24-F24)/ABS(F24) -> -1 | I24: =(1+(G24-D24)/ABS(D24))^(1/3)-1 -> -1
A25: AST | B25: Dịch vụ Hàng không Taseco | C25: HOSE | D25: 23147273239 | E25: 115579778195 | F25: 148621058440 | G25: 250170276714 | H25: =(G25-F25)/ABS(F25) -> 0.68327611 | I25: =(1+(G25-D25)/ABS(D25))^(1/3)-1 -> 1.2109485
A26: ATP | B26: T.Mại và DV An Thành | C26: HOSE | H26: =(G26-F26)/ABS(F26) -> #DIV/0! | I26: =(1+(G26-D26)/ABS(D26))^(1/3)-1 -> #DIV/0!
A27: BAF | B27: Nông nghiệp BAF Việt Nam | C27: HOSE | D27: 286687393478 | E27: 26375283530 | F27: 317047520186 | G27: 98252444426 | H27: =(G27-F27)/ABS(F27) -> -0.69010184 | I27: =(1+(G27-D27)/ABS(D27))^(1/3)-1 -> -0.30019304
A28: BCE | B28: XD và GT Bình Dương | C28: HOSE | D28: -58396060591 | E28: 779086770 | F28: 74583327505 | G28: 101184187695 | H28: =(G28-F28)/ABS(F28) -> 0.35665961 | I28: =(1+(G28-D28)/ABS(D28))^(1/3)-1 -> 0.55122662
A29: BCG | B29: Bamboo Capital | C29: HOSE | D29: 370773543503 | E29: 58983129855 | F29: 404013458717 | H29: =(G29-F29)/ABS(F29) -> -1 | I29: =(1+(G29-D29)/ABS(D29))^(1/3)-1 -> -1
A30: BCM | B30: Becamex Group | C30: HOSE | D30: 1700055767317 | E30: 2423168916542 | F30: 2187091169310 | G30: 3488464715525 | H30: =(G30-F30)/ABS(F30) -> 0.59502483 | I30: =(1+(G30-D30)/ABS(D30))^(1/3)-1 -> 0.27074104
A31: BFC | B31: Phân bón Bình Điền | C31: HOSE | D31: 149798354980 | E31: 148242218196 | F31: 357006351378 | H31: =(G31-F31)/ABS(F31) -> -1 | I31: =(1+(G31-D31)/ABS(D31))^(1/3)-1 -> -1
A32: BHN | B32: HABECO | C32: HOSE | D32: 464709725382 | E32: 336125947746 | F32: 370706599958 | G32: 468516760207 | H32: =(G32-F32)/ABS(F32) -> 0.26384791 | I32: =(1+(G32-D32)/ABS(D32))^(1/3)-1 -> 0.0027233386
A33: BIC | B33: Bảo hiểm BIDV | C33: HOSE | D33: 311516648031 | E33: 449786492195 | F33: 493625369570 | G33: 544057298219 | H33: =(G33-F33)/ABS(F33) -> 0.1021664 | I33: =(1+(G33-D33)/ABS(D33))^(1/3)-1 -> 0.2042624
A34: BID | B34: BIDV | C34: HOSE | D34: 18085912000000 | E34: 21504918000000 | F34: 25140037000000 | G34: 29956962000000 | H34: =(G34-F34)/ABS(F34) -> 0.19160374 | I34: =(1+(G34-D34)/ABS(D34))^(1/3)-1 -> 0.18318445
A35: BKG | B35: Đầu tư BKG Việt Nam | C35: HOSE | D35: 25930267484 | E35: 10540548000 | F35: 14559252016 | G35: 10214015663 | H35: =(G35-F35)/ABS(F35) -> -0.29845189 | I35: =(1+(G35-D35)/ABS(D35))^(1/3)-1 -> -0.26695634
A36: BMC | B36: Khoáng sản Bình Định | C36: HOSE | D36: 21339061199 | E36: 24197136802 | F36: 25541438834 | G36: 11516835981 | H36: =(G36-F36)/ABS(F36) -> -0.54909212 | I36: =(1+(G36-D36)/ABS(D36))^(1/3)-1 -> -0.18582214
A37: BMI | B37: Bảo hiểm Bảo Minh | C37: HOSE | D37: 290869393051 | E37: 328992884771 | F37: 237674042229 | H37: =(G37-F37)/ABS(F37) -> -1 | I37: =(1+(G37-D37)/ABS(D37))^(1/3)-1 -> -1
A38: BMP | B38: Nhựa Bình Minh | C38: HOSE | D38: 694268766316 | E38: 1041006333282 | F38: 990761729138 | G38: 1228735173562 | H38: =(G38-F38)/ABS(F38) -> 0.24019241 | I38: =(1+(G38-D38)/ABS(D38))^(1/3)-1 -> 0.20960495
A39: BRC | B39: Cao su Bến Thành | C39: HOSE | D39: 18621364579 | E39: 19420087019 | F39: 21751243495 | G39: 20817366533 | H39: =(G39-F39)/ABS(F39) -> -0.042934417 | I39: =(1+(G39-D39)/ABS(D39))^(1/3)-1 -> 0.037858378
A40: BSI | B40: Chứng khoán BIDV | C40: HOSE | D40: 112370678169 | E40: 408259606627 | F40: 413071438156 | G40: 493666033520 | H40: =(G40-F40)/ABS(F40) -> 0.19511055 | I40: =(1+(G40-D40)/ABS(D40))^(1/3)-1 -> 0.63779704
A41: BSR | B41: Lọc Hóa dầu Bình Sơn | C41: HOSE | D41: 14725833852993 | E41: 8649771483353 | F41: 631130749304 | G41: 5185942061885 | H41: =(G41-F41)/ABS(F41) -> 7.216906 | I41: =(1+(G41-D41)/ABS(D41))^(1/3)-1 -> -0.29381917
A42: BTP | B42: Nhiệt điện Bà Rịa | C42: HOSE | D42: 70744270207 | E42: 71821405002 | F42: 42816586078 | G42: 41255659773 | H42: =(G42-F42)/ABS(F42) -> -0.036456113 | I42: =(1+(G42-D42)/ABS(D42))^(1/3)-1 -> -0.1645302
A43: BTT | B43: TM - DV Bến Thành | C43: HOSE | D43: 17997614599 | E43: 49477707315 | F43: 46859114200 | G43: 66553765467 | H43: =(G43-F43)/ABS(F43) -> 0.420295 | I43: =(1+(G43-D43)/ABS(D43))^(1/3)-1 -> 0.5463907
A44: BVH | B44: Tập đoàn Bảo Việt | C44: HOSE | D44: 1550994189019 | E44: 1805317054880 | F44: 2110496926600 | H44: =(G44-F44)/ABS(F44) -> -1 | I44: =(1+(G44-D44)/ABS(D44))^(1/3)-1 -> -1
A45: BWE | B45: Nước - Môi trường Bình Dương | C45: HOSE | D45: 742842206787 | E45: 674461285967 | F45: 638928762826 | G45: 991949690144 | H45: =(G45-F45)/ABS(F45) -> 0.55252001 | I45: =(1+(G45-D45)/ABS(D45))^(1/3)-1 -> 0.10119532
A46: C32 | B46: Đầu tư và Xây dựng 3-2 | C46: HOSE | D46: 20510026476 | E46: -26983733569 | F46: 8129411124 | H46: =(G46-F46)/ABS(F46) -> -1 | I46: =(1+(G46-D46)/ABS(D46))^(1/3)-1 -> -1
A47: C47 | B47: Xây dựng 47 | C47: HOSE | D47: 14446636234 | E47: 14749936712 | F47: 3909189265 | G47: 52249441570 | H47: =(G47-F47)/ABS(F47) -> 12.3658 | I47: =(1+(G47-D47)/ABS(D47))^(1/3)-1 -> 0.53498795
A48: CCC | B48: Xây Dựng CDC | C48: HOSE | E48: 23709402998 | F48: 37103018561 | H48: =(G48-F48)/ABS(F48) -> -1 | I48: =(1+(G48-D48)/ABS(D48))^(1/3)-1 -> #DIV/0!
A49: CCI | B49: CIDICO | C49: HOSE | D49: 24913956670 | E49: 25155426972 | F49: 32827950428 | G49: 50350986083 | H49: =(G49-F49)/ABS(F49) -> 0.53378403 | I49: =(1+(G49-D49)/ABS(D49))^(1/3)-1 -> 0.26431442
A50: CCL | B50: ĐT & PT Đô thị Dầu khí Cửu Long | C50: HOSE | D50: 56129835102 | E50: 57697557914 | F50: 42364525565 | G50: 28396115598 | H50: =(G50-F50)/ABS(F50) -> -0.32971949 | I50: =(1+(G50-D50)/ABS(D50))^(1/3)-1 -> -0.20318949
A51: CDC | B51: Chương Dương Corp | C51: HOSE | D51: 4538994708 | E51: 8564054913 | F51: 24047538422 | H51: =(G51-F51)/ABS(F51) -> -1 | I51: =(1+(G51-D51)/ABS(D51))^(1/3)-1 -> -1
A52: CHP | B52: Thủy điện Miền Trung | C52: HOSE | D52: 510295093778 | E52: 336954868099 | F52: 313767090621 | G52: 459973917348 | H52: =(G52-F52)/ABS(F52) -> 0.46597247 | I52: =(1+(G52-D52)/ABS(D52))^(1/3)-1 -> -0.034014507
A53: CIG | B53: Xây dựng COMA 18 | C53: HOSE | D53: -6565738921 | E53: -7198834284 | F53: 54454820494 | H53: =(G53-F53)/ABS(F53) -> -1 | I53: =(1+(G53-D53)/ABS(D53))^(1/3)-1 -> 0.25992105
A54: CII | B54: Hạ tầng Kỹ thuật TP.HCM | C54: HOSE | D54: 695146941142 | E54: 178239051119 | F54: 257224236024 | G54: 132899164240 | H54: =(G54-F54)/ABS(F54) -> -0.48333343 | I54: =(1+(G54-D54)/ABS(D54))^(1/3)-1 -> -0.42392122
A55: CKG | B55: Tập đoàn CIC | C55: HOSE | D55: 167108087656 | E55: 143612337537 | F55: 122776269272 | H55: =(G55-F55)/ABS(F55) -> -1 | I55: =(1+(G55-D55)/ABS(D55))^(1/3)-1 -> -1
A56: CLC | B56: Thuốc lá Cát Lợi | C56: HOSE | D56: 140450356519 | E56: 143976462812 | F56: 150229088842 | G56: 182048908964 | H56: =(G56-F56)/ABS(F56) -> 0.21180865 | I56: =(1+(G56-D56)/ABS(D56))^(1/3)-1 -> 0.090322761
A57: CLL | B57: Cảng Cát Lái | C57: HOSE | D57: 90625958086 | E57: 96847450473 | F57: 97374835265 | H57: =(G57-F57)/ABS(F57) -> -1 | I57: =(1+(G57-D57)/ABS(D57))^(1/3)-1 -> -1
A58: CLW | B58: Cấp nước Chợ Lớn | C58: HOSE | D58: 30122538065 | E58: 48561329804 | F58: 53939786680 | G58: 56732922996 | H58: =(G58-F58)/ABS(F58) -> 0.051782487 | I58: =(1+(G58-D58)/ABS(D58))^(1/3)-1 -> 0.23494571
A59: CMG | B59: Tập đoàn Công nghệ CMC | C59: HOSE | D59: 301226857578 | E59: 324433723331 | F59: 312150507785 | H59: =(G59-F59)/ABS(F59) -> -1 | I59: =(1+(G59-D59)/ABS(D59))^(1/3)-1 -> -1
A60: CMV | B60: Thương nghiệp Cà Mau | C60: HOSE | D60: 23417696822 | E60: 16662668934 | F60: 11462227586 | H60: =(G60-F60)/ABS(F60) -> -1 | I60: =(1+(G60-D60)/ABS(D60))^(1/3)-1 -> -1
A61: CMX | B61: CAMIMEX Group | C61: HOSE | D61: 65845613553 | E61: 48835431041 | F61: 55986975289 | H61: =(G61-F61)/ABS(F61) -> -1 | I61: =(1+(G61-D61)/ABS(D61))^(1/3)-1 -> -1
A62: CNG | B62: CNG Việt Nam | C62: HOSE | D62: 117610813558 | E62: 110268725490 | F62: 90989398177 | G62: 69322420610 | H62: =(G62-F62)/ABS(F62) -> -0.2381264 | I62: =(1+(G62-D62)/ABS(D62))^(1/3)-1 -> -0.16155324
A63: COM | B63: Vật tư Xăng dầu | C63: HOSE | D63: 1278494699 | E63: 34457590900 | F63: 26876180026 | G63: 27470774923 | H63: =(G63-F63)/ABS(F63) -> 0.02212349 | I63: =(1+(G63-D63)/ABS(D63))^(1/3)-1 -> 1.7800802
A64: CRC | B64: Create Capital Việt Nam | C64: HOSE | D64: 24019101087 | E64: 28827721665 | F64: 63712509893 | G64: 56497176373 | H64: =(G64-F64)/ABS(F64) -> -0.1132483 | I64: =(1+(G64-D64)/ABS(D64))^(1/3)-1 -> 0.32991331
A65: CRE | B65: Bất động sản Thế Kỷ | C65: HOSE | D65: 190887249745 | E65: 2003729301 | F65: 41048046349 | H65: =(G65-F65)/ABS(F65) -> -1 | I65: =(1+(G65-D65)/ABS(D65))^(1/3)-1 -> -1
A66: CRV | B66: Tập đoàn Bất động sản CRV | C66: HOSE | D66: 440223907938 | E66: 740304380428 | F66: 756657409533 | H66: =(G66-F66)/ABS(F66) -> -1 | I66: =(1+(G66-D66)/ABS(D66))^(1/3)-1 -> -1
A67: CSM | B67: Cao su Miền Nam | C67: HOSE | D67: 79184939323 | E67: 60374641748 | F67: 72071490392 | G67: 48383526224 | H67: =(G67-F67)/ABS(F67) -> -0.32867316 | I67: =(1+(G67-D67)/ABS(D67))^(1/3)-1 -> -0.15143527
A68: CSV | B68: Hóa chất Cơ bản miền Nam | C68: HOSE | D68: 354438553738 | E68: 209138519943 | F68: 238636262415 | G68: 209476052121 | H68: =(G68-F68)/ABS(F68) -> -0.12219522 | I68: =(1+(G68-D68)/ABS(D68))^(1/3)-1 -> -0.16080193
A69: CTD | B69: Xây dựng Coteccons | C69: HOSE | D69: 20712200279 | E69: 187939139994 | F69: 371375360821 | H69: =(G69-F69)/ABS(F69) -> -1 | I69: =(1+(G69-D69)/ABS(D69))^(1/3)-1 -> -1
A70: CTF | B70: City Auto | C70: HOSE | D70: 111714765882 | E70: 40987323009 | F70: 46431500593 | H70: =(G70-F70)/ABS(F70) -> -1 | I70: =(1+(G70-D70)/ABS(D70))^(1/3)-1 -> -1
A71: CTG | B71: VietinBank | C71: HOSE | D71: 16923725000000 | E71: 19903550000000 | F71: 25348215000000 | G71: 34590657000000 | H71: =(G71-F71)/ABS(F71) -> 0.36461905 | I71: =(1+(G71-D71)/ABS(D71))^(1/3)-1 -> 0.26907596
A72: CTI | B72: Cường Thuận IDICO | C72: HOSE | D72: 92449762260 | E72: 76508381933 | F72: 99068458805 | H72: =(G72-F72)/ABS(F72) -> -1 | I72: =(1+(G72-D72)/ABS(D72))^(1/3)-1 -> -1
A73: CTR | B73: Công trình Viettel | C73: HOSE | D73: 455155190939 | E73: 524597395205 | F73: 538221178258 | G73: 599830934458 | H73: =(G73-F73)/ABS(F73) -> 0.11446922 | I73: =(1+(G73-D73)/ABS(D73))^(1/3)-1 -> 0.096368257
A74: CTS | B74: Chứng khoán Vietinbank | C74: HOSE | D74: 71067936264 | E74: 187400978164 | F74: 231086774298 | G74: 577371584960 | H74: =(G74-F74)/ABS(F74) -> 1.4985055 | I74: =(1+(G74-D74)/ABS(D74))^(1/3)-1 -> 1.0102986
A75: CVT | B75: CMC JSC | C75: HOSE | D75: 94937904086 | E75: 40609938397 | F75: 59808256831 | H75: =(G75-F75)/ABS(F75) -> -1 | I75: =(1+(G75-D75)/ABS(D75))^(1/3)-1 -> -1
A76: D2D | B76: Phát triển Đô thị số 2 | C76: HOSE | D76: 17181711324 | E76: 25753192699 | F76: 88209222744 | G76: 241083409169 | H76: =(G76-F76)/ABS(F76) -> 1.7330862 | I76: =(1+(G76-D76)/ABS(D76))^(1/3)-1 -> 1.4119426
A77: DAH | B77: Tập đoàn Khách sạn Đông Á | C77: HOSE | D77: 43315814732 | E77: 3797166303 | F77: 6847979293 | G77: -70045210331 | H77: =(G77-F77)/ABS(F77) -> -11.228596 | I77: =(1+(G77-D77)/ABS(D77))^(1/3)-1 -> -2.1737546
A78: DAT | B78: ĐT Du lịch và PT Thủy sản | C78: HOSE | D78: 80098959462 | E78: 75313544684 | F78: 58876691423 | G78: 71850941419 | H78: =(G78-F78)/ABS(F78) -> 0.2203631 | I78: =(1+(G78-D78)/ABS(D78))^(1/3)-1 -> -0.035574845
A79: DBC | B79: Tập đoàn DABACO | C79: HOSE | D79: 5194587097 | E79: 25007194215 | F79: 769083752455 | G79: 1506767998626 | H79: =(G79-F79)/ABS(F79) -> 0.95917284 | I79: =(1+(G79-D79)/ABS(D79))^(1/3)-1 -> 5.6196006
A80: DBD | B80: Dược - TB Y tế Bình Định | C80: HOSE | D80: 243555116974 | E80: 269054870446 | F80: 275181949187 | G80: 290747859813 | H80: =(G80-F80)/ABS(F80) -> 0.056565885 | I80: =(1+(G80-D80)/ABS(D80))^(1/3)-1 -> 0.060815254
A81: DBT | B81: Dược phẩm Bến Tre | C81: HOSE | D81: 37990840748 | E81: 16194822010 | F81: 14580884448 | H81: =(G81-F81)/ABS(F81) -> -1 | I81: =(1+(G81-D81)/ABS(D81))^(1/3)-1 -> -1
A82: DC4 | B82: Dicera Holdings | C82: HOSE | D82: -1853054431 | E82: 107358961940 | F82: 120670053678 | H82: =(G82-F82)/ABS(F82) -> -1 | I82: =(1+(G82-D82)/ABS(D82))^(1/3)-1 -> 0.25992105
A83: DCL | B83: Dược phẩm Cửu Long | C83: HOSE | D83: 111640895900 | E83: 61717400131 | F83: 53571100053 | G83: 19516497827 | H83: =(G83-F83)/ABS(F83) -> -0.63568981 | I83: =(1+(G83-D83)/ABS(D83))^(1/3)-1 -> -0.44085275
A84: DCM | B84: Đạm Cà Mau | C84: HOSE | D84: 4315953289589 | E84: 1108892825082 | F84: 1419657938042 | G84: 1915242494331 | H84: =(G84-F84)/ABS(F84) -> 0.3490873 | I84: =(1+(G84-D84)/ABS(D84))^(1/3)-1 -> -0.23724978
A85: DGC | B85: Hóa chất Đức Giang | C85: HOSE | D85: 5565005078678 | E85: 3110379605233 | F85: 2986646667039 | G85: 3024975472108 | H85: =(G85-F85)/ABS(F85) -> 0.012833391 | I85: =(1+(G85-D85)/ABS(D85))^(1/3)-1 -> -0.18388361
A86: DGW | B86: Thế Giới Số | C86: HOSE | D86: 683783287082 | E86: 354392478066 | F86: 443877018277 | G86: 547878824084 | H86: =(G86-F86)/ABS(F86) -> 0.2343032 | I86: =(1+(G86-D86)/ABS(D86))^(1/3)-1 -> -0.071200418
A87: DHA | B87: Hóa An | C87: HOSE | D87: 52332261663 | E87: 87053668250 | F87: 51706620002 | G87: 109743442537 | H87: =(G87-F87)/ABS(F87) -> 1.1224254 | I87: =(1+(G87-D87)/ABS(D87))^(1/3)-1 -> 0.27997953
A88: DHC | B88: Đông Hải Bến Tre | C88: HOSE | D88: 379458584417 | E88: 309338388739 | F88: 242066983472 | G88: 392923854907 | H88: =(G88-F88)/ABS(F88) -> 0.623203 | I88: =(1+(G88-D88)/ABS(D88))^(1/3)-1 -> 0.011691275
A89: DHG | B89: Dược Hậu Giang | C89: HOSE | D89: 988454646072 | E89: 1050662658695 | F89: 775985500216 | G89: 897576116728 | H89: =(G89-F89)/ABS(F89) -> 0.15669187 | I89: =(1+(G89-D89)/ABS(D89))^(1/3)-1 -> -0.031637015
A90: DHM | B90: Khoáng sản Dương Hiếu | C90: HOSE | D90: 1260215640 | E90: 5977885872 | F90: 2775000948 | G90: 6557706842 | H90: =(G90-F90)/ABS(F90) -> 1.3631368 | I90: =(1+(G90-D90)/ABS(D90))^(1/3)-1 -> 0.73288221
A91: DIG | B91: DIC Corp | C91: HOSE | D91: 144128258788 | E91: 118727079683 | F91: 114535926550 | G91: 647777743179 | H91: =(G91-F91)/ABS(F91) -> 4.655673 | I91: =(1+(G91-D91)/ABS(D91))^(1/3)-1 -> 0.65028503
A92: DLG | B92: Đức Long Gia Lai | C92: HOSE | D92: -1219413266472 | E92: -594601137150 | F92: 207913506193 | G92: 364828801399 | H92: =(G92-F92)/ABS(F92) -> 0.75471429 | I92: =(1+(G92-D92)/ABS(D92))^(1/3)-1 -> 0.31984998
A93: DMC | B93: Dược phẩm DOMESCO | C93: HOSE | D93: 200075859018 | E93: 183332760778 | F93: 202706657601 | G93: 198031786940 | H93: =(G93-F93)/ABS(F93) -> -0.023062245 | I93: =(1+(G93-D93)/ABS(D93))^(1/3)-1 -> -0.0034171588
A94: DPG | B94: Tập đoàn Đạt Phương | C94: HOSE | D94: 383255183201 | E94: 203043479885 | F94: 223868298579 | G94: 326722500735 | H94: =(G94-F94)/ABS(F94) -> 0.45944067 | I94: =(1+(G94-D94)/ABS(D94))^(1/3)-1 -> -0.051806437
... A96: DPR | B96: Cao su Đồng Phú | C96: HOSE | D96: 252292001241 | E96: 208841302416 | F96: 261993113128 | G96: 316090098482 | H96: =(G96-F96)/ABS(F96) -> 0.20648247 | I96: =(1+(G96-D96)/ABS(D96))^(1/3)-1 -> 0.078042304
A97: DQC | B97: Tập đoàn Điện Quang | C97: HOSE | D97: 13763699815 | E97: -34398607808 | F97: -122564233007 | H97: =(G97-F97)/ABS(F97) -> 1 | I97: =(1+(G97-D97)/ABS(D97))^(1/3)-1 -> -1
A98: DRC | B98: Cao su Đà Nẵng | C98: HOSE | D98: 307184677256 | E98: 246334432758 | F98: 231618562349 | G98: 121201535880 | H98: =(G98-F98)/ABS(F98) -> -0.47671925 | I98: =(1+(G98-D98)/ABS(D98))^(1/3)-1 -> -0.26655167
A99: DRH | B99: DRH Holdings | C99: HOSE | D99: 66150880 | E99: -103750302666 | F99: -203162910983 | G99: 15645149576 | H99: =(G99-F99)/ABS(F99) -> 1.0770079 | I99: =(1+(G99-D99)/ABS(D99))^(1/3)-1 -> 5.1841692
A100: DRL | B100: Thủy điện - Điện lực 3 | C100: HOSE | D100: 61972910646 | E100: 58029556966 | F100: 44762427034 | G100: 49746472890 | H100: =(G100-F100)/ABS(F100) -> 0.11134441 | I100: =(1+(G100-D100)/ABS(D100))^(1/3)-1 -> -0.070633958
A101: DSC | B101: Chứng khoán DSC | C101: HOSE | D101: 33447233813 | E101: 119916788312 | F101: 176819852316 | G101: 275195244279 | H101: =(G101-F101)/ABS(F101) -> 0.55635943 | I101: =(1+(G101-D101)/ABS(D101))^(1/3)-1 -> 1.0188013
...

Sheet Lọc
D1: Doanh thu | H1: Lợi nhuận | L1: Doanh thu YoY% | P1: Lợi nhuận YoY% | T1: Biên gộp | X1: Tăng trưởng năm | AB1: I, II, III, IV tương ứng 4 quý gần nhất
A2: Mã CK | B2: Tên | C2: Ngành | D2: I | E2: II | F2: III | G2: IV | H2: I | I2: II | J2: III | K2: IV | L2: I | M2: II | N2: III | O2: IV | P2: I | Q2: II | R2: III | S2: IV | T2: I | U2: II | V2: III | W2: IV | X2: 20/19 | Y2: 4 năm | Z2: EPS 4 quý | AA2: P/E | AB2: IV tương đương quý gần nhất
A3: DBV | B3: QL và Sửa chữa đường bộ Vĩnh Phúc | C3: =VLOOKUP(A3,'GIÁ CP'!$K$2:$M$2000,3,FALSE) -> Xây dựng | D3: =VLOOKUP($A3,'Doanh thu'!$A$3:$Q$2000,9,FALSE)/1000000000 -> #N/A | E3: =VLOOKUP($A3,'Doanh thu'!$A$3:$Q$2000,10,FALSE)/1000000000 -> #N/A | F3: =VLOOKUP($A3,'Doanh thu'!$A$3:$Q$2000,11,FALSE)/1000000000 -> #N/A | G3: =VLOOKUP($A3,'Doanh thu'!$A$3:$Q$2000,12,FALSE)/1000000000 -> #N/A | H3: =VLOOKUP($A3,LNST!$A$3:$Q$1635,9,FALSE)/1000000000 -> #N/A | I3: =VLOOKUP($A3,LNST!$A$3:$Q$1635,10,FALSE)/1000000000 -> #N/A | J3: =VLOOKUP($A3,LNST!$A$3:$Q$1635,11,FALSE)/1000000000 -> #N/A | K3: =VLOOKUP($A3,LNST!$A$3:$Q$1635,12,FALSE)/1000000000 -> #N/A | L3: =VLOOKUP($A3,'Doanh thu'!$A$3:$Q$2000,14,FALSE) -> #N/A | M3: =VLOOKUP($A3,'Doanh thu'!$A$3:$Q$2000,15,FALSE) -> #N/A | N3: =VLOOKUP($A3,'Doanh thu'!$A$3:$Q$2000,16,FALSE) -> #N/A | O3: =VLOOKUP($A3,'Doanh thu'!$A$3:$Q$2000,17,FALSE) -> #N/A | P3: =VLOOKUP($A3,LNST!$A$3:$R$1635,14,FALSE) -> #N/A | Q3: =VLOOKUP($A3,LNST!$A$3:$R$1635,15,FALSE) -> #N/A | R3: =VLOOKUP($A3,LNST!$A$3:$R$1635,16,FALSE) -> #N/A | S3: =VLOOKUP($A3,LNST!$A$3:$R$1635,17,FALSE) -> #N/A | T3: =VLOOKUP($A3,LNG!$A$2:$H$1999,4,FALSE)/(D3*10^9) -> #N/A | U3: =VLOOKUP($A3,LNG!$A$2:$H$1999,5,FALSE)/(E3*10^9) -> #N/A | V3: =VLOOKUP($A3,LNG!$A$2:$H$1999,6,FALSE)/(F3*10^9) -> #N/A | W3: =VLOOKUP($A3,LNG!$A$2:$H$1999,7,FALSE)/(G3*10^9) -> #N/A | X3: =VLOOKUP($A3,'LNST năm'!$A$2:$I$2000,8,FALSE) -> #N/A | Y3: =VLOOKUP($A3,'LNST năm'!$A$2:$I$2000,9,FALSE) -> #N/A | Z3: =VLOOKUP($A3,LNG!$A$2:$H$1999,9,FALSE) -> #N/A | AA3: =VLOOKUP($A3,'GIÁ CP'!$A$2:$D$2000,4,FALSE)/Z3 -> #N/A
A4: SCV | B4: Muối Việt Nam | C4: =VLOOKUP(A4,'GIÁ CP'!$K$2:$M$2000,3,FALSE) -> Nuôi trồng nông & hải sản | D4: =VLOOKUP($A4,'Doanh thu'!$A$3:$Q$2000,9,FALSE)/1000000000 -> #N/A | E4: =VLOOKUP($A4,'Doanh thu'!$A$3:$Q$2000,10,FALSE)/1000000000 -> #N/A | F4: =VLOOKUP($A4,'Doanh thu'!$A$3:$Q$2000,11,FALSE)/1000000000 -> #N/A | G4: =VLOOKUP($A4,'Doanh thu'!$A$3:$Q$2000,12,FALSE)/1000000000 -> #N/A | H4: =VLOOKUP($A4,LNST!$A$3:$Q$1635,9,FALSE)/1000000000 -> #N/A | I4: =VLOOKUP($A4,LNST!$A$3:$Q$1635,10,FALSE)/1000000000 -> #N/A | J4: =VLOOKUP($A4,LNST!$A$3:$Q$1635,11,FALSE)/1000000000 -> #N/A | K4: =VLOOKUP($A4,LNST!$A$3:$Q$1635,12,FALSE)/1000000000 -> #N/A | L4: =VLOOKUP($A4,'Doanh thu'!$A$3:$Q$2000,14,FALSE) -> #N/A | M4: =VLOOKUP($A4,'Doanh thu'!$A$3:$Q$2000,15,FALSE) -> #N/A | N4: =VLOOKUP($A4,'Doanh thu'!$A$3:$Q$2000,16,FALSE) -> #N/A | O4: =VLOOKUP($A4,'Doanh thu'!$A$3:$Q$2000,17,FALSE) -> #N/A | P4: =VLOOKUP($A4,LNST!$A$3:$R$1635,14,FALSE) -> #N/A | Q4: =VLOOKUP($A4,LNST!$A$3:$R$1635,15,FALSE) -> #N/A | R4: =VLOOKUP($A4,LNST!$A$3:$R$1635,16,FALSE) -> #N/A | S4: =VLOOKUP($A4,LNST!$A$3:$R$1635,17,FALSE) -> #N/A | T4: =VLOOKUP($A4,LNG!$A$2:$H$1999,4,FALSE)/(D4*10^9) -> #N/A | U4: =VLOOKUP($A4,LNG!$A$2:$H$1999,5,FALSE)/(E4*10^9) -> #N/A | V4: =VLOOKUP($A4,LNG!$A$2:$H$1999,6,FALSE)/(F4*10^9) -> #N/A | W4: =VLOOKUP($A4,LNG!$A$2:$H$1999,7,FALSE)/(G4*10^9) -> #N/A | X4: =VLOOKUP($A4,'LNST năm'!$A$2:$I$2000,8,FALSE) -> #N/A | Y4: =VLOOKUP($A4,'LNST năm'!$A$2:$I$2000,9,FALSE) -> #N/A | Z4: =VLOOKUP($A4,LNG!$A$2:$H$1999,9,FALSE) -> #N/A | AA4: =VLOOKUP($A4,'GIÁ CP'!$A$2:$D$2000,4,FALSE)/Z4 -> #N/A
A5: LYF | B5: Công ty Lương Thực Lương Yên | C5: =VLOOKUP(A5,'GIÁ CP'!$K$2:$M$2000,3,FALSE) -> Thực phẩm | D5: =VLOOKUP($A5,'Doanh thu'!$A$3:$Q$2000,9,FALSE)/1000000000 -> #N/A | E5: =VLOOKUP($A5,'Doanh thu'!$A$3:$Q$2000,10,FALSE)/1000000000 -> #N/A | F5: =VLOOKUP($A5,'Doanh thu'!$A$3:$Q$2000,11,FALSE)/1000000000 -> #N/A | G5: =VLOOKUP($A5,'Doanh thu'!$A$3:$Q$2000,12,FALSE)/1000000000 -> #N/A | H5: =VLOOKUP($A5,LNST!$A$3:$Q$1635,9,FALSE)/1000000000 -> #N/A | I5: =VLOOKUP($A5,LNST!$A$3:$Q$1635,10,FALSE)/1000000000 -> #N/A | J5: =VLOOKUP($A5,LNST!$A$3:$Q$1635,11,FALSE)/1000000000 -> #N/A | K5: =VLOOKUP($A5,LNST!$A$3:$Q$1635,12,FALSE)/1000000000 -> #N/A | L5: =VLOOKUP($A5,'Doanh thu'!$A$3:$Q$2000,14,FALSE) -> #N/A | M5: =VLOOKUP($A5,'Doanh thu'!$A$3:$Q$2000,15,FALSE) -> #N/A | N5: =VLOOKUP($A5,'Doanh thu'!$A$3:$Q$2000,16,FALSE) -> #N/A | O5: =VLOOKUP($A5,'Doanh thu'!$A$3:$Q$2000,17,FALSE) -> #N/A | P5: =VLOOKUP($A5,LNST!$A$3:$R$1635,14,FALSE) -> #N/A | Q5: =VLOOKUP($A5,LNST!$A$3:$R$1635,15,FALSE) -> #N/A | R5: =VLOOKUP($A5,LNST!$A$3:$R$1635,16,FALSE) -> #N/A | S5: =VLOOKUP($A5,LNST!$A$3:$R$1635,17,FALSE) -> #N/A | T5: =VLOOKUP($A5,LNG!$A$2:$H$1999,4,FALSE)/(D5*10^9) -> #N/A | U5: =VLOOKUP($A5,LNG!$A$2:$H$1999,5,FALSE)/(E5*10^9) -> #N/A | V5: =VLOOKUP($A5,LNG!$A$2:$H$1999,6,FALSE)/(F5*10^9) -> #N/A | W5: =VLOOKUP($A5,LNG!$A$2:$H$1999,7,FALSE)/(G5*10^9) -> #N/A | X5: =VLOOKUP($A5,'LNST năm'!$A$2:$I$2000,8,FALSE) -> #N/A | Y5: =VLOOKUP($A5,'LNST năm'!$A$2:$I$2000,9,FALSE) -> #N/A | Z5: =VLOOKUP($A5,LNG!$A$2:$H$1999,9,FALSE) -> #N/A | AA5: =VLOOKUP($A5,'GIÁ CP'!$A$2:$D$2000,4,FALSE)/Z5 -> #N/A
A6: HTH | B6: Hoa tiêu Hàng hải - TKV | C6: =VLOOKUP(A6,'GIÁ CP'!$K$2:$M$2000,3,FALSE) -> Kho bãi, hậu cần và bảo dưỡng | D6: =VLOOKUP($A6,'Doanh thu'!$A$3:$Q$2000,9,FALSE)/1000000000 -> #N/A | E6: =VLOOKUP($A6,'Doanh thu'!$A$3:$Q$2000,10,FALSE)/1000000000 -> #N/A | F6: =VLOOKUP($A6,'Doanh thu'!$A$3:$Q$2000,11,FALSE)/1000000000 -> #N/A | G6: =VLOOKUP($A6,'Doanh thu'!$A$3:$Q$2000,12,FALSE)/1000000000 -> #N/A | H6: =VLOOKUP($A6,LNST!$A$3:$Q$1635,9,FALSE)/1000000000 -> #N/A | I6: =VLOOKUP($A6,LNST!$A$3:$Q$1635,10,FALSE)/1000000000 -> #N/A | J6: =VLOOKUP($A6,LNST!$A$3:$Q$1635,11,FALSE)/1000000000 -> #N/A | K6: =VLOOKUP($A6,LNST!$A$3:$Q$1635,12,FALSE)/1000000000 -> #N/A | L6: =VLOOKUP($A6,'Doanh thu'!$A$3:$Q$2000,14,FALSE) -> #N/A | M6: =VLOOKUP($A6,'Doanh thu'!$A$3:$Q$2000,15,FALSE) -> #N/A | N6: =VLOOKUP($A6,'Doanh thu'!$A$3:$Q$2000,16,FALSE) -> #N/A | O6: =VLOOKUP($A6,'Doanh thu'!$A$3:$Q$2000,17,FALSE) -> #N/A | P6: =VLOOKUP($A6,LNST!$A$3:$R$1635,14,FALSE) -> #N/A | Q6: =VLOOKUP($A6,LNST!$A$3:$R$1635,15,FALSE) -> #N/A | R6: =VLOOKUP($A6,LNST!$A$3:$R$1635,16,FALSE) -> #N/A | S6: =VLOOKUP($A6,LNST!$A$3:$R$1635,17,FALSE) -> #N/A | T6: =VLOOKUP($A6,LNG!$A$2:$H$1999,4,FALSE)/(D6*10^9) -> #N/A | U6: =VLOOKUP($A6,LNG!$A$2:$H$1999,5,FALSE)/(E6*10^9) -> #N/A | V6: =VLOOKUP($A6,LNG!$A$2:$H$1999,6,FALSE)/(F6*10^9) -> #N/A | W6: =VLOOKUP($A6,LNG!$A$2:$H$1999,7,FALSE)/(G6*10^9) -> #N/A | X6: =VLOOKUP($A6,'LNST năm'!$A$2:$I$2000,8,FALSE) -> #N/A | Y6: =VLOOKUP($A6,'LNST năm'!$A$2:$I$2000,9,FALSE) -> #N/A | Z6: =VLOOKUP($A6,LNG!$A$2:$H$1999,9,FALSE) -> #N/A | AA6: =VLOOKUP($A6,'GIÁ CP'!$A$2:$D$2000,4,FALSE)/Z6 -> #N/A
A7: LPT | B7: TM và SX Lập Phương Thành | C7: =VLOOKUP(A7,'GIÁ CP'!$K$2:$M$2000,3,FALSE) -> Đào tạo & Việc làm | D7: =VLOOKUP($A7,'Doanh thu'!$A$3:$Q$2000,9,FALSE)/1000000000 -> 83.249055 | E7: =VLOOKUP($A7,'Doanh thu'!$A$3:$Q$2000,10,FALSE)/1000000000 -> 74.111288 | F7: =VLOOKUP($A7,'Doanh thu'!$A$3:$Q$2000,11,FALSE)/1000000000 -> 78.273342 | G7: =VLOOKUP($A7,'Doanh thu'!$A$3:$Q$2000,12,FALSE)/1000000000 -> 113.26877 | H7: =VLOOKUP($A7,LNST!$A$3:$Q$1635,9,FALSE)/1000000000 -> 0.33301626 | I7: =VLOOKUP($A7,LNST!$A$3:$Q$1635,10,FALSE)/1000000000 -> 3.9322022 | J7: =VLOOKUP($A7,LNST!$A$3:$Q$1635,11,FALSE)/1000000000 -> 7.9923162 | K7: =VLOOKUP($A7,LNST!$A$3:$Q$1635,12,FALSE)/1000000000 -> 6.3921186 | L7: =VLOOKUP($A7,'Doanh thu'!$A$3:$Q$2000,14,FALSE) -> -0.1260799 | M7: =VLOOKUP($A7,'Doanh thu'!$A$3:$Q$2000,15,FALSE) -> 0.032061299 | N7: =VLOOKUP($A7,'Doanh thu'!$A$3:$Q$2000,16,FALSE) -> 0.077223678 | O7: =VLOOKUP($A7,'Doanh thu'!$A$3:$Q$2000,17,FALSE) -> 0.39598299 | P7: =VLOOKUP($A7,LNST!$A$3:$R$1635,14,FALSE) -> -0.92727759 | Q7: =VLOOKUP($A7,LNST!$A$3:$R$1635,15,FALSE) -> 1.1979189 | R7: =VLOOKUP($A7,LNST!$A$3:$R$1635,16,FALSE) -> 3.3708026 | S7: =VLOOKUP($A7,LNST!$A$3:$R$1635,17,FALSE) -> 3.0320277 | T7: =VLOOKUP($A7,LNG!$A$2:$H$1999,4,FALSE)/(D7*10^9) -> -0.0088467399 | U7: =VLOOKUP($A7,LNG!$A$2:$H$1999,5,FALSE)/(E7*10^9) -> 0.024288142 | V7: =VLOOKUP($A7,LNG!$A$2:$H$1999,6,FALSE)/(F7*10^9) -> 0.075142136 | W7: =VLOOKUP($A7,LNG!$A$2:$H$1999,7,FALSE)/(G7*10^9) -> 0.10310785 | X7: =VLOOKUP($A7,'LNST năm'!$A$2:$I$2000,8,FALSE) -> -0.35667616 | Y7: =VLOOKUP($A7,'LNST năm'!$A$2:$I$2000,9,FALSE) -> -0.016543997 | Z7: =VLOOKUP($A7,LNG!$A$2:$H$1999,9,FALSE) -> #REF! | AA7: =VLOOKUP($A7,'GIÁ CP'!$A$2:$D$2000,4,FALSE)/Z7 -> #REF!
A8: ACE | B8: Bê tông An Giang | C8: =VLOOKUP(A8,'GIÁ CP'!$K$2:$M$2000,3,FALSE) -> Vật liệu xây dựng & Nội thất | D8: =VLOOKUP($A8,'Doanh thu'!$A$3:$Q$2000,9,FALSE)/1000000000 -> 0 | E8: =VLOOKUP($A8,'Doanh thu'!$A$3:$Q$2000,10,FALSE)/1000000000 -> 0 | F8: =VLOOKUP($A8,'Doanh thu'!$A$3:$Q$2000,11,FALSE)/1000000000 -> 0 | G8: =VLOOKUP($A8,'Doanh thu'!$A$3:$Q$2000,12,FALSE)/1000000000 -> 0 | H8: =VLOOKUP($A8,LNST!$A$3:$Q$1635,9,FALSE)/1000000000 -> 0 | I8: =VLOOKUP($A8,LNST!$A$3:$Q$1635,10,FALSE)/1000000000 -> 0 | J8: =VLOOKUP($A8,LNST!$A$3:$Q$1635,11,FALSE)/1000000000 -> 0 | K8: =VLOOKUP($A8,LNST!$A$3:$Q$1635,12,FALSE)/1000000000 -> 0 | L8: =VLOOKUP($A8,'Doanh thu'!$A$3:$Q$2000,14,FALSE) -> #DIV/0! | M8: =VLOOKUP($A8,'Doanh thu'!$A$3:$Q$2000,15,FALSE) -> #DIV/0! | N8: =VLOOKUP($A8,'Doanh thu'!$A$3:$Q$2000,16,FALSE) -> #DIV/0! | O8: =VLOOKUP($A8,'Doanh thu'!$A$3:$Q$2000,17,FALSE) -> #DIV/0! | P8: =VLOOKUP($A8,LNST!$A$3:$R$1635,14,FALSE) -> #DIV/0! | Q8: =VLOOKUP($A8,LNST!$A$3:$R$1635,15,FALSE) -> #DIV/0! | R8: =VLOOKUP($A8,LNST!$A$3:$R$1635,16,FALSE) -> #DIV/0! | S8: =VLOOKUP($A8,LNST!$A$3:$R$1635,17,FALSE) -> #DIV/0! | T8: =VLOOKUP($A8,LNG!$A$2:$H$1999,4,FALSE)/(D8*10^9) -> #DIV/0! | U8: =VLOOKUP($A8,LNG!$A$2:$H$1999,5,FALSE)/(E8*10^9) -> #DIV/0! | V8: =VLOOKUP($A8,LNG!$A$2:$H$1999,6,FALSE)/(F8*10^9) -> #DIV/0! | W8: =VLOOKUP($A8,LNG!$A$2:$H$1999,7,FALSE)/(G8*10^9) -> #DIV/0! | X8: =VLOOKUP($A8,'LNST năm'!$A$2:$I$2000,8,FALSE) -> -1 | Y8: =VLOOKUP($A8,'LNST năm'!$A$2:$I$2000,9,FALSE) -> -1 | Z8: =VLOOKUP($A8,LNG!$A$2:$H$1999,9,FALSE) -> #REF! | AA8: =VLOOKUP($A8,'GIÁ CP'!$A$2:$D$2000,4,FALSE)/Z8 -> #REF!
A9: ACS | B9: Xây lắp Thương mại 2 | C9: =VLOOKUP(A9,'GIÁ CP'!$K$2:$M$2000,3,FALSE) -> Xây dựng | D9: =VLOOKUP($A9,'Doanh thu'!$A$3:$Q$2000,9,FALSE)/1000000000 -> 0 | E9: =VLOOKUP($A9,'Doanh thu'!$A$3:$Q$2000,10,FALSE)/1000000000 -> 0 | F9: =VLOOKUP($A9,'Doanh thu'!$A$3:$Q$2000,11,FALSE)/1000000000 -> 0 | G9: =VLOOKUP($A9,'Doanh thu'!$A$3:$Q$2000,12,FALSE)/1000000000 -> 0 | H9: =VLOOKUP($A9,LNST!$A$3:$Q$1635,9,FALSE)/1000000000 -> 0 | I9: =VLOOKUP($A9,LNST!$A$3:$Q$1635,10,FALSE)/1000000000 -> 0 | J9: =VLOOKUP($A9,LNST!$A$3:$Q$1635,11,FALSE)/1000000000 -> 0 | K9: =VLOOKUP($A9,LNST!$A$3:$Q$1635,12,FALSE)/1000000000 -> 0 | L9: =VLOOKUP($A9,'Doanh thu'!$A$3:$Q$2000,14,FALSE) -> #DIV/0! | M9: =VLOOKUP($A9,'Doanh thu'!$A$3:$Q$2000,15,FALSE) -> #DIV/0! | N9: =VLOOKUP($A9,'Doanh thu'!$A$3:$Q$2000,16,FALSE) -> #DIV/0! | O9: =VLOOKUP($A9,'Doanh thu'!$A$3:$Q$2000,17,FALSE) -> #DIV/0! | P9: =VLOOKUP($A9,LNST!$A$3:$R$1635,14,FALSE) -> #DIV/0! | Q9: =VLOOKUP($A9,LNST!$A$3:$R$1635,15,FALSE) -> #DIV/0! | R9: =VLOOKUP($A9,LNST!$A$3:$R$1635,16,FALSE) -> #DIV/0! | S9: =VLOOKUP($A9,LNST!$A$3:$R$1635,17,FALSE) -> #DIV/0! | T9: =VLOOKUP($A9,LNG!$A$2:$H$1999,4,FALSE)/(D9*10^9) -> #DIV/0! | U9: =VLOOKUP($A9,LNG!$A$2:$H$1999,5,FALSE)/(E9*10^9) -> #DIV/0! | V9: =VLOOKUP($A9,LNG!$A$2:$H$1999,6,FALSE)/(F9*10^9) -> #DIV/0! | W9: =VLOOKUP($A9,LNG!$A$2:$H$1999,7,FALSE)/(G9*10^9) -> #DIV/0! | X9: =VLOOKUP($A9,'LNST năm'!$A$2:$I$2000,8,FALSE) -> -1 | Y9: =VLOOKUP($A9,'LNST năm'!$A$2:$I$2000,9,FALSE) -> -1 | Z9: =VLOOKUP($A9,LNG!$A$2:$H$1999,9,FALSE) -> #REF! | AA9: =VLOOKUP($A9,'GIÁ CP'!$A$2:$D$2000,4,FALSE)/Z9 -> #REF!
A10: AGB | B10: Công ty Bình Phú | C10: =VLOOKUP(A10,'GIÁ CP'!$K$2:$M$2000,3,FALSE) -> Hàng May mặc | D10: =VLOOKUP($A10,'Doanh thu'!$A$3:$Q$2000,9,FALSE)/1000000000 -> #N/A | E10: =VLOOKUP($A10,'Doanh thu'!$A$3:$Q$2000,10,FALSE)/1000000000 -> #N/A | F10: =VLOOKUP($A10,'Doanh thu'!$A$3:$Q$2000,11,FALSE)/1000000000 -> #N/A | G10: =VLOOKUP($A10,'Doanh thu'!$A$3:$Q$2000,12,FALSE)/1000000000 -> #N/A | H10: =VLOOKUP($A10,LNST!$A$3:$Q$1635,9,FALSE)/1000000000 -> #N/A | I10: =VLOOKUP($A10,LNST!$A$3:$Q$1635,10,FALSE)/1000000000 -> #N/A | J10: =VLOOKUP($A10,LNST!$A$3:$Q$1635,11,FALSE)/1000000000 -> #N/A | K10: =VLOOKUP($A10,LNST!$A$3:$Q$1635,12,FALSE)/1000000000 -> #N/A | L10: =VLOOKUP($A10,'Doanh thu'!$A$3:$Q$2000,14,FALSE) -> #N/A | M10: =VLOOKUP($A10,'Doanh thu'!$A$3:$Q$2000,15,FALSE) -> #N/A | N10: =VLOOKUP($A10,'Doanh thu'!$A$3:$Q$2000,16,FALSE) -> #N/A | O10: =VLOOKUP($A10,'Doanh thu'!$A$3:$Q$2000,17,FALSE) -> #N/A | P10: =VLOOKUP($A10,LNST!$A$3:$R$1635,14,FALSE) -> #N/A | Q10: =VLOOKUP($A10,LNST!$A$3:$R$1635,15,FALSE) -> #N/A | R10: =VLOOKUP($A10,LNST!$A$3:$R$1635,16,FALSE) -> #N/A | S10: =VLOOKUP($A10,LNST!$A$3:$R$1635,17,FALSE) -> #N/A | T10: =VLOOKUP($A10,LNG!$A$2:$H$1999,4,FALSE)/(D10*10^9) -> #N/A | U10: =VLOOKUP($A10,LNG!$A$2:$H$1999,5,FALSE)/(E10*10^9) -> #N/A | V10: =VLOOKUP($A10,LNG!$A$2:$H$1999,6,FALSE)/(F10*10^9) -> #N/A | W10: =VLOOKUP($A10,LNG!$A$2:$H$1999,7,FALSE)/(G10*10^9) -> #N/A | X10: =VLOOKUP($A10,'LNST năm'!$A$2:$I$2000,8,FALSE) -> #N/A | Y10: =VLOOKUP($A10,'LNST năm'!$A$2:$I$2000,9,FALSE) -> #N/A | Z10: =VLOOKUP($A10,LNG!$A$2:$H$1999,9,FALSE) -> #N/A | AA10: =VLOOKUP($A10,'GIÁ CP'!$A$2:$D$2000,4,FALSE)/Z10 -> #N/A
A11: CKA | B11: Cơ khí An Giang | C11: =VLOOKUP(A11,'GIÁ CP'!$K$2:$M$2000,3,FALSE) -> Máy công nghiệp | D11: =VLOOKUP($A11,'Doanh thu'!$A$3:$Q$2000,9,FALSE)/1000000000 -> 0 | E11: =VLOOKUP($A11,'Doanh thu'!$A$3:$Q$2000,10,FALSE)/1000000000 -> 0 | F11: =VLOOKUP($A11,'Doanh thu'!$A$3:$Q$2000,11,FALSE)/1000000000 -> 0 | G11: =VLOOKUP($A11,'Doanh thu'!$A$3:$Q$2000,12,FALSE)/1000000000 -> 0 | H11: =VLOOKUP($A11,LNST!$A$3:$Q$1635,9,FALSE)/1000000000 -> 0 | I11: =VLOOKUP($A11,LNST!$A$3:$Q$1635,10,FALSE)/1000000000 -> 0 | J11: =VLOOKUP($A11,LNST!$A$3:$Q$1635,11,FALSE)/1000000000 -> 0 | K11: =VLOOKUP($A11,LNST!$A$3:$Q$1635,12,FALSE)/1000000000 -> 0 | L11: =VLOOKUP($A11,'Doanh thu'!$A$3:$Q$2000,14,FALSE) -> #DIV/0! | M11: =VLOOKUP($A11,'Doanh thu'!$A$3:$Q$2000,15,FALSE) -> #DIV/0! | N11: =VLOOKUP($A11,'Doanh thu'!$A$3:$Q$2000,16,FALSE) -> #DIV/0! | O11: =VLOOKUP($A11,'Doanh thu'!$A$3:$Q$2000,17,FALSE) -> #DIV/0! | P11: =VLOOKUP($A11,LNST!$A$3:$R$1635,14,FALSE) -> #DIV/0! | Q11: =VLOOKUP($A11,LNST!$A$3:$R$1635,15,FALSE) -> #DIV/0! | R11: =VLOOKUP($A11,LNST!$A$3:$R$1635,16,FALSE) -> #DIV/0! | S11: =VLOOKUP($A11,LNST!$A$3:$R$1635,17,FALSE) -> #DIV/0! | T11: =VLOOKUP($A11,LNG!$A$2:$H$1999,4,FALSE)/(D11*10^9) -> #DIV/0! | U11: =VLOOKUP($A11,LNG!$A$2:$H$1999,5,FALSE)/(E11*10^9) -> #DIV/0! | V11: =VLOOKUP($A11,LNG!$A$2:$H$1999,6,FALSE)/(F11*10^9) -> #DIV/0! | W11: =VLOOKUP($A11,LNG!$A$2:$H$1999,7,FALSE)/(G11*10^9) -> #DIV/0! | X11: =VLOOKUP($A11,'LNST năm'!$A$2:$I$2000,8,FALSE) -> -1 | Y11: =VLOOKUP($A11,'LNST năm'!$A$2:$I$2000,9,FALSE) -> -1 | Z11: =VLOOKUP($A11,LNG!$A$2:$H$1999,9,FALSE) -> #REF! | AA11: =VLOOKUP($A11,'GIÁ CP'!$A$2:$D$2000,4,FALSE)/Z11 -> #REF!
A12: AGX | B12: Nông sản Xuất khẩu Sài Gòn | C12: =VLOOKUP(A12,'GIÁ CP'!$K$2:$M$2000,3,FALSE) -> Phân phối thực phẩm | D12: =VLOOKUP($A12,'Doanh thu'!$A$3:$Q$2000,9,FALSE)/1000000000 -> 0 | E12: =VLOOKUP($A12,'Doanh thu'!$A$3:$Q$2000,10,FALSE)/1000000000 -> 0 | F12: =VLOOKUP($A12,'Doanh thu'!$A$3:$Q$2000,11,FALSE)/1000000000 -> 0 | G12: =VLOOKUP($A12,'Doanh thu'!$A$3:$Q$2000,12,FALSE)/1000000000 -> 0 | H12: =VLOOKUP($A12,LNST!$A$3:$Q$1635,9,FALSE)/1000000000 -> 0 | I12: =VLOOKUP($A12,LNST!$A$3:$Q$1635,10,FALSE)/1000000000 -> 0 | J12: =VLOOKUP($A12,LNST!$A$3:$Q$1635,11,FALSE)/1000000000 -> 0 | K12: =VLOOKUP($A12,LNST!$A$3:$Q$1635,12,FALSE)/1000000000 -> 0 | L12: =VLOOKUP($A12,'Doanh thu'!$A$3:$Q$2000,14,FALSE) -> #DIV/0! | M12: =VLOOKUP($A12,'Doanh thu'!$A$3:$Q$2000,15,FALSE) -> #DIV/0! | N12: =VLOOKUP($A12,'Doanh thu'!$A$3:$Q$2000,16,FALSE) -> #DIV/0! | O12: =VLOOKUP($A12,'Doanh thu'!$A$3:$Q$2000,17,FALSE) -> #DIV/0! | P12: =VLOOKUP($A12,LNST!$A$3:$R$1635,14,FALSE) -> #DIV/0! | Q12: =VLOOKUP($A12,LNST!$A$3:$R$1635,15,FALSE) -> #DIV/0! | R12: =VLOOKUP($A12,LNST!$A$3:$R$1635,16,FALSE) -> #DIV/0! | S12: =VLOOKUP($A12,LNST!$A$3:$R$1635,17,FALSE) -> #DIV/0! | T12: =VLOOKUP($A12,LNG!$A$2:$H$1999,4,FALSE)/(D12*10^9) -> #DIV/0! | U12: =VLOOKUP($A12,LNG!$A$2:$H$1999,5,FALSE)/(E12*10^9) -> #DIV/0! | V12: =VLOOKUP($A12,LNG!$A$2:$H$1999,6,FALSE)/(F12*10^9) -> #DIV/0! | W12: =VLOOKUP($A12,LNG!$A$2:$H$1999,7,FALSE)/(G12*10^9) -> #DIV/0! | X12: =VLOOKUP($A12,'LNST năm'!$A$2:$I$2000,8,FALSE) -> -1 | Y12: =VLOOKUP($A12,'LNST năm'!$A$2:$I$2000,9,FALSE) -> -1 | Z12: =VLOOKUP($A12,LNG!$A$2:$H$1999,9,FALSE) -> #REF! | AA12: =VLOOKUP($A12,'GIÁ CP'!$A$2:$D$2000,4,FALSE)/Z12 -> #REF!
A13: CAF | B13: AGRIMEXCO CAMAU | C13: =VLOOKUP(A13,'GIÁ CP'!$K$2:$M$2000,3,FALSE) -> Nuôi trồng nông & hải sản | D13: =VLOOKUP($A13,'Doanh thu'!$A$3:$Q$2000,9,FALSE)/1000000000 -> 0 | E13: =VLOOKUP($A13,'Doanh thu'!$A$3:$Q$2000,10,FALSE)/1000000000 -> 0 | F13: =VLOOKUP($A13,'Doanh thu'!$A$3:$Q$2000,11,FALSE)/1000000000 -> 0 | G13: =VLOOKUP($A13,'Doanh thu'!$A$3:$Q$2000,12,FALSE)/1000000000 -> 0 | H13: =VLOOKUP($A13,LNST!$A$3:$Q$1635,9,FALSE)/1000000000 -> 0 | I13: =VLOOKUP($A13,LNST!$A$3:$Q$1635,10,FALSE)/1000000000 -> 0 | J13: =VLOOKUP($A13,LNST!$A$3:$Q$1635,11,FALSE)/1000000000 -> 0 | K13: =VLOOKUP($A13,LNST!$A$3:$Q$1635,12,FALSE)/1000000000 -> 0 | L13: =VLOOKUP($A13,'Doanh thu'!$A$3:$Q$2000,14,FALSE) -> #DIV/0! | M13: =VLOOKUP($A13,'Doanh thu'!$A$3:$Q$2000,15,FALSE) -> #DIV/0! | N13: =VLOOKUP($A13,'Doanh thu'!$A$3:$Q$2000,16,FALSE) -> #DIV/0! | O13: =VLOOKUP($A13,'Doanh thu'!$A$3:$Q$2000,17,FALSE) -> #DIV/0! | P13: =VLOOKUP($A13,LNST!$A$3:$R$1635,14,FALSE) -> #DIV/0! | Q13: =VLOOKUP($A13,LNST!$A$3:$R$1635,15,FALSE) -> #DIV/0! | R13: =VLOOKUP($A13,LNST!$A$3:$R$1635,16,FALSE) -> #DIV/0! | S13: =VLOOKUP($A13,LNST!$A$3:$R$1635,17,FALSE) -> #DIV/0! | T13: =VLOOKUP($A13,LNG!$A$2:$H$1999,4,FALSE)/(D13*10^9) -> #DIV/0! | U13: =VLOOKUP($A13,LNG!$A$2:$H$1999,5,FALSE)/(E13*10^9) -> #DIV/0! | V13: =VLOOKUP($A13,LNG!$A$2:$H$1999,6,FALSE)/(F13*10^9) -> #DIV/0! | W13: =VLOOKUP($A13,LNG!$A$2:$H$1999,7,FALSE)/(G13*10^9) -> #DIV/0! | X13: =VLOOKUP($A13,'LNST năm'!$A$2:$I$2000,8,FALSE) -> #DIV/0! | Y13: =VLOOKUP($A13,'LNST năm'!$A$2:$I$2000,9,FALSE) -> #DIV/0! | Z13: =VLOOKUP($A13,LNG!$A$2:$H$1999,9,FALSE) -> #REF! | AA13: =VLOOKUP($A13,'GIÁ CP'!$A$2:$D$2000,4,FALSE)/Z13 -> #N/A
A14: AG1 | B14: Công ty 28.1 | C14: =VLOOKUP(A14,'GIÁ CP'!$K$2:$M$2000,3,FALSE) -> Hàng May mặc | D14: =VLOOKUP($A14,'Doanh thu'!$A$3:$Q$2000,9,FALSE)/1000000000 -> 0 | E14: =VLOOKUP($A14,'Doanh thu'!$A$3:$Q$2000,10,FALSE)/1000000000 -> 0 | F14: =VLOOKUP($A14,'Doanh thu'!$A$3:$Q$2000,11,FALSE)/1000000000 -> 0 | G14: =VLOOKUP($A14,'Doanh thu'!$A$3:$Q$2000,12,FALSE)/1000000000 -> 0 | H14: =VLOOKUP($A14,LNST!$A$3:$Q$1635,9,FALSE)/1000000000 -> 0 | I14: =VLOOKUP($A14,LNST!$A$3:$Q$1635,10,FALSE)/1000000000 -> 0 | J14: =VLOOKUP($A14,LNST!$A$3:$Q$1635,11,FALSE)/1000000000 -> 0 | K14: =VLOOKUP($A14,LNST!$A$3:$Q$1635,12,FALSE)/1000000000 -> 0 | L14: =VLOOKUP($A14,'Doanh thu'!$A$3:$Q$2000,14,FALSE) -> #DIV/0! | M14: =VLOOKUP($A14,'Doanh thu'!$A$3:$Q$2000,15,FALSE) -> #DIV/0! | N14: =VLOOKUP($A14,'Doanh thu'!$A$3:$Q$2000,16,FALSE) -> #DIV/0! | O14: =VLOOKUP($A14,'Doanh thu'!$A$3:$Q$2000,17,FALSE) -> #DIV/0! | P14: =VLOOKUP($A14,LNST!$A$3:$R$1635,14,FALSE) -> #DIV/0! | Q14: =VLOOKUP($A14,LNST!$A$3:$R$1635,15,FALSE) -> #DIV/0! | R14: =VLOOKUP($A14,LNST!$A$3:$R$1635,16,FALSE) -> #DIV/0! | S14: =VLOOKUP($A14,LNST!$A$3:$R$1635,17,FALSE) -> #DIV/0! | T14: =VLOOKUP($A14,LNG!$A$2:$H$1999,4,FALSE)/(D14*10^9) -> #DIV/0! | U14: =VLOOKUP($A14,LNG!$A$2:$H$1999,5,FALSE)/(E14*10^9) -> #DIV/0! | V14: =VLOOKUP($A14,LNG!$A$2:$H$1999,6,FALSE)/(F14*10^9) -> #DIV/0! | W14: =VLOOKUP($A14,LNG!$A$2:$H$1999,7,FALSE)/(G14*10^9) -> #DIV/0! | X14: =VLOOKUP($A14,'LNST năm'!$A$2:$I$2000,8,FALSE) -> -1 | Y14: =VLOOKUP($A14,'LNST năm'!$A$2:$I$2000,9,FALSE) -> -1 | Z14: =VLOOKUP($A14,LNG!$A$2:$H$1999,9,FALSE) -> #REF! | AA14: =VLOOKUP($A14,'GIÁ CP'!$A$2:$D$2000,4,FALSE)/Z14 -> #REF!
... A978: BVB | B978: Ngân hàng Bản Việt | C978: =VLOOKUP(A978,'GIÁ CP'!$K$2:$M$2000,3,FALSE) -> Ngân hàng | D978: =VLOOKUP($A978,'Doanh thu'!$A$3:$Q$2000,9,FALSE)/1000000000 -> 0 | E978: =VLOOKUP($A978,'Doanh thu'!$A$3:$Q$2000,10,FALSE)/1000000000 -> 0 | F978: =VLOOKUP($A978,'Doanh thu'!$A$3:$Q$2000,11,FALSE)/1000000000 -> 0 | G978: =VLOOKUP($A978,'Doanh thu'!$A$3:$Q$2000,12,FALSE)/1000000000 -> 0 | H978: =VLOOKUP($A978,LNST!$A$3:$Q$1635,9,FALSE)/1000000000 -> 10.338 | I978: =VLOOKUP($A978,LNST!$A$3:$Q$1635,10,FALSE)/1000000000 -> 274.218 | J978: =VLOOKUP($A978,LNST!$A$3:$Q$1635,11,FALSE)/1000000000 -> 68.007 | K978: =VLOOKUP($A978,LNST!$A$3:$Q$1635,12,FALSE)/1000000000 -> 172.37 | L978: =VLOOKUP($A978,'Doanh thu'!$A$3:$Q$2000,14,FALSE) -> #DIV/0! | M978: =VLOOKUP($A978,'Doanh thu'!$A$3:$Q$2000,15,FALSE) -> #DIV/0! | N978: =VLOOKUP($A978,'Doanh thu'!$A$3:$Q$2000,16,FALSE) -> #DIV/0! | O978: =VLOOKUP($A978,'Doanh thu'!$A$3:$Q$2000,17,FALSE) -> #DIV/0! | P978: =VLOOKUP($A978,LNST!$A$3:$R$1635,14,FALSE) -> -0.84399004 | Q978: =VLOOKUP($A978,LNST!$A$3:$R$1635,15,FALSE) -> 10.901306 | R978: =VLOOKUP($A978,LNST!$A$3:$R$1635,16,FALSE) -> -0.59200533 | S978: =VLOOKUP($A978,LNST!$A$3:$R$1635,17,FALSE) -> 1.6887021 | T978: =VLOOKUP($A978,LNG!$A$2:$H$1999,4,FALSE)/(D978*10^9) -> #DIV/0! | U978: =VLOOKUP($A978,LNG!$A$2:$H$1999,5,FALSE)/(E978*10^9) -> #DIV/0! | V978: =VLOOKUP($A978,LNG!$A$2:$H$1999,6,FALSE)/(F978*10^9) -> #DIV/0! | W978: =VLOOKUP($A978,LNG!$A$2:$H$1999,7,FALSE)/(G978*10^9) -> #DIV/0! | X978: =VLOOKUP($A978,'LNST năm'!$A$2:$I$2000,8,FALSE) -> 0.33869662 | Y978: =VLOOKUP($A978,'LNST năm'!$A$2:$I$2000,9,FALSE) -> 0.046032607 | Z978: =VLOOKUP($A978,LNG!$A$2:$H$1999,9,FALSE) -> #REF! | AA978: =VLOOKUP($A978,'GIÁ CP'!$A$2:$D$2000,4,FALSE)/Z978 -> #REF!
A979: DHP | B979: Điện cơ Hải Phòng | C979: =VLOOKUP(A979,'GIÁ CP'!$K$2:$M$2000,3,FALSE) -> Thiết bị điện | D979: =VLOOKUP($A979,'Doanh thu'!$A$3:$Q$2000,9,FALSE)/1000000000 -> 84.267903 | E979: h | F979: =VLOOKUP($A979,'Doanh thu'!$A$3:$Q$2000,11,FALSE)/1000000000 -> 40.538927 | G979: =VLOOKUP($A979,'Doanh thu'!$A$3:$Q$2000,12,FALSE)/1000000000 -> 63.100084 | H979: =VLOOKUP($A979,LNST!$A$3:$Q$1635,9,FALSE)/1000000000 -> 4.6718612 | I979: =VLOOKUP($A979,LNST!$A$3:$Q$1635,10,FALSE)/1000000000 -> 2.7323025 | J979: =VLOOKUP($A979,LNST!$A$3:$Q$1635,11,FALSE)/1000000000 -> 2.6602073 | K979: =VLOOKUP($A979,LNST!$A$3:$Q$1635,12,FALSE)/1000000000 -> 2.8242891 | L979: =VLOOKUP($A979,'Doanh thu'!$A$3:$Q$2000,14,FALSE) -> -0.078978075 | M979: =VLOOKUP($A979,'Doanh thu'!$A$3:$Q$2000,15,FALSE) -> 0.03143347 | N979: =VLOOKUP($A979,'Doanh thu'!$A$3:$Q$2000,16,FALSE) -> 0.088739119 | O979: =VLOOKUP($A979,'Doanh thu'!$A$3:$Q$2000,17,FALSE) -> -0.0070727523 | P979: =VLOOKUP($A979,LNST!$A$3:$R$1635,14,FALSE) -> -0.044563132 | Q979: =VLOOKUP($A979,LNST!$A$3:$R$1635,15,FALSE) -> 0.04450967 | R979: =VLOOKUP($A979,LNST!$A$3:$R$1635,16,FALSE) -> 0.073134699 | S979: =VLOOKUP($A979,LNST!$A$3:$R$1635,17,FALSE) -> -0.077904159 | T979: =VLOOKUP($A979,LNG!$A$2:$H$1999,4,FALSE)/(D979*10^9) -> 0.11336746 | U979: =VLOOKUP($A979,LNG!$A$2:$H$1999,5,FALSE)/(E979*10^9) -> #VALUE! | V979: =VLOOKUP($A979,LNG!$A$2:$H$1999,6,FALSE)/(F979*10^9) -> 0.19570233 | W979: =VLOOKUP($A979,LNG!$A$2:$H$1999,7,FALSE)/(G979*10^9) -> 0.060780569 | X979: =VLOOKUP($A979,'LNST năm'!$A$2:$I$2000,8,FALSE) -> -0.017224245 | Y979: =VLOOKUP($A979,'LNST năm'!$A$2:$I$2000,9,FALSE) -> -0.022466624 | Z979: =VLOOKUP($A979,LNG!$A$2:$H$1999,9,FALSE) -> #REF! | AA979: =VLOOKUP($A979,'GIÁ CP'!$A$2:$D$2000,4,FALSE)/Z979 -> #REF!
A980: SDD | B980: Xây lắp Sông Đà | C980: =VLOOKUP(A980,'GIÁ CP'!$K$2:$M$2000,3,FALSE) -> Xây dựng | D980: =VLOOKUP($A980,'Doanh thu'!$A$3:$Q$2000,9,FALSE)/1000000000 -> 2.1282085 | E980: =VLOOKUP($A980,'Doanh thu'!$A$3:$Q$2000,10,FALSE)/1000000000 -> 4.2704695 | F980: =VLOOKUP($A980,'Doanh thu'!$A$3:$Q$2000,11,FALSE)/1000000000 -> 3.8170545 | G980: =VLOOKUP($A980,'Doanh thu'!$A$3:$Q$2000,12,FALSE)/1000000000 -> 1.5075487 | H980: =VLOOKUP($A980,LNST!$A$3:$Q$1635,9,FALSE)/1000000000 -> -2.4003673 | I980: =VLOOKUP($A980,LNST!$A$3:$Q$1635,10,FALSE)/1000000000 -> -1.2934633 | J980: =VLOOKUP($A980,LNST!$A$3:$Q$1635,11,FALSE)/1000000000 -> -3.2862584 | K980: =VLOOKUP($A980,LNST!$A$3:$Q$1635,12,FALSE)/1000000000 -> -3.6295066 | L980: =VLOOKUP($A980,'Doanh thu'!$A$3:$Q$2000,14,FALSE) -> -0.15834986 | M980: =VLOOKUP($A980,'Doanh thu'!$A$3:$Q$2000,15,FALSE) -> 0.13695818 | N980: =VLOOKUP($A980,'Doanh thu'!$A$3:$Q$2000,16,FALSE) -> -0.064791054 | O980: =VLOOKUP($A980,'Doanh thu'!$A$3:$Q$2000,17,FALSE) -> 0.3613474 | P980: =VLOOKUP($A980,LNST!$A$3:$R$1635,14,FALSE) -> 0.69829669 | Q980: =VLOOKUP($A980,LNST!$A$3:$R$1635,15,FALSE) -> 0.31063933 | R980: =VLOOKUP($A980,LNST!$A$3:$R$1635,16,FALSE) -> -0.28241538 | S980: =VLOOKUP($A980,LNST!$A$3:$R$1635,17,FALSE) -> 0.11474256 | T980: =VLOOKUP($A980,LNG!$A$2:$H$1999,4,FALSE)/(D980*10^9) -> -1.04956 | U980: =VLOOKUP($A980,LNG!$A$2:$H$1999,5,FALSE)/(E980*10^9) -> -0.29924157 | V980: =VLOOKUP($A980,LNG!$A$2:$H$1999,6,FALSE)/(F980*10^9) -> 0.23585875 | W980: =VLOOKUP($A980,LNG!$A$2:$H$1999,7,FALSE)/(G980*10^9) -> 0.25892863 | X980: =VLOOKUP($A980,'LNST năm'!$A$2:$I$2000,8,FALSE) -> 0.29919723 | Y980: =VLOOKUP($A980,'LNST năm'!$A$2:$I$2000,9,FALSE) -> -0.084091591 | Z980: =VLOOKUP($A980,LNG!$A$2:$H$1999,9,FALSE) -> #REF! | AA980: =VLOOKUP($A980,'GIÁ CP'!$A$2:$D$2000,4,FALSE)/Z980 -> #REF!
A981: PVM | B981: Thiết bị dầu khí (PV MACHINO) | C981: =VLOOKUP(A981,'GIÁ CP'!$K$2:$M$2000,3,FALSE) -> Nhà cung cấp thiết bị | D981: =VLOOKUP($A981,'Doanh thu'!$A$3:$Q$2000,9,FALSE)/1000000000 -> 510.54374 | E981: =VLOOKUP($A981,'Doanh thu'!$A$3:$Q$2000,10,FALSE)/1000000000 -> 432.4834 | F981: =VLOOKUP($A981,'Doanh thu'!$A$3:$Q$2000,11,FALSE)/1000000000 -> 553.72224 | G981: =VLOOKUP($A981,'Doanh thu'!$A$3:$Q$2000,12,FALSE)/1000000000 -> 432.7657 | H981: =VLOOKUP($A981,LNST!$A$3:$Q$1635,9,FALSE)/1000000000 -> 28.447293 | I981: =VLOOKUP($A981,LNST!$A$3:$Q$1635,10,FALSE)/1000000000 -> 2.8665252 | J981: =VLOOKUP($A981,LNST!$A$3:$Q$1635,11,FALSE)/1000000000 -> 1.2297507 | K981: =VLOOKUP($A981,LNST!$A$3:$Q$1635,12,FALSE)/1000000000 -> 0.3041551 | L981: =VLOOKUP($A981,'Doanh thu'!$A$3:$Q$2000,14,FALSE) -> 0.10972928 | M981: =VLOOKUP($A981,'Doanh thu'!$A$3:$Q$2000,15,FALSE) -> -0.1641174 | N981: =VLOOKUP($A981,'Doanh thu'!$A$3:$Q$2000,16,FALSE) -> 0.047046612 | O981: =VLOOKUP($A981,'Doanh thu'!$A$3:$Q$2000,17,FALSE) -> 0.07146982 | P981: =VLOOKUP($A981,LNST!$A$3:$R$1635,14,FALSE) -> 0.015140107 | Q981: =VLOOKUP($A981,LNST!$A$3:$R$1635,15,FALSE) -> -0.30826304 | R981: =VLOOKUP($A981,LNST!$A$3:$R$1635,16,FALSE) -> -0.90385432 | S981: =VLOOKUP($A981,LNST!$A$3:$R$1635,17,FALSE) -> -0.79196369 | T981: =VLOOKUP($A981,LNG!$A$2:$H$1999,4,FALSE)/(D981*10^9) -> 0.034912511 | U981: =VLOOKUP($A981,LNG!$A$2:$H$1999,5,FALSE)/(E981*10^9) -> 0.040458998 | V981: =VLOOKUP($A981,LNG!$A$2:$H$1999,6,FALSE)/(F981*10^9) -> 0.048855804 | W981: =VLOOKUP($A981,LNG!$A$2:$H$1999,7,FALSE)/(G981*10^9) -> 0.096471288 | X981: =VLOOKUP($A981,'LNST năm'!$A$2:$I$2000,8,FALSE) -> -1 | Y981: =VLOOKUP($A981,'LNST năm'!$A$2:$I$2000,9,FALSE) -> -1 | Z981: =VLOOKUP($A981,LNG!$A$2:$H$1999,9,FALSE) -> #REF! | AA981: =VLOOKUP($A981,'GIÁ CP'!$A$2:$D$2000,4,FALSE)/Z981 -> #REF!
A982: KLB | B982: Ngân hàng Kiên Long | C982: =VLOOKUP(A982,'GIÁ CP'!$K$2:$M$2000,3,FALSE) -> Ngân hàng | D982: =VLOOKUP($A982,'Doanh thu'!$A$3:$Q$2000,9,FALSE)/1000000000 -> 0 | E982: =VLOOKUP($A982,'Doanh thu'!$A$3:$Q$2000,10,FALSE)/1000000000 -> 0 | F982: =VLOOKUP($A982,'Doanh thu'!$A$3:$Q$2000,11,FALSE)/1000000000 -> 0 | G982: =VLOOKUP($A982,'Doanh thu'!$A$3:$Q$2000,12,FALSE)/1000000000 -> 0 | H982: =VLOOKUP($A982,LNST!$A$3:$Q$1635,9,FALSE)/1000000000 -> 451.463 | I982: =VLOOKUP($A982,LNST!$A$3:$Q$1635,10,FALSE)/1000000000 -> 491.859 | J982: =VLOOKUP($A982,LNST!$A$3:$Q$1635,11,FALSE)/1000000000 -> 628.175 | K982: =VLOOKUP($A982,LNST!$A$3:$Q$1635,12,FALSE)/1000000000 -> 416.809 | L982: =VLOOKUP($A982,'Doanh thu'!$A$3:$Q$2000,14,FALSE) -> #DIV/0! | M982: =VLOOKUP($A982,'Doanh thu'!$A$3:$Q$2000,15,FALSE) -> #DIV/0! | N982: =VLOOKUP($A982,'Doanh thu'!$A$3:$Q$2000,16,FALSE) -> #DIV/0! | O982: =VLOOKUP($A982,'Doanh thu'!$A$3:$Q$2000,17,FALSE) -> #DIV/0! | P982: =VLOOKUP($A982,LNST!$A$3:$R$1635,14,FALSE) -> 0.67656845 | Q982: =VLOOKUP($A982,LNST!$A$3:$R$1635,15,FALSE) -> 1.9485121 | R982: =VLOOKUP($A982,LNST!$A$3:$R$1635,16,FALSE) -> 1.2376802 | S982: =VLOOKUP($A982,LNST!$A$3:$R$1635,17,FALSE) -> 0.46412651 | T982: =VLOOKUP($A982,LNG!$A$2:$H$1999,4,FALSE)/(D982*10^9) -> #DIV/0! | U982: =VLOOKUP($A982,LNG!$A$2:$H$1999,5,FALSE)/(E982*10^9) -> #DIV/0! | V982: =VLOOKUP($A982,LNG!$A$2:$H$1999,6,FALSE)/(F982*10^9) -> #DIV/0! | W982: =VLOOKUP($A982,LNG!$A$2:$H$1999,7,FALSE)/(G982*10^9) -> #DIV/0! | X982: =VLOOKUP($A982,'LNST năm'!$A$2:$I$2000,8,FALSE) -> 1.0914823 | Y982: =VLOOKUP($A982,'LNST năm'!$A$2:$I$2000,9,FALSE) -> 0.50499479 | Z982: =VLOOKUP($A982,LNG!$A$2:$H$1999,9,FALSE) -> #REF! | AA982: =VLOOKUP($A982,'GIÁ CP'!$A$2:$D$2000,4,FALSE)/Z982 -> #REF!
A983: DMC | B983: Dược phẩm DOMESCO | C983: =VLOOKUP(A983,'GIÁ CP'!$K$2:$M$2000,3,FALSE) -> Dược phẩm | D983: =VLOOKUP($A983,'Doanh thu'!$A$3:$Q$2000,9,FALSE)/1000000000 -> 510.28806 | E983: =VLOOKUP($A983,'Doanh thu'!$A$3:$Q$2000,10,FALSE)/1000000000 -> 528.89614 | F983: =VLOOKUP($A983,'Doanh thu'!$A$3:$Q$2000,11,FALSE)/1000000000 -> 559.00399 | G983: =VLOOKUP($A983,'Doanh thu'!$A$3:$Q$2000,12,FALSE)/1000000000 -> 519.59035 | H983: =VLOOKUP($A983,LNST!$A$3:$Q$1635,9,FALSE)/1000000000 -> 31.712946 | I983: =VLOOKUP($A983,LNST!$A$3:$Q$1635,10,FALSE)/1000000000 -> 27.912217 | J983: =VLOOKUP($A983,LNST!$A$3:$Q$1635,11,FALSE)/1000000000 -> 91.377546 | K983: =VLOOKUP($A983,LNST!$A$3:$Q$1635,12,FALSE)/1000000000 -> 52.928702 | L983: =VLOOKUP($A983,'Doanh thu'!$A$3:$Q$2000,14,FALSE) -> 0.10532152 | M983: =VLOOKUP($A983,'Doanh thu'!$A$3:$Q$2000,15,FALSE) -> 0.18036977 | N983: =VLOOKUP($A983,'Doanh thu'!$A$3:$Q$2000,16,FALSE) -> -0.020164918 | O983: =VLOOKUP($A983,'Doanh thu'!$A$3:$Q$2000,17,FALSE) -> 0.10756338 | P983: =VLOOKUP($A983,LNST!$A$3:$R$1635,14,FALSE) -> -0.39111713 | Q983: =VLOOKUP($A983,LNST!$A$3:$R$1635,15,FALSE) -> -0.14852048 | R983: =VLOOKUP($A983,LNST!$A$3:$R$1635,16,FALSE) -> 0.18855084 | S983: =VLOOKUP($A983,LNST!$A$3:$R$1635,17,FALSE) -> 0.12544631 | T983: =VLOOKUP($A983,LNG!$A$2:$H$1999,4,FALSE)/(D983*10^9) -> 0.18830183 | U983: =VLOOKUP($A983,LNG!$A$2:$H$1999,5,FALSE)/(E983*10^9) -> 0.1609637 | V983: =VLOOKUP($A983,LNG!$A$2:$H$1999,6,FALSE)/(F983*10^9) -> 0.12953463 | W983: =VLOOKUP($A983,LNG!$A$2:$H$1999,7,FALSE)/(G983*10^9) -> 0.29886223 | X983: =VLOOKUP($A983,'LNST năm'!$A$2:$I$2000,8,FALSE) -> -0.023062245 | Y983: =VLOOKUP($A983,'LNST năm'!$A$2:$I$2000,9,FALSE) -> -0.0034171588 | Z983: =VLOOKUP($A983,LNG!$A$2:$H$1999,9,FALSE) -> #REF! | AA983: =VLOOKUP($A983,'GIÁ CP'!$A$2:$D$2000,4,FALSE)/Z983 -> #REF!
A984: NHA | B984: PT Nhà và Đô thị Nam HN | C984: =VLOOKUP(A984,'GIÁ CP'!$K$2:$M$2000,3,FALSE) -> Xây dựng | D984: =VLOOKUP($A984,'Doanh thu'!$A$3:$Q$2000,9,FALSE)/1000000000 -> 75.371413 | E984: =VLOOKUP($A984,'Doanh thu'!$A$3:$Q$2000,10,FALSE)/1000000000 -> 97.292349 | F984: =VLOOKUP($A984,'Doanh thu'!$A$3:$Q$2000,11,FALSE)/1000000000 -> 25.534367 | G984: =VLOOKUP($A984,'Doanh thu'!$A$3:$Q$2000,12,FALSE)/1000000000 -> 14.342264 | H984: =VLOOKUP($A984,LNST!$A$3:$Q$1635,9,FALSE)/1000000000 -> 14.729944 | I984: =VLOOKUP($A984,LNST!$A$3:$Q$1635,10,FALSE)/1000000000 -> 28.087371 | J984: =VLOOKUP($A984,LNST!$A$3:$Q$1635,11,FALSE)/1000000000 -> 2.0336748 | K984: =VLOOKUP($A984,LNST!$A$3:$Q$1635,12,FALSE)/1000000000 -> 0.69608971 | L984: =VLOOKUP($A984,'Doanh thu'!$A$3:$Q$2000,14,FALSE) -> 0.23990275 | M984: =VLOOKUP($A984,'Doanh thu'!$A$3:$Q$2000,15,FALSE) -> 2.9423317 | N984: =VLOOKUP($A984,'Doanh thu'!$A$3:$Q$2000,16,FALSE) -> -0.36933723 | O984: =VLOOKUP($A984,'Doanh thu'!$A$3:$Q$2000,17,FALSE) -> -0.85151371 | P984: =VLOOKUP($A984,LNST!$A$3:$R$1635,14,FALSE) -> -0.49800123 | Q984: =VLOOKUP($A984,LNST!$A$3:$R$1635,15,FALSE) -> 1.3670012 | R984: =VLOOKUP($A984,LNST!$A$3:$R$1635,16,FALSE) -> -0.79650496 | S984: =VLOOKUP($A984,LNST!$A$3:$R$1635,17,FALSE) -> -0.97958029 | T984: =VLOOKUP($A984,LNG!$A$2:$H$1999,4,FALSE)/(D984*10^9) -> 0.60049899 | U984: =VLOOKUP($A984,LNG!$A$2:$H$1999,5,FALSE)/(E984*10^9) -> 0.2311932 | V984: =VLOOKUP($A984,LNG!$A$2:$H$1999,6,FALSE)/(F984*10^9) -> 1.5077182 | W984: =VLOOKUP($A984,LNG!$A$2:$H$1999,7,FALSE)/(G984*10^9) -> 0.67562486 | X984: =VLOOKUP($A984,'LNST năm'!$A$2:$I$2000,8,FALSE) -> 0.25319801 | Y984: =VLOOKUP($A984,'LNST năm'!$A$2:$I$2000,9,FALSE) -> 2.4806633 | Z984: =VLOOKUP($A984,LNG!$A$2:$H$1999,9,FALSE) -> #REF! | AA984: =VLOOKUP($A984,'GIÁ CP'!$A$2:$D$2000,4,FALSE)/Z984 -> #REF!
